Workbook

Sheet Read_Me
A1: Car and Home Insurance Toolkit (Excel edition)
A2: Version 5.0 (September 29, 2026) · A learning-grade model, not a quote and not advice. Confirm anything you act on with a licensed agent and your state insurance department.
A4: What this workbook is
A5: The data, formulas and checklists behind the web tool, in one place. The two calculators are live: change the blue cells and the estimate, range and percentile recalculate. The quote sheets score themselves once real prices are entered.
A7: Colour legend
A8: Blue text on yellow | B8: Input: edit these
A9: Blue text | B9: Hardcoded data or assumption (change on the data sheets)
A10: Black text | B10: Formula
A11: Green text | B11: Formula that reads another sheet
A13: Sheet guide
A14: Sheet | B14: What it does
A15: Car_Calculator | B15: Live car price check with steps, range, percentile, and your state's legal minimum
A16: Home_Calculator | B16: Live home price check plus rebuild-cost check, storm deductibles, roof exposure and a 12-situation stress test
A17: Car_Data / Home_Data | B17: State tables (51 places plus a national row) and every factor, each marked sourced or assumed
A18: OK_Official_Data | B18: 1,800 real insurer prices from the Oklahoma Insurance Department
A19: OK_Benchmark | B19: Model vs. the median insurer for 11 profiles, plus how much insurers differ (live formulas)
A20: Validation | B20: Before/after and other independent checks
A21: Quote_Requests / Quote_Test | B21: 180 standardized home profiles (TX, FL, CA). Enter real quotes; the sheets score the model
A22: Fairness_Screen / Monitoring | B22: Templates: adverse impact ratios and month-by-month alerts (example rows to replace)
A23: Fairness_Rules_Audit / Controls_Register | B23: What changes the price and the 12-item governance controls with honest status
A24: Min_Liability / Home_Reference | B24: Legal minimums and home insurance facts
A25: Consultancy_Benchmark | B25: What ten consultancies point to and what was built
A26: Checklists / Quote_Kit / Limits_Next_Steps / Sources | B26: How to test, how to collect quotes, what is not done, and where every number came from
A28: The five findings worth knowing
A29: 1. Insurers disagree far more than most people expect: in Oklahoma's official samples the highest insurer charged about 4.7 to 4.9 times the lowest for the same customer.
A30: 2. The first version of the model was 12% to 51% low against those official prices; testing found it and it was corrected.
A31: 3. The biggest home risks are gaps, not price: rebuild cost estimates run from $162 to $350 a square foot, storm deductibles can be thousands of dollars, and an older roof paid at depreciated value can leave most of a replacement to the owner.
A32: 4. When prices rise, many households cut coverage or let policies lapse instead of shopping. Use the ranked ways to save and the "do not cut" reminders in the web tool.
A33: 5. Regulators expect documented, tested and monitored models. The Controls_Register lists what is built and the two controls that are not.
A35: Not done
A36: No real quotes tested in Texas, Florida or California; Oklahoma's samples are partly in-sample.
A37: Home prices are the roughest number.
A38: The address lookup (in the web tool) has passed offline tests only.
A39: Tested in Chromium only (no Safari, Firefox, real-phone or screen-reader test); no legal review.

Sheet Car_Calculator
A1: Car insurance price check (live calculator)
A2: Change the blue cells. The estimate, range and percentile update. A learning model, not a quote.
A4: Your details (edit the blue cells) | E4: Results
A5: State (two-letter code) | B5: TX | C5: dropdown list of codes | E5: Estimate ($ per year, rounded) | F5: =ROUND($B$42,-1) -> 3970
A6: Your age (16 to 99) | B6: 34 | E6: Typical range: low ($) | F6: =ROUND($B$42*EXP(-Car_Data!$B$123*Car_Data!$B$122),-1) -> 2950
A7: Years driving | B7: 16 | E7: Typical range: high ($) | F7: =ROUND($B$42*EXP(Car_Data!$B$123*Car_Data!$B$122),-1) -> 5340
A8: Accidents you caused, past 5 years (0 to 3) | B8: 0 | E8: Your price ($) | F8: =$B$21 -> 2280
A9: Tickets, past 3 years (0 to 3) | B9: 0 | E9: Verdict | F9: =IF(F8>F7,"May be overpaying",IF(F8<F6,"Below typical","Inside the typical range")) -> Below typical
A10: DUI in the past 5 years? | B10: No | C10: Yes or No | E10: Share of expected insurer prices below yours | F10: =IF(AND($B$21>0,$B$42>0),NORMSDIST(LN($B$21/$B$42)/Car_Data!$B$122),0.5) -> 0.10388009
A11: Credit rating (blank to skip) | B11: good | C11: poor, fair, good, excellent | E11: Best-case yearly saving ($) | F11: =MAX(0,F8-F6) -> 0
A12: What the car is worth ($) | B12: 31000 | E12: Published median, reference driver in your state ($) | F12: =$B$26 -> 3608
A13: Cover on your own car | B13: full | C13: full, coll, liab | E13: Legal minimum liability in your state | F13: =INDEX(Car_Data!$J$5:$J$56,$B$25) -> 30/60/25
A14: Deductible ($) | B14: 1000 | C14: 500, 1000 or 2000 | E14: Status of that minimum | F14: =INDEX(Car_Data!$K$5:$K$56,$B$25) -> Checked against an official state source
A15: Liability limits | B15: l100 | C15: min, l50, l100, unsure | E15: Uninsured-motorist rule | F15: =INDEX(Car_Data!$I$5:$I$56,$B$25) -> Must be offered; may be rejected in writing
A16: Miles per year | B16: mid | C16: low, mid, high | E16: No-fault state? (PIP and lawsuit threshold) | F16: =INDEX(Car_Data!$G$5:$G$56,$B$25)&IF(INDEX(Car_Data!$G$5:$G$56,$B$25)="Yes"," - "&INDEX(Car_Data!$H$5:$H$56,$B$25),"") -> No
A17: Use | B17: personal | C17: personal, business, commercial
A18: Flooding where you park? | B18: No | C18: Yes or No | E18: How to read this
A19: Hailstorms where you park? | B19: Yes | C19: Yes or No | E19: The range is the middle half of expected insurer prices. For the same customer, insurers differed by about 4.7x to 4.9x between the highest and lowest in Oklahoma's official samples.
A20: Car thefts where you park? | B20: No | C20: Yes or No | E20: The percentile applies that Oklahoma spread to every state, so treat it as a rough guide.
A21: What you pay per year ($) | B21: 2280 | C21: monthly price x 12 | E21: Credit is ignored where a state bans it. Gender, marital status, occupation, income and ZIP code are not used.
E22: A price below the range can mean thinner coverage. Check limits and deductibles before switching.
A24: Workings (formulas)
A25: State row | B25: =MATCH($B$5,Car_Data!$B$5:$B$56,0) -> 43
A26: Published state median ($) | B26: =INDEX(Car_Data!$C$5:$C$56,$B$25) -> 3608
A27: Liability share | B27: =INDEX(Car_Data!$B$100:$B$103,MATCH($B$15,Car_Data!$A$100:$A$103,0)) -> 0.36
A28: Own-car cover share | B28: =INDEX(Car_Data!$B$104:$B$106,MATCH($B$13,Car_Data!$A$104:$A$106,0)) -> 0.64
A29: Vehicle value factor | B29: =IF($B$28=0,1,MIN(Car_Data!$B$121,MAX(Car_Data!$B$120,(MAX($B$12,1000)/Car_Data!$B$118)^Car_Data!$B$119))) -> 1.0898549
A30: Deductible factor | B30: =IF($B$28=0,1,IF($B$14<=500,Car_Data!$B$113,IF($B$14>=2000,Car_Data!$B$114,1))) -> 1
A31: Area factor (full cover only) | B31: =IF($B$13="full",1+IF(($B$18="Yes"),Car_Data!$B$115,0)+IF(($B$19="Yes"),Car_Data!$B$116,0)+IF(($B$20="Yes"),Car_Data!$B$117,0),1) -> 1.03
A32: Cover factor (liability + own-car) | B32: =$B$27+$B$28*$B$29*$B$30*$B$31 -> 1.0784323
A33: Age table position | B33: =IFERROR(MATCH($B$6,Car_Data!$A$61:$A$74,1),1) -> 5
A34: Age multiple | B34: =IF($B$33>=ROWS(Car_Data!$A$61:$A$74),INDEX(Car_Data!$B$61:$B$74,ROWS(Car_Data!$A$61:$A$74)),INDEX(Car_Data!$B$61:$B$74,$B$33)+(INDEX(Car_Data!$B$61:$B$74,$B$33+1)-INDEX(Car_Data!$B$61:$B$74,$B$33))*($B$6-INDEX(Car_Data!$A$61:$A$74,$B$33))/(INDEX(Car_Data!$A$61:$A$74,$B$33+1)-INDEX(Car_Data!$A$61:$A$74,$B$33))) -> 1.02
A35: Inexperience multiple | B35: =IF($B$7<2,Car_Data!$B$95,1) -> 1
A36: Accident multiple | B36: =INDEX(Car_Data!$B$79:$B$82,MIN(3,MAX(0,$B$8))+1) -> 1
A37: Ticket multiple | B37: =INDEX(Car_Data!$B$83:$B$86,MIN(3,MAX(0,$B$9))+1) -> 1
A38: DUI multiple | B38: =IF(($B$10="Yes"),Car_Data!$B$87,1) -> 1
A39: Mileage multiple | B39: =IF($B$16="high",Car_Data!$B$92,1) -> 1
A40: Use multiple | B40: =IF($B$17="commercial",Car_Data!$B$94,IF($B$17="business",Car_Data!$B$93,1)) -> 1
A41: Credit multiple (1.00 where banned) | B41: =IF(INDEX(Car_Data!$E$5:$E$56,$B$25)="Yes",1,IF($B$11="poor",Car_Data!$B$88,IF($B$11="fair",Car_Data!$B$89,IF($B$11="excellent",Car_Data!$B$91,Car_Data!$B$90)))) -> 1
A42: Estimate before rounding ($) | B42: =$B$26*$B$32*$B$34*$B$35*$B$36*$B$37*$B$38*$B$39*$B$40*$B$41 -> 3968.8036

Sheet Home_Calculator
A1: Home insurance price and coverage check (live calculator)
A2: Change the blue cells. Price, rebuild-cost check, storm deductibles, roof exposure and a stress test update. A learning model, not a quote.
A4: Your home and policy (edit the blue cells) | E4: Results
A5: State (two-letter code) | B5: FL | E5: Estimate ($ per year, rounded) | F5: =ROUND($B$54,-1) -> 11300
A6: Size (square feet) | B6: 2100 | E6: Typical range: low ($) | F6: =ROUND($B$54*EXP(-Car_Data!$B$123*Home_Data!$B$91),-1) -> 8230
A7: Year built | B7: 1998 | E7: Typical range: high ($) | F7: =ROUND($B$54*EXP(Car_Data!$B$123*Home_Data!$B$91),-1) -> 15520
A8: Roof age (years) | B8: 17 | E8: Your price ($) | F8: =$B$32 -> 3900
A9: Built with | B9: frame | C9: frame or brick | E9: Verdict | F9: =IF(F8>F7,"May be above typical",IF(F8<F6,"Below typical","Inside the typical range")) -> Below typical
A10: How the home is used | B10: own | C10: own, rental, vacation | E10: Share of expected insurer prices below yours | F10: =IF(AND($B$32>0,$B$54>0),NORMSDIST(LN($B$32/$B$54)/Home_Data!$B$91),0.5) -> 0.011778884
A11: Credit rating (blank to skip) | B11: good | C11: poor, fair, good, excellent | E11: Best-case yearly saving ($) | F11: =MAX(0,F8-F6) -> 0
A12: Claims, past 5 years (0 to 3) | B12: 0 | E12: Published state average at $300,000 ($) | F12: =INDEX(Home_Data!$D$5:$D$56,$B$37) -> 8471
A13: House coverage limit ($) | B13: 350000 | C13: Dwelling / Coverage A
A14: Standard deductible ($) | B14: 2500
A15: Personal liability ($000: 100, 300 or 500) | B15: 300 | E15: Is your house cover enough to rebuild?
A16: Hurricane area? | B16: Yes | C16: Yes or No | E16: Estimate | F16: Rebuild cost ($) | G16: Your limit as a share | H16: Shortfall ($)
A17: Wildfire area? | B17: No | C17: Yes or No | E17: Low | F17: =$B$6*Home_Data!$B$95 -> 340200 | G17: =IF(F17>0,$B$13/F17,0) -> 1.0288066 | H17: =MAX(0,F17-$B$13) -> 0
A18: Hail or tornado area? | B18: No | C18: Yes or No | E18: Midpoint | F18: =$B$6*Home_Data!$B$96 -> 588000 | G18: =IF(F18>0,$B$13/F18,0) -> 0.5952381 | H18: =MAX(0,F18-$B$13) -> 238000
A19: In or near a flood zone? | B19: Yes | C19: Yes or No | E19: High | F19: =$B$6*Home_Data!$B$97 -> 735000 | G19: =IF(F19>0,$B$13/F19,0) -> 0.47619048 | H19: =MAX(0,F19-$B$13) -> 385000
A20: Earthquake area? | B20: No | C20: Yes or No | E20: Verdict | F20: =IF($B$13<=0,"Enter a limit",IF($B$13>=F18,"Meets the midpoint estimate",IF($B$13>=0.8*F18,"Close, but below the midpoint",IF($B$13>=F17,"May be short (under 80% of midpoint)","Below even the lowest estimate")))) -> May be short (under 80% of midpoint)
A21: Hurricane deductible (% of house limit; 0 = none) | B21: 0.02 | C21: e.g. 2%
A22: Wind or hail deductible (% of limit; 0 = same as standard) | B22: 0 | E22: Storm deductibles
A23: Roof material | B23: asphalt | C23: asphalt, tile, metal, other | E23: Deductible | F23: Amount you pay first ($) | G23: Note
A24: How the roof is paid | B24: unsure | C24: rcv, acv, sched, unsure | E24: Standard | F24: =$B$14 -> 2500 | G24: fire, theft, water
A25: Roof replacement cost ($) | B25: 20000 | C25: Get a local roofer's quote | E25: Wind or hail | F25: =IF($B$22>0,$B$13*$B$22,$F$24) -> 2500 | G25: percentage of the house limit if set
A26: Extended replacement cost? | B26: No | C26: Yes or No | E26: Hurricane or named storm | F26: =IF($B$21>0,$B$13*$B$21,$F$24) -> 7000 | G26: percentage of the house limit if set
A27: Ordinance or law (code upgrades)? | B27: No | C27: Yes or No | E27: Average wind or hail claim pays | F27: =MAX(0,Home_Data!$B$104-$F$25) -> 11011 | G27: average claim minus the wind deductible
A28: Water backup cover? | B28: No | C28: Yes or No
A29: Separate flood policy? | B29: No | C29: Yes or No | E29: Your roof after a storm
A30: Earthquake cover? | B30: No | C30: Yes or No | E30: Depreciation (straight line over roof life) | F30: =MIN(Home_Data!$B$122,$B$8/IF($B$23="tile",Home_Data!$B$110,IF($B$23="metal",Home_Data!$B$111,IF($B$23="other",Home_Data!$B$112,Home_Data!$B$109)))) -> 0.85
A31: Umbrella policy? | B31: No | C31: Yes or No | E31: If a storm damages the roof | F31: You collect ($) | G31: You pay ($)
A32: What you pay per year ($) | B32: 3900 | E32: Paid at replacement cost | F32: =MAX(0,$B$25-$F$25) -> 17500 | G32: =$B$25-F32 -> 2500
E33: Paid at actual cash value | F33: =MAX(0,$B$25*(1-$F$30)-$F$25) -> 500 | G33: =$B$25-F33 -> 19500
E35: Policy stress test: what would you actually pay?
A36: Price workings (formulas) | E36: Situation | F36: Loss ($) | G36: You collect ($) | H36: You pay ($) | I36: Loss basis
A37: State row | B37: =MATCH($B$5,Home_Data!$B$5:$B$56,0) -> 9 | E37: Typical fire claim | F37: =Home_Data!$B$101 -> 83991 | G37: =MAX(0,F37-$B$14) -> 81491 | H37: =F37-G37 -> 2500 | I37: Average claim (IBHS/III)
A38: Limit used for the curve ($) | B38: =MIN(MAX($B$13,50000),3000000) -> 350000 | E38: House destroyed (rebuild at the midpoint estimate plus code upgrades) | F38: =F18*(1+Home_Data!$B$113) -> 646800 | G38: =MAX(0,MIN($B$13+IF($B$26="Yes",Home_Data!$B$114*$B$13,0)+IF($B$27="Yes",Home_Data!$B$115*$B$13,0),F38-$B$14)) -> 350000 | H38: =F38-G38 -> 296800 | I38: Midpoint estimate + assumed code upgrades
A39: Curve segment | B39: =IFERROR(MIN(3,MAX(1,MATCH($B$38,Home_Data!$C$4:$F$4,1))),1) -> 2 | E39: Typical wind or hail claim | F39: =Home_Data!$B$104 -> 13511 | G39: =MAX(0,F39-$F$25) -> 11011 | H39: =F39-G39 -> 2500 | I39: Average claim
A40: State price at segment start ($) | B40: =INDEX(Home_Data!$C$5:$F$56,$B$37,$B$39) -> 8471 | E40: Hurricane damage (illustrative) | F40: =Home_Data!$B$116 -> 40000 | G40: =MAX(0,F40-$F$26) -> 33000 | H40: =F40-G40 -> 7000 | I40: Illustrative; applies only in hurricane areas
A41: State price at segment end ($) | B41: =INDEX(Home_Data!$C$5:$F$56,$B$37,$B$39+1) -> 11161 | E41: Roof replaced after a storm | F41: =$B$25 -> 20000 | G41: =IF($B$24="rcv",F32,F33) -> 500 | H41: =F41-G41 -> 19500 | I41: Your roof cost; unsure or schedule treated as actual cash value
A42: Segment start limit ($) | B42: =INDEX(Home_Data!$C$4:$F$4,$B$39) -> 300000 | E42: Burst pipe or other water damage | F42: =Home_Data!$B$103 -> 13954 | G42: =MAX(0,F42-$B$14) -> 11454 | H42: =F42-G42 -> 2500 | I42: Average claim
A43: Segment end limit ($) | B43: =INDEX(Home_Data!$C$4:$F$4,$B$39+1) -> 400000 | E43: Sewer or drain backup (illustrative) | F43: =Home_Data!$B$117 -> 10000 | G43: =IF($B$28="Yes",MAX(0,F43-$B$14),0) -> 0 | H43: =F43-G43 -> 10000 | I43: Usually excluded without a water-backup endorsement
A44: State price at your house limit ($) | B44: =IF($B$13<200000,INDEX(Home_Data!$C$5:$F$56,$B$37,1)*(MAX($B$13,Home_Data!$B$90)/200000)^Home_Data!$B$89,$B$40*($B$38/$B$42)^(LN($B$41/$B$40)/LN($B$43/$B$42))) -> 9819.9896 | E44: Theft | F44: =Home_Data!$B$105 -> 5024 | G44: =MAX(0,F44-$B$14) -> 2524 | H44: =F44-G44 -> 2500 | I44: Average claim; special limits can cap jewelry and firearms
A45: Liability factor | B45: =IF($B$15=100,Home_Data!$B$67,IF($B$15=500,Home_Data!$B$69,Home_Data!$B$68)) -> 1 | E45: Injury lawsuit at the average size | F45: =Home_Data!$B$102 -> 31690 | G45: =MIN(F45,$B$15*1000) -> 31690 | H45: =F45-G45 -> 0 | I45: Average claim
A46: Deductible factor | B46: =IF($B$14<=Home_Data!$B$61,Home_Data!$B$64,IF($B$14>=Home_Data!$B$63,Home_Data!$B$66,IF($B$14<=Home_Data!$B$62,Home_Data!$B$64+(Home_Data!$B$65-Home_Data!$B$64)*(LN($B$14)-LN(Home_Data!$B$61))/(LN(Home_Data!$B$62)-LN(Home_Data!$B$61)),Home_Data!$B$65+(Home_Data!$B$66-Home_Data!$B$65)*(LN($B$14)-LN(Home_Data!$B$62))/(LN(Home_Data!$B$63)-LN(Home_Data!$B$62))))) -> 0.91 | E46: Large injury lawsuit (illustrative) | F46: =Home_Data!$B$118 -> 500000 | G46: =MIN(F46,$B$15*1000+IF($B$31="Yes",Home_Data!$B$119,0)) -> 300000 | H46: =F46-G46 -> 200000 | I46: Illustrative; umbrella assumed at $1 million
A47: Roof multiple | B47: =IF($B$8>=20,Home_Data!$B$80,IF($B$8>=10,Home_Data!$B$79,1)) -> 1.1 | E47: House flooded (illustrative) | F47: =Home_Data!$B$120 -> 50000 | G47: =IF($B$29="Yes",F47,0) -> 0 | H47: =F47-G47 -> 50000 | I47: Standard policies exclude flood
A48: House-age multiple | B48: =IF($B$7<1960,Home_Data!$B$81,IF($B$7<1980,Home_Data!$B$82,IF($B$7>=2000,Home_Data!$B$83,1))) -> 1 | E48: Earthquake damage (illustrative) | F48: =Home_Data!$B$121 -> 50000 | G48: =IF($B$30="Yes",F48,0) -> 0 | H48: =F48-G48 -> 50000 | I48: Standard policies exclude earthquake; applies only in earthquake areas
A49: Construction multiple | B49: =IF($B$9="brick",Home_Data!$B$78,1) -> 1 | E49: Largest amount you would pay | H49: =MAX(H37:H48) -> 296800
A50: Use multiple | B50: =IF($B$10="rental",Home_Data!$B$84,IF($B$10="vacation",Home_Data!$B$85,1)) -> 1 | E50: Situation with the largest amount you pay | F50: =INDEX(E37:E48,MATCH(H49,H37:H48,0)) -> House destroyed (rebuild at the midpoint estimate plus code upgrades)
A51: Claims multiple | B51: =INDEX(Home_Data!$B$70:$B$73,MIN(3,MAX(0,$B$12))+1) -> 1
A52: Credit multiple (1.00 where banned) | B52: =IF(INDEX(Home_Data!$H$5:$H$56,$B$37)="Yes",1,IF($B$11="poor",Home_Data!$B$74,IF($B$11="fair",Home_Data!$B$75,IF($B$11="excellent",Home_Data!$B$77,Home_Data!$B$76)))) -> 1
A53: Local-hazard multiple | B53: =IF(($B$16="Yes"),Home_Data!$B$86,1)*IF(($B$17="Yes"),Home_Data!$B$87,1)*IF(($B$18="Yes"),Home_Data!$B$88,1) -> 1.15
A54: Estimate before rounding ($) | B54: =$B$44*$B$45*$B$46*$B$47*$B$48*$B$49*$B$50*$B$51*$B$52*$B$53 -> 11304.281

Sheet Quote_Requests
A1: Quote request sheets (TX, FL, CA): fill the yellow cells and the model scores itself
A2: Standardized home profiles. Ask an independent agent to price each one with 3 to 5 insurers on the same day, for the standard coverage in the Quote_Kit sheet. Copy the row once per insurer (formulas copy with it). Enter the insurer, date and annual price in the yellow cells.
A4: Standard coverage to request
A5: HO-3, owner-occupied; house cover at the listed limit at replacement cost (record the insurer's figure in the House limit column if it differs); other structures 10%, contents 50%, loss of use 20%; the listed liability and deductible; no optional endorsements; no elective discounts. Record actual property details if the insurer's data differ from the profile.
A7: Profile | B7: State | C7: Sq ft | D7: Year built | E7: Roof age | F7: Build | G7: Use | H7: Claims | I7: House limit ($) | J7: Deductible ($) | K7: Liability ($000) | L7: Credit | M7: Flood | N7: Hurricane | O7: Wildfire | P7: Hail | Q7: Quake | R7: Location guidance | S7: Insurer | T7: Quote date | U7: Annual price ($) | V7: State row | W7: Limit used for the curve ($) | X7: Curve segment | Y7: State price at segment start ($) | Z7: State price at segment end ($) | AA7: Segment start limit ($) | AB7: Segment end limit ($) | AC7: State price at your house limit ($) | AD7: Liability factor | AE7: Deductible factor | AF7: Roof multiple | AG7: House-age multiple | AH7: Construction multiple | AI7: Use multiple | AJ7: Claims multiple | AK7: Credit multiple (1.00 where banned) | AL7: Local-hazard multiple | AM7: Estimate before rounding ($) | AN7: Range low ($) | AO7: Range high ($) | AP7: Inside range? (1 = yes) | AQ7: Error vs. model
A8: TX-1001 | B8: TX | C8: 2400 | D8: 2017 | E8: 8 | F8: brick | G8: own | H8: 1 | I8: 625000 | J8: 5000 | K8: 300 | L8: good | M8: 0 | N8: 0 | O8: 0 | P8: 1 | Q8: 0 | R8: hail or tornado region | V8: =MATCH($B8,Home_Data!$B$5:$B$56,0) -> 43 | W8: =MIN(MAX($I8,50000),3000000) -> 625000 | X8: =IFERROR(MIN(3,MAX(1,MATCH(W8,Home_Data!$C$4:$F$4,1))),1) -> 3 | Y8: =INDEX(Home_Data!$C$5:$F$56,V8,X8) -> 5733 | Z8: =INDEX(Home_Data!$C$5:$F$56,V8,X8+1) -> 7858 | AA8: =INDEX(Home_Data!$C$4:$F$4,X8) -> 400000 | AB8: =INDEX(Home_Data!$C$4:$F$4,X8+1) -> 600000 | AC8: =IF($I8<200000,INDEX(Home_Data!$C$5:$F$56,V8,1)*(MAX($I8,Home_Data!$B$90)/200000)^Home_Data!$B$89,Y8*(W8/AA8)^(LN(Z8/Y8)/LN(AB8/AA8))) -> 8111.442 | AD8: =IF($K8=100,Home_Data!$B$67,IF($K8=500,Home_Data!$B$69,Home_Data!$B$68)) -> 1 | AE8: =IF($J8<=Home_Data!$B$61,Home_Data!$B$64,IF($J8>=Home_Data!$B$63,Home_Data!$B$66,IF($J8<=Home_Data!$B$62,Home_Data!$B$64+(Home_Data!$B$65-Home_Data!$B$64)*(LN($J8)-LN(Home_Data!$B$61))/(LN(Home_Data!$B$62)-LN(Home_Data!$B$61)),Home_Data!$B$65+(Home_Data!$B$66-Home_Data!$B$65)*(LN($J8)-LN(Home_Data!$B$62))/(LN(Home_Data!$B$63)-LN(Home_Data!$B$62))))) -> 0.84 | AF8: =IF($E8>=20,Home_Data!$B$80,IF($E8>=10,Home_Data!$B$79,1)) -> 1 | AG8: =IF($D8<1960,Home_Data!$B$81,IF($D8<1980,Home_Data!$B$82,IF($D8>=2000,Home_Data!$B$83,1))) -> 0.95 | AH8: =IF($F8="brick",Home_Data!$B$78,1) -> 0.98 | AI8: =IF($G8="rental",Home_Data!$B$84,IF($G8="vacation",Home_Data!$B$85,1)) -> 1 | AJ8: =INDEX(Home_Data!$B$70:$B$73,MIN(3,MAX(0,$H8))+1) -> 1.16 | AK8: =IF(INDEX(Home_Data!$H$5:$H$56,V8)="Yes",1,IF($L8="poor",Home_Data!$B$74,IF($L8="fair",Home_Data!$B$75,IF($L8="excellent",Home_Data!$B$77,Home_Data!$B$76)))) -> 1 | AL8: =IF(($N8=1),Home_Data!$B$86,1)*IF(($O8=1),Home_Data!$B$87,1)*IF(($P8=1),Home_Data!$B$88,1) -> 1.08 | AM8: =AC8*AD8*AE8*AF8*AG8*AH8*AI8*AJ8*AK8*AL8 -> 7947.1018 | AN8: =AM8*EXP(-Car_Data!$B$123*Home_Data!$B$91) -> 5788.0597 | AO8: =AM8*EXP(Car_Data!$B$123*Home_Data!$B$91) -> 10911.502 | AP8: =IF($U8>0,IF(AND($U8>=AN8,$U8<=AO8),1,0),"") | AQ8: =IF($U8>0,$U8/AM8-1,"")
A9: TX-1002 | B9: TX | C9: 1300 | D9: 2004 | E9: 22 | F9: frame | G9: own | H9: 1 | I9: 310000 | J9: 2500 | K9: 300 | L9: excellent | M9: 0 | N9: 1 | O9: 0 | P9: 0 | Q9: 0 | R9: coastal or hurricane-exposed county | V9: =MATCH($B9,Home_Data!$B$5:$B$56,0) -> 43 | W9: =MIN(MAX($I9,50000),3000000) -> 310000 | X9: =IFERROR(MIN(3,MAX(1,MATCH(W9,Home_Data!$C$4:$F$4,1))),1) -> 2 | Y9: =INDEX(Home_Data!$C$5:$F$56,V9,X9) -> 4582 | Z9: =INDEX(Home_Data!$C$5:$F$56,V9,X9+1) -> 5733 | AA9: =INDEX(Home_Data!$C$4:$F$4,X9) -> 300000 | AB9: =INDEX(Home_Data!$C$4:$F$4,X9+1) -> 400000 | AC9: =IF($I9<200000,INDEX(Home_Data!$C$5:$F$56,V9,1)*(MAX($I9,Home_Data!$B$90)/200000)^Home_Data!$B$89,Y9*(W9/AA9)^(LN(Z9/Y9)/LN(AB9/AA9))) -> 4700.5463 | AD9: =IF($K9=100,Home_Data!$B$67,IF($K9=500,Home_Data!$B$69,Home_Data!$B$68)) -> 1 | AE9: =IF($J9<=Home_Data!$B$61,Home_Data!$B$64,IF($J9>=Home_Data!$B$63,Home_Data!$B$66,IF($J9<=Home_Data!$B$62,Home_Data!$B$64+(Home_Data!$B$65-Home_Data!$B$64)*(LN($J9)-LN(Home_Data!$B$61))/(LN(Home_Data!$B$62)-LN(Home_Data!$B$61)),Home_Data!$B$65+(Home_Data!$B$66-Home_Data!$B$65)*(LN($J9)-LN(Home_Data!$B$62))/(LN(Home_Data!$B$63)-LN(Home_Data!$B$62))))) -> 0.91 | AF9: =IF($E9>=20,Home_Data!$B$80,IF($E9>=10,Home_Data!$B$79,1)) -> 1.3 | AG9: =IF($D9<1960,Home_Data!$B$81,IF($D9<1980,Home_Data!$B$82,IF($D9>=2000,Home_Data!$B$83,1))) -> 0.95 | AH9: =IF($F9="brick",Home_Data!$B$78,1) -> 1 | AI9: =IF($G9="rental",Home_Data!$B$84,IF($G9="vacation",Home_Data!$B$85,1)) -> 1 | AJ9: =INDEX(Home_Data!$B$70:$B$73,MIN(3,MAX(0,$H9))+1) -> 1.16 | AK9: =IF(INDEX(Home_Data!$H$5:$H$56,V9)="Yes",1,IF($L9="poor",Home_Data!$B$74,IF($L9="fair",Home_Data!$B$75,IF($L9="excellent",Home_Data!$B$77,Home_Data!$B$76)))) -> 0.89 | AL9: =IF(($N9=1),Home_Data!$B$86,1)*IF(($O9=1),Home_Data!$B$87,1)*IF(($P9=1),Home_Data!$B$88,1) -> 1.15 | AM9: =AC9*AD9*AE9*AF9*AG9*AH9*AI9*AJ9*AK9*AL9 -> 6271.9491 | AN9: =AM9*EXP(-Car_Data!$B$123*Home_Data!$B$91) -> 4568.0069 | AO9: =AM9*EXP(Car_Data!$B$123*Home_Data!$B$91) -> 8611.4899 | AP9: =IF($U9>0,IF(AND($U9>=AN9,$U9<=AO9),1,0),"") | AQ9: =IF($U9>0,$U9/AM9-1,"")
A10: TX-1003 | B10: TX | C10: 3100 | D10: 2017 | E10: 0 | F10: frame | G10: own | H10: 2 | I10: 660000 | J10: 1000 | K10: 300 | L10: excellent | M10: 0 | N10: 0 | O10: 0 | P10: 0 | Q10: 0 | R10: inland, no special hazard | V10: =MATCH($B10,Home_Data!$B$5:$B$56,0) -> 43 | W10: =MIN(MAX($I10,50000),3000000) -> 660000 | X10: =IFERROR(MIN(3,MAX(1,MATCH(W10,Home_Data!$C$4:$F$4,1))),1) -> 3 | Y10: =INDEX(Home_Data!$C$5:$F$56,V10,X10) -> 5733 | Z10: =INDEX(Home_Data!$C$5:$F$56,V10,X10+1) -> 7858 | AA10: =INDEX(Home_Data!$C$4:$F$4,X10) -> 400000 | AB10: =INDEX(Home_Data!$C$4:$F$4,X10+1) -> 600000 | AC10: =IF($I10<200000,INDEX(Home_Data!$C$5:$F$56,V10,1)*(MAX($I10,Home_Data!$B$90)/200000)^Home_Data!$B$89,Y10*(W10/AA10)^(LN(Z10/Y10)/LN(AB10/AA10))) -> 8462.5127 | AD10: =IF($K10=100,Home_Data!$B$67,IF($K10=500,Home_Data!$B$69,Home_Data!$B$68)) -> 1 | AE10: =IF($J10<=Home_Data!$B$61,Home_Data!$B$64,IF($J10>=Home_Data!$B$63,Home_Data!$B$66,IF($J10<=Home_Data!$B$62,Home_Data!$B$64+(Home_Data!$B$65-Home_Data!$B$64)*(LN($J10)-LN(Home_Data!$B$61))/(LN(Home_Data!$B$62)-LN(Home_Data!$B$61)),Home_Data!$B$65+(Home_Data!$B$66-Home_Data!$B$65)*(LN($J10)-LN(Home_Data!$B$62))/(LN(Home_Data!$B$63)-LN(Home_Data!$B$62))))) -> 1 | AF10: =IF($E10>=20,Home_Data!$B$80,IF($E10>=10,Home_Data!$B$79,1)) -> 1 | AG10: =IF($D10<1960,Home_Data!$B$81,IF($D10<1980,Home_Data!$B$82,IF($D10>=2000,Home_Data!$B$83,1))) -> 0.95 | AH10: =IF($F10="brick",Home_Data!$B$78,1) -> 1 | AI10: =IF($G10="rental",Home_Data!$B$84,IF($G10="vacation",Home_Data!$B$85,1)) -> 1 | AJ10: =INDEX(Home_Data!$B$70:$B$73,MIN(3,MAX(0,$H10))+1) -> 1.29 | AK10: =IF(INDEX(Home_Data!$H$5:$H$56,V10)="Yes",1,IF($L10="poor",Home_Data!$B$74,IF($L10="fair",Home_Data!$B$75,IF($L10="excellent",Home_Data!$B$77,Home_Data!$B$76)))) -> 0.89 | AL10: =IF(($N10=1),Home_Data!$B$86,1)*IF(($O10=1),Home_Data!$B$87,1)*IF(($P10=1),Home_Data!$B$88,1) -> 1 | AM10: =AC10*AD10*AE10*AF10*AG10*AH10*AI10*AJ10*AK10*AL10 -> 9230.0203 | AN10: =AM10*EXP(-Car_Data!$B$123*Home_Data!$B$91) -> 6722.4392 | AO10: =AM10*EXP(Car_Data!$B$123*Home_Data!$B$91) -> 12672.971 | AP10: =IF($U10>0,IF(AND($U10>=AN10,$U10<=AO10),1,0),"") | AQ10: =IF($U10>0,$U10/AM10-1,"")
A11: TX-1004 | B11: TX | C11: 2500 | D11: 2010 | E11: 11 | F11: frame | G11: own | H11: 0 | I11: 685000 | J11: 2500 | K11: 500 | L11: good | M11: 0 | N11: 1 | O11: 0 | P11: 1 | Q11: 0 | R11: coastal or hurricane-exposed county; hail or tornado region | V11: =MATCH($B11,Home_Data!$B$5:$B$56,0) -> 43 | W11: =MIN(MAX($I11,50000),3000000) -> 685000 | X11: =IFERROR(MIN(3,MAX(1,MATCH(W11,Home_Data!$C$4:$F$4,1))),1) -> 3 | Y11: =INDEX(Home_Data!$C$5:$F$56,V11,X11) -> 5733 | Z11: =INDEX(Home_Data!$C$5:$F$56,V11,X11+1) -> 7858 | AA11: =INDEX(Home_Data!$C$4:$F$4,X11) -> 400000 | AB11: =INDEX(Home_Data!$C$4:$F$4,X11+1) -> 600000 | AC11: =IF($I11<200000,INDEX(Home_Data!$C$5:$F$56,V11,1)*(MAX($I11,Home_Data!$B$90)/200000)^Home_Data!$B$89,Y11*(W11/AA11)^(LN(Z11/Y11)/LN(AB11/AA11))) -> 8710.7409 | AD11: =IF($K11=100,Home_Data!$B$67,IF($K11=500,Home_Data!$B$69,Home_Data!$B$68)) -> 1.005 | AE11: =IF($J11<=Home_Data!$B$61,Home_Data!$B$64,IF($J11>=Home_Data!$B$63,Home_Data!$B$66,IF($J11<=Home_Data!$B$62,Home_Data!$B$64+(Home_Data!$B$65-Home_Data!$B$64)*(LN($J11)-LN(Home_Data!$B$61))/(LN(Home_Data!$B$62)-LN(Home_Data!$B$61)),Home_Data!$B$65+(Home_Data!$B$66-Home_Data!$B$65)*(LN($J11)-LN(Home_Data!$B$62))/(LN(Home_Data!$B$63)-LN(Home_Data!$B$62))))) -> 0.91 | AF11: =IF($E11>=20,Home_Data!$B$80,IF($E11>=10,Home_Data!$B$79,1)) -> 1.1 | AG11: =IF($D11<1960,Home_Data!$B$81,IF($D11<1980,Home_Data!$B$82,IF($D11>=2000,Home_Data!$B$83,1))) -> 0.95 | AH11: =IF($F11="brick",Home_Data!$B$78,1) -> 1 | AI11: =IF($G11="rental",Home_Data!$B$84,IF($G11="vacation",Home_Data!$B$85,1)) -> 1 | AJ11: =INDEX(Home_Data!$B$70:$B$73,MIN(3,MAX(0,$H11))+1) -> 1 | AK11: =IF(INDEX(Home_Data!$H$5:$H$56,V11)="Yes",1,IF($L11="poor",Home_Data!$B$74,IF($L11="fair",Home_Data!$B$75,IF($L11="excellent",Home_Data!$B$77,Home_Data!$B$76)))) -> 1 | AL11: =IF(($N11=1),Home_Data!$B$86,1)*IF(($O11=1),Home_Data!$B$87,1)*IF(($P11=1),Home_Data!$B$88,1) -> 1.242 | AM11: =AC11*AD11*AE11*AF11*AG11*AH11*AI11*AJ11*AK11*AL11 -> 10339.521 | AN11: =AM11*EXP(-Car_Data!$B$123*Home_Data!$B$91) -> 7530.5148 | AO11: =AM11*EXP(Car_Data!$B$123*Home_Data!$B$91) -> 14196.334 | AP11: =IF($U11>0,IF(AND($U11>=AN11,$U11<=AO11),1,0),"") | AQ11: =IF($U11>0,$U11/AM11-1,"")
A12: TX-1005 | B12: TX | C12: 3750 | D12: 1987 | E12: 23 | F12: brick | G12: own | H12: 0 | I12: 905000 | J12: 5000 | K12: 300 | L12: fair | M12: 0 | N12: 0 | O12: 0 | P12: 1 | Q12: 0 | R12: hail or tornado region | V12: =MATCH($B12,Home_Data!$B$5:$B$56,0) -> 43 | W12: =MIN(MAX($I12,50000),3000000) -> 905000 | X12: =IFERROR(MIN(3,MAX(1,MATCH(W12,Home_Data!$C$4:$F$4,1))),1) -> 3 | Y12: =INDEX(Home_Data!$C$5:$F$56,V12,X12) -> 5733 | Z12: =INDEX(Home_Data!$C$5:$F$56,V12,X12+1) -> 7858 | AA12: =INDEX(Home_Data!$C$4:$F$4,X12) -> 400000 | AB12: =INDEX(Home_Data!$C$4:$F$4,X12+1) -> 600000 | AC12: =IF($I12<200000,INDEX(Home_Data!$C$5:$F$56,V12,1)*(MAX($I12,Home_Data!$B$90)/200000)^Home_Data!$B$89,Y12*(W12/AA12)^(LN(Z12/Y12)/LN(AB12/AA12))) -> 10817.156 | AD12: =IF($K12=100,Home_Data!$B$67,IF($K12=500,Home_Data!$B$69,Home_Data!$B$68)) -> 1 | AE12: =IF($J12<=Home_Data!$B$61,Home_Data!$B$64,IF($J12>=Home_Data!$B$63,Home_Data!$B$66,IF($J12<=Home_Data!$B$62,Home_Data!$B$64+(Home_Data!$B$65-Home_Data!$B$64)*(LN($J12)-LN(Home_Data!$B$61))/(LN(Home_Data!$B$62)-LN(Home_Data!$B$61)),Home_Data!$B$65+(Home_Data!$B$66-Home_Data!$B$65)*(LN($J12)-LN(Home_Data!$B$62))/(LN(Home_Data!$B$63)-LN(Home_Data!$B$62))))) -> 0.84 | AF12: =IF($E12>=20,Home_Data!$B$80,IF($E12>=10,Home_Data!$B$79,1)) -> 1.3 | AG12: =IF($D12<1960,Home_Data!$B$81,IF($D12<1980,Home_Data!$B$82,IF($D12>=2000,Home_Data!$B$83,1))) -> 1 | AH12: =IF($F12="brick",Home_Data!$B$78,1) -> 0.98 | AI12: =IF($G12="rental",Home_Data!$B$84,IF($G12="vacation",Home_Data!$B$85,1)) -> 1 | AJ12: =INDEX(Home_Data!$B$70:$B$73,MIN(3,MAX(0,$H12))+1) -> 1 | AK12: =IF(INDEX(Home_Data!$H$5:$H$56,V12)="Yes",1,IF($L12="poor",Home_Data!$B$74,IF($L12="fair",Home_Data!$B$75,IF($L12="excellent",Home_Data!$B$77,Home_Data!$B$76)))) -> 1.07 | AL12: =IF(($N12=1),Home_Data!$B$86,1)*IF(($O12=1),Home_Data!$B$87,1)*IF(($P12=1),Home_Data!$B$88,1) -> 1.08 | AM12: =AC12*AD12*AE12*AF12*AG12*AH12*AI12*AJ12*AK12*AL12 -> 13377.327 | AN12: =AM12*EXP(-Car_Data!$B$123*Home_Data!$B$91) -> 9743.0193 | AO12: =AM12*EXP(Car_Data!$B$123*Home_Data!$B$91) -> 18367.291 | AP12: =IF($U12>0,IF(AND($U12>=AN12,$U12<=AO12),1,0),"") | AQ12: =IF($U12>0,$U12/AM12-1,"")
A13: TX-1006 | B13: TX | C13: 3150 | D13: 1978 | E13: 21 | F13: frame | G13: own | H13: 0 | I13: 825000 | J13: 5000 | K13: 300 | L13: good | M13: 0 | N13: 1 | O13: 0 | P13: 1 | Q13: 0 | R13: coastal or hurricane-exposed county; hail or tornado region | V13: =MATCH($B13,Home_Data!$B$5:$B$56,0) -> 43 | W13: =MIN(MAX($I13,50000),3000000) -> 825000 | X13: =IFERROR(MIN(3,MAX(1,MATCH(W13,Home_Data!$C$4:$F$4,1))),1) -> 3 | Y13: =INDEX(Home_Data!$C$5:$F$56,V13,X13) -> 5733 | Z13: =INDEX(Home_Data!$C$5:$F$56,V13,X13+1) -> 7858 | AA13: =INDEX(Home_Data!$C$4:$F$4,X13) -> 400000 | AB13: =INDEX(Home_Data!$C$4:$F$4,X13+1) -> 600000 | AC13: =IF($I13<200000,INDEX(Home_Data!$C$5:$F$56,V13,1)*(MAX($I13,Home_Data!$B$90)/200000)^Home_Data!$B$89,Y13*(W13/AA13)^(LN(Z13/Y13)/LN(AB13/AA13))) -> 10066.011 | AD13: =IF($K13=100,Home_Data!$B$67,IF($K13=500,Home_Data!$B$69,Home_Data!$B$68)) -> 1 | AE13: =IF($J13<=Home_Data!$B$61,Home_Data!$B$64,IF($J13>=Home_Data!$B$63,Home_Data!$B$66,IF($J13<=Home_Data!$B$62,Home_Data!$B$64+(Home_Data!$B$65-Home_Data!$B$64)*(LN($J13)-LN(Home_Data!$B$61))/(LN(Home_Data!$B$62)-LN(Home_Data!$B$61)),Home_Data!$B$65+(Home_Data!$B$66-Home_Data!$B$65)*(LN($J13)-LN(Home_Data!$B$62))/(LN(Home_Data!$B$63)-LN(Home_Data!$B$62))))) -> 0.84 | AF13: =IF($E13>=20,Home_Data!$B$80,IF($E13>=10,Home_Data!$B$79,1)) -> 1.3 | AG13: =IF($D13<1960,Home_Data!$B$81,IF($D13<1980,Home_Data!$B$82,IF($D13>=2000,Home_Data!$B$83,1))) -> 1.08 | AH13: =IF($F13="brick",Home_Data!$B$78,1) -> 1 | AI13: =IF($G13="rental",Home_Data!$B$84,IF($G13="vacation",Home_Data!$B$85,1)) -> 1 | AJ13: =INDEX(Home_Data!$B$70:$B$73,MIN(3,MAX(0,$H13))+1) -> 1 | AK13: =IF(INDEX(Home_Data!$H$5:$H$56,V13)="Yes",1,IF($L13="poor",Home_Data!$B$74,IF($L13="fair",Home_Data!$B$75,IF($L13="excellent",Home_Data!$B$77,Home_Data!$B$76)))) -> 1 | AL13: =IF(($N13=1),Home_Data!$B$86,1)*IF(($O13=1),Home_Data!$B$87,1)*IF(($P13=1),Home_Data!$B$88,1) -> 1.242 | AM13: =AC13*AD13*AE13*AF13*AG13*AH13*AI13*AJ13*AK13*AL13 -> 14744.342 | AN13: =AM13*EXP(-Car_Data!$B$123*Home_Data!$B$91) -> 10738.648 | AO13: =AM13*EXP(Car_Data!$B$123*Home_Data!$B$91) -> 20244.225 | AP13: =IF($U13>0,IF(AND($U13>=AN13,$U13<=AO13),1,0),"") | AQ13: =IF($U13>0,$U13/AM13-1,"")
A14: TX-1007 | B14: TX | C14: 1200 | D14: 1976 | E14: 16 | F14: frame | G14: own | H14: 0 | I14: 295000 | J14: 1000 | K14: 100 | L14: good | M14: 0 | N14: 0 | O14: 0 | P14: 1 | Q14: 0 | R14: hail or tornado region | V14: =MATCH($B14,Home_Data!$B$5:$B$56,0) -> 43 | W14: =MIN(MAX($I14,50000),3000000) -> 295000 | X14: =IFERROR(MIN(3,MAX(1,MATCH(W14,Home_Data!$C$4:$F$4,1))),1) -> 1 | Y14: =INDEX(Home_Data!$C$5:$F$56,V14,X14) -> 3294 | Z14: =INDEX(Home_Data!$C$5:$F$56,V14,X14+1) -> 4582 | AA14: =INDEX(Home_Data!$C$4:$F$4,X14) -> 200000 | AB14: =INDEX(Home_Data!$C$4:$F$4,X14+1) -> 300000 | AC14: =IF($I14<200000,INDEX(Home_Data!$C$5:$F$56,V14,1)*(MAX($I14,Home_Data!$B$90)/200000)^Home_Data!$B$89,Y14*(W14/AA14)^(LN(Z14/Y14)/LN(AB14/AA14))) -> 4519.7435 | AD14: =IF($K14=100,Home_Data!$B$67,IF($K14=500,Home_Data!$B$69,Home_Data!$B$68)) -> 0.991 | AE14: =IF($J14<=Home_Data!$B$61,Home_Data!$B$64,IF($J14>=Home_Data!$B$63,Home_Data!$B$66,IF($J14<=Home_Data!$B$62,Home_Data!$B$64+(Home_Data!$B$65-Home_Data!$B$64)*(LN($J14)-LN(Home_Data!$B$61))/(LN(Home_Data!$B$62)-LN(Home_Data!$B$61)),Home_Data!$B$65+(Home_Data!$B$66-Home_Data!$B$65)*(LN($J14)-LN(Home_Data!$B$62))/(LN(Home_Data!$B$63)-LN(Home_Data!$B$62))))) -> 1 | AF14: =IF($E14>=20,Home_Data!$B$80,IF($E14>=10,Home_Data!$B$79,1)) -> 1.1 | AG14: =IF($D14<1960,Home_Data!$B$81,IF($D14<1980,Home_Data!$B$82,IF($D14>=2000,Home_Data!$B$83,1))) -> 1.08 | AH14: =IF($F14="brick",Home_Data!$B$78,1) -> 1 | AI14: =IF($G14="rental",Home_Data!$B$84,IF($G14="vacation",Home_Data!$B$85,1)) -> 1 | AJ14: =INDEX(Home_Data!$B$70:$B$73,MIN(3,MAX(0,$H14))+1) -> 1 | AK14: =IF(INDEX(Home_Data!$H$5:$H$56,V14)="Yes",1,IF($L14="poor",Home_Data!$B$74,IF($L14="fair",Home_Data!$B$75,IF($L14="excellent",Home_Data!$B$77,Home_Data!$B$76)))) -> 1 | AL14: =IF(($N14=1),Home_Data!$B$86,1)*IF(($O14=1),Home_Data!$B$87,1)*IF(($P14=1),Home_Data!$B$88,1) -> 1.08 | AM14: =AC14*AD14*AE14*AF14*AG14*AH14*AI14*AJ14*AK14*AL14 -> 5746.8206 | AN14: =AM14*EXP(-Car_Data!$B$123*Home_Data!$B$91) -> 4185.5435 | AO14: =AM14*EXP(Car_Data!$B$123*Home_Data!$B$91) -> 7890.4798 | AP14: =IF($U14>0,IF(AND($U14>=AN14,$U14<=AO14),1,0),"") | AQ14: =IF($U14>0,$U14/AM14-1,"")
A15: TX-1008 | B15: TX | C15: 3750 | D15: 2018 | E15: 1 | F15: frame | G15: own | H15: 0 | I15: 1035000 | J15: 1000 | K15: 300 | L15: good | M15: 0 | N15: 0 | O15: 0 | P15: 0 | Q15: 0 | R15: inland, no special hazard | V15: =MATCH($B15,Home_Data!$B$5:$B$56,0) -> 43 | W15: =MIN(MAX($I15,50000),3000000) -> 1035000 | X15: =IFERROR(MIN(3,MAX(1,MATCH(W15,Home_Data!$C$4:$F$4,1))),1) -> 3 | Y15: =INDEX(Home_Data!$C$5:$F$56,V15,X15) -> 5733 | Z15: =INDEX(Home_Data!$C$5:$F$56,V15,X15+1) -> 7858 | AA15: =INDEX(Home_Data!$C$4:$F$4,X15) -> 400000 | AB15: =INDEX(Home_Data!$C$4:$F$4,X15+1) -> 600000 | AC15: =IF($I15<200000,INDEX(Home_Data!$C$5:$F$56,V15,1)*(MAX($I15,Home_Data!$B$90)/200000)^Home_Data!$B$89,Y15*(W15/AA15)^(LN(Z15/Y15)/LN(AB15/AA15))) -> 12007.187 | AD15: =IF($K15=100,Home_Data!$B$67,IF($K15=500,Home_Data!$B$69,Home_Data!$B$68)) -> 1 | AE15: =IF($J15<=Home_Data!$B$61,Home_Data!$B$64,IF($J15>=Home_Data!$B$63,Home_Data!$B$66,IF($J15<=Home_Data!$B$62,Home_Data!$B$64+(Home_Data!$B$65-Home_Data!$B$64)*(LN($J15)-LN(Home_Data!$B$61))/(LN(Home_Data!$B$62)-LN(Home_Data!$B$61)),Home_Data!$B$65+(Home_Data!$B$66-Home_Data!$B$65)*(LN($J15)-LN(Home_Data!$B$62))/(LN(Home_Data!$B$63)-LN(Home_Data!$B$62))))) -> 1 | AF15: =IF($E15>=20,Home_Data!$B$80,IF($E15>=10,Home_Data!$B$79,1)) -> 1 | AG15: =IF($D15<1960,Home_Data!$B$81,IF($D15<1980,Home_Data!$B$82,IF($D15>=2000,Home_Data!$B$83,1))) -> 0.95 | AH15: =IF($F15="brick",Home_Data!$B$78,1) -> 1 | AI15: =IF($G15="rental",Home_Data!$B$84,IF($G15="vacation",Home_Data!$B$85,1)) -> 1 | AJ15: =INDEX(Home_Data!$B$70:$B$73,MIN(3,MAX(0,$H15))+1) -> 1 | AK15: =IF(INDEX(Home_Data!$H$5:$H$56,V15)="Yes",1,IF($L15="poor",Home_Data!$B$74,IF($L15="fair",Home_Data!$B$75,IF($L15="excellent",Home_Data!$B$77,Home_Data!$B$76)))) -> 1 | AL15: =IF(($N15=1),Home_Data!$B$86,1)*IF(($O15=1),Home_Data!$B$87,1)*IF(($P15=1),Home_Data!$B$88,1) -> 1 | AM15: =AC15*AD15*AE15*AF15*AG15*AH15*AI15*AJ15*AK15*AL15 -> 11406.828 | AN15: =AM15*EXP(-Car_Data!$B$123*Home_Data!$B$91) -> 8307.8587 | AO15: =AM15*EXP(Car_Data!$B$123*Home_Data!$B$91) -> 15661.763 | AP15: =IF($U15>0,IF(AND($U15>=AN15,$U15<=AO15),1,0),"") | AQ15: =IF($U15>0,$U15/AM15-1,"")
A16: TX-1009 | B16: TX | C16: 1500 | D16: 1972 | E16: 1 | F16: frame | G16: own | H16: 0 | I16: 335000 | J16: 1000 | K16: 100 | L16: good | M16: 0 | N16: 0 | O16: 1 | P16: 1 | Q16: 0 | R16: hail or tornado region; wildfire-exposed area | V16: =MATCH($B16,Home_Data!$B$5:$B$56,0) -> 43 | W16: =MIN(MAX($I16,50000),3000000) -> 335000 | X16: =IFERROR(MIN(3,MAX(1,MATCH(W16,Home_Data!$C$4:$F$4,1))),1) -> 2 | Y16: =INDEX(Home_Data!$C$5:$F$56,V16,X16) -> 4582 | Z16: =INDEX(Home_Data!$C$5:$F$56,V16,X16+1) -> 5733 | AA16: =INDEX(Home_Data!$C$4:$F$4,X16) -> 300000 | AB16: =INDEX(Home_Data!$C$4:$F$4,X16+1) -> 400000 | AC16: =IF($I16<200000,INDEX(Home_Data!$C$5:$F$56,V16,1)*(MAX($I16,Home_Data!$B$90)/200000)^Home_Data!$B$89,Y16*(W16/AA16)^(LN(Z16/Y16)/LN(AB16/AA16))) -> 4993.2967 | AD16: =IF($K16=100,Home_Data!$B$67,IF($K16=500,Home_Data!$B$69,Home_Data!$B$68)) -> 0.991 | AE16: =IF($J16<=Home_Data!$B$61,Home_Data!$B$64,IF($J16>=Home_Data!$B$63,Home_Data!$B$66,IF($J16<=Home_Data!$B$62,Home_Data!$B$64+(Home_Data!$B$65-Home_Data!$B$64)*(LN($J16)-LN(Home_Data!$B$61))/(LN(Home_Data!$B$62)-LN(Home_Data!$B$61)),Home_Data!$B$65+(Home_Data!$B$66-Home_Data!$B$65)*(LN($J16)-LN(Home_Data!$B$62))/(LN(Home_Data!$B$63)-LN(Home_Data!$B$62))))) -> 1 | AF16: =IF($E16>=20,Home_Data!$B$80,IF($E16>=10,Home_Data!$B$79,1)) -> 1 | AG16: =IF($D16<1960,Home_Data!$B$81,IF($D16<1980,Home_Data!$B$82,IF($D16>=2000,Home_Data!$B$83,1))) -> 1.08 | AH16: =IF($F16="brick",Home_Data!$B$78,1) -> 1 | AI16: =IF($G16="rental",Home_Data!$B$84,IF($G16="vacation",Home_Data!$B$85,1)) -> 1 | AJ16: =INDEX(Home_Data!$B$70:$B$73,MIN(3,MAX(0,$H16))+1) -> 1 | AK16: =IF(INDEX(Home_Data!$H$5:$H$56,V16)="Yes",1,IF($L16="poor",Home_Data!$B$74,IF($L16="fair",Home_Data!$B$75,IF($L16="excellent",Home_Data!$B$77,Home_Data!$B$76)))) -> 1 | AL16: =IF(($N16=1),Home_Data!$B$86,1)*IF(($O16=1),Home_Data!$B$87,1)*IF(($P16=1),Home_Data!$B$88,1) -> 1.242 | AM16: =AC16*AD16*AE16*AF16*AG16*AH16*AI16*AJ16*AK16*AL16 -> 6637.5282 | AN16: =AM16*EXP(-Car_Data!$B$123*Home_Data!$B$91) -> 4834.2667 | AO16: =AM16*EXP(Car_Data!$B$123*Home_Data!$B$91) -> 9113.436 | AP16: =IF($U16>0,IF(AND($U16>=AN16,$U16<=AO16),1,0),"") | AQ16: =IF($U16>0,$U16/AM16-1,"")
A17: TX-1010 | B17: TX | C17: 2500 | D17: 1999 | E17: 6 | F17: frame | G17: own | H17: 0 | I17: 545000 | J17: 1000 | K17: 300 | L17: excellent | M17: 0 | N17: 0 | O17: 0 | P17: 0 | Q17: 0 | R17: inland, no special hazard | V17: =MATCH($B17,Home_Data!$B$5:$B$56,0) -> 43 | W17: =MIN(MAX($I17,50000),3000000) -> 545000 | X17: =IFERROR(MIN(3,MAX(1,MATCH(W17,Home_Data!$C$4:$F$4,1))),1) -> 3 | Y17: =INDEX(Home_Data!$C$5:$F$56,V17,X17) -> 5733 | Z17: =INDEX(Home_Data!$C$5:$F$56,V17,X17+1) -> 7858 | AA17: =INDEX(Home_Data!$C$4:$F$4,X17) -> 400000 | AB17: =INDEX(Home_Data!$C$4:$F$4,X17+1) -> 600000 | AC17: =IF($I17<200000,INDEX(Home_Data!$C$5:$F$56,V17,1)*(MAX($I17,Home_Data!$B$90)/200000)^Home_Data!$B$89,Y17*(W17/AA17)^(LN(Z17/Y17)/LN(AB17/AA17))) -> 7291.9414 | AD17: =IF($K17=100,Home_Data!$B$67,IF($K17=500,Home_Data!$B$69,Home_Data!$B$68)) -> 1 | AE17: =IF($J17<=Home_Data!$B$61,Home_Data!$B$64,IF($J17>=Home_Data!$B$63,Home_Data!$B$66,IF($J17<=Home_Data!$B$62,Home_Data!$B$64+(Home_Data!$B$65-Home_Data!$B$64)*(LN($J17)-LN(Home_Data!$B$61))/(LN(Home_Data!$B$62)-LN(Home_Data!$B$61)),Home_Data!$B$65+(Home_Data!$B$66-Home_Data!$B$65)*(LN($J17)-LN(Home_Data!$B$62))/(LN(Home_Data!$B$63)-LN(Home_Data!$B$62))))) -> 1 | AF17: =IF($E17>=20,Home_Data!$B$80,IF($E17>=10,Home_Data!$B$79,1)) -> 1 | AG17: =IF($D17<1960,Home_Data!$B$81,IF($D17<1980,Home_Data!$B$82,IF($D17>=2000,Home_Data!$B$83,1))) -> 1 | AH17: =IF($F17="brick",Home_Data!$B$78,1) -> 1 | AI17: =IF($G17="rental",Home_Data!$B$84,IF($G17="vacation",Home_Data!$B$85,1)) -> 1 | AJ17: =INDEX(Home_Data!$B$70:$B$73,MIN(3,MAX(0,$H17))+1) -> 1 | AK17: =IF(INDEX(Home_Data!$H$5:$H$56,V17)="Yes",1,IF($L17="poor",Home_Data!$B$74,IF($L17="fair",Home_Data!$B$75,IF($L17="excellent",Home_Data!$B$77,Home_Data!$B$76)))) -> 0.89 | AL17: =IF(($N17=1),Home_Data!$B$86,1)*IF(($O17=1),Home_Data!$B$87,1)*IF(($P17=1),Home_Data!$B$88,1) -> 1 | AM17: =AC17*AD17*AE17*AF17*AG17*AH17*AI17*AJ17*AK17*AL17 -> 6489.8279 | AN17: =AM17*EXP(-Car_Data!$B$123*Home_Data!$B$91) -> 4726.6931 | AO17: =AM17*EXP(Car_Data!$B$123*Home_Data!$B$91) -> 8910.6411 | AP17: =IF($U17>0,IF(AND($U17>=AN17,$U17<=AO17),1,0),"") | AQ17: =IF($U17>0,$U17/AM17-1,"")
A18: TX-1011 | B18: TX | C18: 3200 | D18: 2013 | E18: 8 | F18: frame | G18: own | H18: 0 | I18: 905000 | J18: 1000 | K18: 300 | L18: good | M18: 0 | N18: 0 | O18: 1 | P18: 0 | Q18: 0 | R18: wildfire-exposed area | V18: =MATCH($B18,Home_Data!$B$5:$B$56,0) -> 43 | W18: =MIN(MAX($I18,50000),3000000) -> 905000 | X18: =IFERROR(MIN(3,MAX(1,MATCH(W18,Home_Data!$C$4:$F$4,1))),1) -> 3 | Y18: =INDEX(Home_Data!$C$5:$F$56,V18,X18) -> 5733 | Z18: =INDEX(Home_Data!$C$5:$F$56,V18,X18+1) -> 7858 | AA18: =INDEX(Home_Data!$C$4:$F$4,X18) -> 400000 | AB18: =INDEX(Home_Data!$C$4:$F$4,X18+1) -> 600000 | AC18: =IF($I18<200000,INDEX(Home_Data!$C$5:$F$56,V18,1)*(MAX($I18,Home_Data!$B$90)/200000)^Home_Data!$B$89,Y18*(W18/AA18)^(LN(Z18/Y18)/LN(AB18/AA18))) -> 10817.156 | AD18: =IF($K18=100,Home_Data!$B$67,IF($K18=500,Home_Data!$B$69,Home_Data!$B$68)) -> 1 | AE18: =IF($J18<=Home_Data!$B$61,Home_Data!$B$64,IF($J18>=Home_Data!$B$63,Home_Data!$B$66,IF($J18<=Home_Data!$B$62,Home_Data!$B$64+(Home_Data!$B$65-Home_Data!$B$64)*(LN($J18)-LN(Home_Data!$B$61))/(LN(Home_Data!$B$62)-LN(Home_Data!$B$61)),Home_Data!$B$65+(Home_Data!$B$66-Home_Data!$B$65)*(LN($J18)-LN(Home_Data!$B$62))/(LN(Home_Data!$B$63)-LN(Home_Data!$B$62))))) -> 1 | AF18: =IF($E18>=20,Home_Data!$B$80,IF($E18>=10,Home_Data!$B$79,1)) -> 1 | AG18: =IF($D18<1960,Home_Data!$B$81,IF($D18<1980,Home_Data!$B$82,IF($D18>=2000,Home_Data!$B$83,1))) -> 0.95 | AH18: =IF($F18="brick",Home_Data!$B$78,1) -> 1 | AI18: =IF($G18="rental",Home_Data!$B$84,IF($G18="vacation",Home_Data!$B$85,1)) -> 1 | AJ18: =INDEX(Home_Data!$B$70:$B$73,MIN(3,MAX(0,$H18))+1) -> 1 | AK18: =IF(INDEX(Home_Data!$H$5:$H$56,V18)="Yes",1,IF($L18="poor",Home_Data!$B$74,IF($L18="fair",Home_Data!$B$75,IF($L18="excellent",Home_Data!$B$77,Home_Data!$B$76)))) -> 1 | AL18: =IF(($N18=1),Home_Data!$B$86,1)*IF(($O18=1),Home_Data!$B$87,1)*IF(($P18=1),Home_Data!$B$88,1) -> 1.15 | AM18: =AC18*AD18*AE18*AF18*AG18*AH18*AI18*AJ18*AK18*AL18 -> 11817.743 | AN18: =AM18*EXP(-Car_Data!$B$123*Home_Data!$B$91) -> 8607.1379 | AO18: =AM18*EXP(Car_Data!$B$123*Home_Data!$B$91) -> 16225.956 | AP18: =IF($U18>0,IF(AND($U18>=AN18,$U18<=AO18),1,0),"") | AQ18: =IF($U18>0,$U18/AM18-1,"")
A19: TX-1012 | B19: TX | C19: 3150 | D19: 2004 | E19: 10 | F19: frame | G19: own | H19: 0 | I19: 650000 | J19: 1000 | K19: 300 | L19: good | M19: 0 | N19: 0 | O19: 0 | P19: 1 | Q19: 0 | R19: hail or tornado region | V19: =MATCH($B19,Home_Data!$B$5:$B$56,0) -> 43 | W19: =MIN(MAX($I19,50000),3000000) -> 650000 | X19: =IFERROR(MIN(3,MAX(1,MATCH(W19,Home_Data!$C$4:$F$4,1))),1) -> 3 | Y19: =INDEX(Home_Data!$C$5:$F$56,V19,X19) -> 5733 | Z19: =INDEX(Home_Data!$C$5:$F$56,V19,X19+1) -> 7858 | AA19: =INDEX(Home_Data!$C$4:$F$4,X19) -> 400000 | AB19: =INDEX(Home_Data!$C$4:$F$4,X19+1) -> 600000 | AC19: =IF($I19<200000,INDEX(Home_Data!$C$5:$F$56,V19,1)*(MAX($I19,Home_Data!$B$90)/200000)^Home_Data!$B$89,Y19*(W19/AA19)^(LN(Z19/Y19)/LN(AB19/AA19))) -> 8362.6388 | AD19: =IF($K19=100,Home_Data!$B$67,IF($K19=500,Home_Data!$B$69,Home_Data!$B$68)) -> 1 | AE19: =IF($J19<=Home_Data!$B$61,Home_Data!$B$64,IF($J19>=Home_Data!$B$63,Home_Data!$B$66,IF($J19<=Home_Data!$B$62,Home_Data!$B$64+(Home_Data!$B$65-Home_Data!$B$64)*(LN($J19)-LN(Home_Data!$B$61))/(LN(Home_Data!$B$62)-LN(Home_Data!$B$61)),Home_Data!$B$65+(Home_Data!$B$66-Home_Data!$B$65)*(LN($J19)-LN(Home_Data!$B$62))/(LN(Home_Data!$B$63)-LN(Home_Data!$B$62))))) -> 1 | AF19: =IF($E19>=20,Home_Data!$B$80,IF($E19>=10,Home_Data!$B$79,1)) -> 1.1 | AG19: =IF($D19<1960,Home_Data!$B$81,IF($D19<1980,Home_Data!$B$82,IF($D19>=2000,Home_Data!$B$83,1))) -> 0.95 | AH19: =IF($F19="brick",Home_Data!$B$78,1) -> 1 | AI19: =IF($G19="rental",Home_Data!$B$84,IF($G19="vacation",Home_Data!$B$85,1)) -> 1 | AJ19: =INDEX(Home_Data!$B$70:$B$73,MIN(3,MAX(0,$H19))+1) -> 1 | AK19: =IF(INDEX(Home_Data!$H$5:$H$56,V19)="Yes",1,IF($L19="poor",Home_Data!$B$74,IF($L19="fair",Home_Data!$B$75,IF($L19="excellent",Home_Data!$B$77,Home_Data!$B$76)))) -> 1 | AL19: =IF(($N19=1),Home_Data!$B$86,1)*IF(($O19=1),Home_Data!$B$87,1)*IF(($P19=1),Home_Data!$B$88,1) -> 1.08 | AM19: =AC19*AD19*AE19*AF19*AG19*AH19*AI19*AJ19*AK19*AL19 -> 9438.0741 | AN19: =AM19*EXP(-Car_Data!$B$123*Home_Data!$B$91) -> 6873.9697 | AO19: =AM19*EXP(Car_Data!$B$123*Home_Data!$B$91) -> 12958.632 | AP19: =IF($U19>0,IF(AND($U19>=AN19,$U19<=AO19),1,0),"") | AQ19: =IF($U19>0,$U19/AM19-1,"")
... A127: FL-1060 | B127: FL | C127: 1800 | D127: 1984 | E127: 22 | F127: frame | G127: own | H127: 0 | I127: 425000 | J127: 1000 | K127: 300 | L127: excellent | M127: 0 | N127: 0 | O127: 0 | P127: 0 | Q127: 0 | R127: inland, no special hazard | V127: =MATCH($B127,Home_Data!$B$5:$B$56,0) -> 9 | W127: =MIN(MAX($I127,50000),3000000) -> 425000 | X127: =IFERROR(MIN(3,MAX(1,MATCH(W127,Home_Data!$C$4:$F$4,1))),1) -> 3 | Y127: =INDEX(Home_Data!$C$5:$F$56,V127,X127) -> 11161 | Z127: =INDEX(Home_Data!$C$5:$F$56,V127,X127+1) -> 16690 | AA127: =INDEX(Home_Data!$C$4:$F$4,X127) -> 400000 | AB127: =INDEX(Home_Data!$C$4:$F$4,X127+1) -> 600000 | AC127: =IF($I127<200000,INDEX(Home_Data!$C$5:$F$56,V127,1)*(MAX($I127,Home_Data!$B$90)/200000)^Home_Data!$B$89,Y127*(W127/AA127)^(LN(Z127/Y127)/LN(AB127/AA127))) -> 11853.101 | AD127: =IF($K127=100,Home_Data!$B$67,IF($K127=500,Home_Data!$B$69,Home_Data!$B$68)) -> 1 | AE127: =IF($J127<=Home_Data!$B$61,Home_Data!$B$64,IF($J127>=Home_Data!$B$63,Home_Data!$B$66,IF($J127<=Home_Data!$B$62,Home_Data!$B$64+(Home_Data!$B$65-Home_Data!$B$64)*(LN($J127)-LN(Home_Data!$B$61))/(LN(Home_Data!$B$62)-LN(Home_Data!$B$61)),Home_Data!$B$65+(Home_Data!$B$66-Home_Data!$B$65)*(LN($J127)-LN(Home_Data!$B$62))/(LN(Home_Data!$B$63)-LN(Home_Data!$B$62))))) -> 1 | AF127: =IF($E127>=20,Home_Data!$B$80,IF($E127>=10,Home_Data!$B$79,1)) -> 1.3 | AG127: =IF($D127<1960,Home_Data!$B$81,IF($D127<1980,Home_Data!$B$82,IF($D127>=2000,Home_Data!$B$83,1))) -> 1 | AH127: =IF($F127="brick",Home_Data!$B$78,1) -> 1 | AI127: =IF($G127="rental",Home_Data!$B$84,IF($G127="vacation",Home_Data!$B$85,1)) -> 1 | AJ127: =INDEX(Home_Data!$B$70:$B$73,MIN(3,MAX(0,$H127))+1) -> 1 | AK127: =IF(INDEX(Home_Data!$H$5:$H$56,V127)="Yes",1,IF($L127="poor",Home_Data!$B$74,IF($L127="fair",Home_Data!$B$75,IF($L127="excellent",Home_Data!$B$77,Home_Data!$B$76)))) -> 0.89 | AL127: =IF(($N127=1),Home_Data!$B$86,1)*IF(($O127=1),Home_Data!$B$87,1)*IF(($P127=1),Home_Data!$B$88,1) -> 1 | AM127: =AC127*AD127*AE127*AF127*AG127*AH127*AI127*AJ127*AK127*AL127 -> 13714.038 | AN127: =AM127*EXP(-Car_Data!$B$123*Home_Data!$B$91) -> 9988.2539 | AO127: =AM127*EXP(Car_Data!$B$123*Home_Data!$B$91) -> 18829.601 | AP127: =IF($U127>0,IF(AND($U127>=AN127,$U127<=AO127),1,0),"") | AQ127: =IF($U127>0,$U127/AM127-1,"")
A128: CA-1001 | B128: CA | C128: 2400 | D128: 1991 | E128: 0 | F128: brick | G128: own | H128: 0 | I128: 490000 | J128: 1000 | K128: 300 | M128: 0 | N128: 0 | O128: 1 | P128: 0 | Q128: 1 | R128: wildfire-exposed area; earthquake region | V128: =MATCH($B128,Home_Data!$B$5:$B$56,0) -> 5 | W128: =MIN(MAX($I128,50000),3000000) -> 490000 | X128: =IFERROR(MIN(3,MAX(1,MATCH(W128,Home_Data!$C$4:$F$4,1))),1) -> 3 | Y128: =INDEX(Home_Data!$C$5:$F$56,V128,X128) -> 2090 | Z128: =INDEX(Home_Data!$C$5:$F$56,V128,X128+1) -> 3092 | AA128: =INDEX(Home_Data!$C$4:$F$4,X128) -> 400000 | AB128: =INDEX(Home_Data!$C$4:$F$4,X128+1) -> 600000 | AC128: =IF($I128<200000,INDEX(Home_Data!$C$5:$F$56,V128,1)*(MAX($I128,Home_Data!$B$90)/200000)^Home_Data!$B$89,Y128*(W128/AA128)^(LN(Z128/Y128)/LN(AB128/AA128))) -> 2542.613 | AD128: =IF($K128=100,Home_Data!$B$67,IF($K128=500,Home_Data!$B$69,Home_Data!$B$68)) -> 1 | AE128: =IF($J128<=Home_Data!$B$61,Home_Data!$B$64,IF($J128>=Home_Data!$B$63,Home_Data!$B$66,IF($J128<=Home_Data!$B$62,Home_Data!$B$64+(Home_Data!$B$65-Home_Data!$B$64)*(LN($J128)-LN(Home_Data!$B$61))/(LN(Home_Data!$B$62)-LN(Home_Data!$B$61)),Home_Data!$B$65+(Home_Data!$B$66-Home_Data!$B$65)*(LN($J128)-LN(Home_Data!$B$62))/(LN(Home_Data!$B$63)-LN(Home_Data!$B$62))))) -> 1 | AF128: =IF($E128>=20,Home_Data!$B$80,IF($E128>=10,Home_Data!$B$79,1)) -> 1 | AG128: =IF($D128<1960,Home_Data!$B$81,IF($D128<1980,Home_Data!$B$82,IF($D128>=2000,Home_Data!$B$83,1))) -> 1 | AH128: =IF($F128="brick",Home_Data!$B$78,1) -> 0.98 | AI128: =IF($G128="rental",Home_Data!$B$84,IF($G128="vacation",Home_Data!$B$85,1)) -> 1 | AJ128: =INDEX(Home_Data!$B$70:$B$73,MIN(3,MAX(0,$H128))+1) -> 1 | AK128: =IF(INDEX(Home_Data!$H$5:$H$56,V128)="Yes",1,IF($L128="poor",Home_Data!$B$74,IF($L128="fair",Home_Data!$B$75,IF($L128="excellent",Home_Data!$B$77,Home_Data!$B$76)))) -> 1 | AL128: =IF(($N128=1),Home_Data!$B$86,1)*IF(($O128=1),Home_Data!$B$87,1)*IF(($P128=1),Home_Data!$B$88,1) -> 1.15 | AM128: =AC128*AD128*AE128*AF128*AG128*AH128*AI128*AJ128*AK128*AL128 -> 2865.5249 | AN128: =AM128*EXP(-Car_Data!$B$123*Home_Data!$B$91) -> 2087.0286 | AO128: =AM128*EXP(Car_Data!$B$123*Home_Data!$B$91) -> 3934.4131 | AP128: =IF($U128>0,IF(AND($U128>=AN128,$U128<=AO128),1,0),"") | AQ128: =IF($U128>0,$U128/AM128-1,"")
A129: CA-1002 | B129: CA | C129: 3400 | D129: 1969 | E129: 19 | F129: frame | G129: own | H129: 0 | I129: 845000 | J129: 1000 | K129: 300 | M129: 0 | N129: 0 | O129: 1 | P129: 0 | Q129: 1 | R129: wildfire-exposed area; earthquake region | V129: =MATCH($B129,Home_Data!$B$5:$B$56,0) -> 5 | W129: =MIN(MAX($I129,50000),3000000) -> 845000 | X129: =IFERROR(MIN(3,MAX(1,MATCH(W129,Home_Data!$C$4:$F$4,1))),1) -> 3 | Y129: =INDEX(Home_Data!$C$5:$F$56,V129,X129) -> 2090 | Z129: =INDEX(Home_Data!$C$5:$F$56,V129,X129+1) -> 3092 | AA129: =INDEX(Home_Data!$C$4:$F$4,X129) -> 400000 | AB129: =INDEX(Home_Data!$C$4:$F$4,X129+1) -> 600000 | AC129: =IF($I129<200000,INDEX(Home_Data!$C$5:$F$56,V129,1)*(MAX($I129,Home_Data!$B$90)/200000)^Home_Data!$B$89,Y129*(W129/AA129)^(LN(Z129/Y129)/LN(AB129/AA129))) -> 4304.0738 | AD129: =IF($K129=100,Home_Data!$B$67,IF($K129=500,Home_Data!$B$69,Home_Data!$B$68)) -> 1 | AE129: =IF($J129<=Home_Data!$B$61,Home_Data!$B$64,IF($J129>=Home_Data!$B$63,Home_Data!$B$66,IF($J129<=Home_Data!$B$62,Home_Data!$B$64+(Home_Data!$B$65-Home_Data!$B$64)*(LN($J129)-LN(Home_Data!$B$61))/(LN(Home_Data!$B$62)-LN(Home_Data!$B$61)),Home_Data!$B$65+(Home_Data!$B$66-Home_Data!$B$65)*(LN($J129)-LN(Home_Data!$B$62))/(LN(Home_Data!$B$63)-LN(Home_Data!$B$62))))) -> 1 | AF129: =IF($E129>=20,Home_Data!$B$80,IF($E129>=10,Home_Data!$B$79,1)) -> 1.1 | AG129: =IF($D129<1960,Home_Data!$B$81,IF($D129<1980,Home_Data!$B$82,IF($D129>=2000,Home_Data!$B$83,1))) -> 1.08 | AH129: =IF($F129="brick",Home_Data!$B$78,1) -> 1 | AI129: =IF($G129="rental",Home_Data!$B$84,IF($G129="vacation",Home_Data!$B$85,1)) -> 1 | AJ129: =INDEX(Home_Data!$B$70:$B$73,MIN(3,MAX(0,$H129))+1) -> 1 | AK129: =IF(INDEX(Home_Data!$H$5:$H$56,V129)="Yes",1,IF($L129="poor",Home_Data!$B$74,IF($L129="fair",Home_Data!$B$75,IF($L129="excellent",Home_Data!$B$77,Home_Data!$B$76)))) -> 1 | AL129: =IF(($N129=1),Home_Data!$B$86,1)*IF(($O129=1),Home_Data!$B$87,1)*IF(($P129=1),Home_Data!$B$88,1) -> 1.15 | AM129: =AC129*AD129*AE129*AF129*AG129*AH129*AI129*AJ129*AK129*AL129 -> 5880.2256 | AN129: =AM129*EXP(-Car_Data!$B$123*Home_Data!$B$91) -> 4282.7055 | AO129: =AM129*EXP(Car_Data!$B$123*Home_Data!$B$91) -> 8073.647 | AP129: =IF($U129>0,IF(AND($U129>=AN129,$U129<=AO129),1,0),"") | AQ129: =IF($U129>0,$U129/AM129-1,"")
A130: CA-1003 | B130: CA | C130: 1300 | D130: 2018 | E130: 1 | F130: frame | G130: own | H130: 0 | I130: 270000 | J130: 1000 | K130: 500 | M130: 0 | N130: 0 | O130: 1 | P130: 0 | Q130: 1 | R130: wildfire-exposed area; earthquake region | V130: =MATCH($B130,Home_Data!$B$5:$B$56,0) -> 5 | W130: =MIN(MAX($I130,50000),3000000) -> 270000 | X130: =IFERROR(MIN(3,MAX(1,MATCH(W130,Home_Data!$C$4:$F$4,1))),1) -> 1 | Y130: =INDEX(Home_Data!$C$5:$F$56,V130,X130) -> 1244 | Z130: =INDEX(Home_Data!$C$5:$F$56,V130,X130+1) -> 1653 | AA130: =INDEX(Home_Data!$C$4:$F$4,X130) -> 200000 | AB130: =INDEX(Home_Data!$C$4:$F$4,X130+1) -> 300000 | AC130: =IF($I130<200000,INDEX(Home_Data!$C$5:$F$56,V130,1)*(MAX($I130,Home_Data!$B$90)/200000)^Home_Data!$B$89,Y130*(W130/AA130)^(LN(Z130/Y130)/LN(AB130/AA130))) -> 1535.3013 | AD130: =IF($K130=100,Home_Data!$B$67,IF($K130=500,Home_Data!$B$69,Home_Data!$B$68)) -> 1.005 | AE130: =IF($J130<=Home_Data!$B$61,Home_Data!$B$64,IF($J130>=Home_Data!$B$63,Home_Data!$B$66,IF($J130<=Home_Data!$B$62,Home_Data!$B$64+(Home_Data!$B$65-Home_Data!$B$64)*(LN($J130)-LN(Home_Data!$B$61))/(LN(Home_Data!$B$62)-LN(Home_Data!$B$61)),Home_Data!$B$65+(Home_Data!$B$66-Home_Data!$B$65)*(LN($J130)-LN(Home_Data!$B$62))/(LN(Home_Data!$B$63)-LN(Home_Data!$B$62))))) -> 1 | AF130: =IF($E130>=20,Home_Data!$B$80,IF($E130>=10,Home_Data!$B$79,1)) -> 1 | AG130: =IF($D130<1960,Home_Data!$B$81,IF($D130<1980,Home_Data!$B$82,IF($D130>=2000,Home_Data!$B$83,1))) -> 0.95 | AH130: =IF($F130="brick",Home_Data!$B$78,1) -> 1 | AI130: =IF($G130="rental",Home_Data!$B$84,IF($G130="vacation",Home_Data!$B$85,1)) -> 1 | AJ130: =INDEX(Home_Data!$B$70:$B$73,MIN(3,MAX(0,$H130))+1) -> 1 | AK130: =IF(INDEX(Home_Data!$H$5:$H$56,V130)="Yes",1,IF($L130="poor",Home_Data!$B$74,IF($L130="fair",Home_Data!$B$75,IF($L130="excellent",Home_Data!$B$77,Home_Data!$B$76)))) -> 1 | AL130: =IF(($N130=1),Home_Data!$B$86,1)*IF(($O130=1),Home_Data!$B$87,1)*IF(($P130=1),Home_Data!$B$88,1) -> 1.15 | AM130: =AC130*AD130*AE130*AF130*AG130*AH130*AI130*AJ130*AK130*AL130 -> 1685.7032 | AN130: =AM130*EXP(-Car_Data!$B$123*Home_Data!$B$91) -> 1227.737 | AO130: =AM130*EXP(Car_Data!$B$123*Home_Data!$B$91) -> 2314.4984 | AP130: =IF($U130>0,IF(AND($U130>=AN130,$U130<=AO130),1,0),"") | AQ130: =IF($U130>0,$U130/AM130-1,"")
A131: CA-1004 | B131: CA | C131: 2950 | D131: 1971 | E131: 20 | F131: frame | G131: own | H131: 0 | I131: 850000 | J131: 2500 | K131: 100 | M131: 0 | N131: 0 | O131: 0 | P131: 0 | Q131: 0 | R131: inland, no special hazard | V131: =MATCH($B131,Home_Data!$B$5:$B$56,0) -> 5 | W131: =MIN(MAX($I131,50000),3000000) -> 850000 | X131: =IFERROR(MIN(3,MAX(1,MATCH(W131,Home_Data!$C$4:$F$4,1))),1) -> 3 | Y131: =INDEX(Home_Data!$C$5:$F$56,V131,X131) -> 2090 | Z131: =INDEX(Home_Data!$C$5:$F$56,V131,X131+1) -> 3092 | AA131: =INDEX(Home_Data!$C$4:$F$4,X131) -> 400000 | AB131: =INDEX(Home_Data!$C$4:$F$4,X131+1) -> 600000 | AC131: =IF($I131<200000,INDEX(Home_Data!$C$5:$F$56,V131,1)*(MAX($I131,Home_Data!$B$90)/200000)^Home_Data!$B$89,Y131*(W131/AA131)^(LN(Z131/Y131)/LN(AB131/AA131))) -> 4328.6717 | AD131: =IF($K131=100,Home_Data!$B$67,IF($K131=500,Home_Data!$B$69,Home_Data!$B$68)) -> 0.991 | AE131: =IF($J131<=Home_Data!$B$61,Home_Data!$B$64,IF($J131>=Home_Data!$B$63,Home_Data!$B$66,IF($J131<=Home_Data!$B$62,Home_Data!$B$64+(Home_Data!$B$65-Home_Data!$B$64)*(LN($J131)-LN(Home_Data!$B$61))/(LN(Home_Data!$B$62)-LN(Home_Data!$B$61)),Home_Data!$B$65+(Home_Data!$B$66-Home_Data!$B$65)*(LN($J131)-LN(Home_Data!$B$62))/(LN(Home_Data!$B$63)-LN(Home_Data!$B$62))))) -> 0.91 | AF131: =IF($E131>=20,Home_Data!$B$80,IF($E131>=10,Home_Data!$B$79,1)) -> 1.3 | AG131: =IF($D131<1960,Home_Data!$B$81,IF($D131<1980,Home_Data!$B$82,IF($D131>=2000,Home_Data!$B$83,1))) -> 1.08 | AH131: =IF($F131="brick",Home_Data!$B$78,1) -> 1 | AI131: =IF($G131="rental",Home_Data!$B$84,IF($G131="vacation",Home_Data!$B$85,1)) -> 1 | AJ131: =INDEX(Home_Data!$B$70:$B$73,MIN(3,MAX(0,$H131))+1) -> 1 | AK131: =IF(INDEX(Home_Data!$H$5:$H$56,V131)="Yes",1,IF($L131="poor",Home_Data!$B$74,IF($L131="fair",Home_Data!$B$75,IF($L131="excellent",Home_Data!$B$77,Home_Data!$B$76)))) -> 1 | AL131: =IF(($N131=1),Home_Data!$B$86,1)*IF(($O131=1),Home_Data!$B$87,1)*IF(($P131=1),Home_Data!$B$88,1) -> 1 | AM131: =AC131*AD131*AE131*AF131*AG131*AH131*AI131*AJ131*AK131*AL131 -> 5480.7097 | AN131: =AM131*EXP(-Car_Data!$B$123*Home_Data!$B$91) -> 3991.7288 | AO131: =AM131*EXP(Car_Data!$B$123*Home_Data!$B$91) -> 7525.1052 | AP131: =IF($U131>0,IF(AND($U131>=AN131,$U131<=AO131),1,0),"") | AQ131: =IF($U131>0,$U131/AM131-1,"")
A132: CA-1005 | B132: CA | C132: 1550 | D132: 2005 | E132: 5 | F132: frame | G132: own | H132: 0 | I132: 395000 | J132: 1000 | K132: 300 | M132: 0 | N132: 0 | O132: 0 | P132: 0 | Q132: 1 | R132: earthquake region | V132: =MATCH($B132,Home_Data!$B$5:$B$56,0) -> 5 | W132: =MIN(MAX($I132,50000),3000000) -> 395000 | X132: =IFERROR(MIN(3,MAX(1,MATCH(W132,Home_Data!$C$4:$F$4,1))),1) -> 2 | Y132: =INDEX(Home_Data!$C$5:$F$56,V132,X132) -> 1653 | Z132: =INDEX(Home_Data!$C$5:$F$56,V132,X132+1) -> 2090 | AA132: =INDEX(Home_Data!$C$4:$F$4,X132) -> 300000 | AB132: =INDEX(Home_Data!$C$4:$F$4,X132+1) -> 400000 | AC132: =IF($I132<200000,INDEX(Home_Data!$C$5:$F$56,V132,1)*(MAX($I132,Home_Data!$B$90)/200000)^Home_Data!$B$89,Y132*(W132/AA132)^(LN(Z132/Y132)/LN(AB132/AA132))) -> 2068.6733 | AD132: =IF($K132=100,Home_Data!$B$67,IF($K132=500,Home_Data!$B$69,Home_Data!$B$68)) -> 1 | AE132: =IF($J132<=Home_Data!$B$61,Home_Data!$B$64,IF($J132>=Home_Data!$B$63,Home_Data!$B$66,IF($J132<=Home_Data!$B$62,Home_Data!$B$64+(Home_Data!$B$65-Home_Data!$B$64)*(LN($J132)-LN(Home_Data!$B$61))/(LN(Home_Data!$B$62)-LN(Home_Data!$B$61)),Home_Data!$B$65+(Home_Data!$B$66-Home_Data!$B$65)*(LN($J132)-LN(Home_Data!$B$62))/(LN(Home_Data!$B$63)-LN(Home_Data!$B$62))))) -> 1 | AF132: =IF($E132>=20,Home_Data!$B$80,IF($E132>=10,Home_Data!$B$79,1)) -> 1 | AG132: =IF($D132<1960,Home_Data!$B$81,IF($D132<1980,Home_Data!$B$82,IF($D132>=2000,Home_Data!$B$83,1))) -> 0.95 | AH132: =IF($F132="brick",Home_Data!$B$78,1) -> 1 | AI132: =IF($G132="rental",Home_Data!$B$84,IF($G132="vacation",Home_Data!$B$85,1)) -> 1 | AJ132: =INDEX(Home_Data!$B$70:$B$73,MIN(3,MAX(0,$H132))+1) -> 1 | AK132: =IF(INDEX(Home_Data!$H$5:$H$56,V132)="Yes",1,IF($L132="poor",Home_Data!$B$74,IF($L132="fair",Home_Data!$B$75,IF($L132="excellent",Home_Data!$B$77,Home_Data!$B$76)))) -> 1 | AL132: =IF(($N132=1),Home_Data!$B$86,1)*IF(($O132=1),Home_Data!$B$87,1)*IF(($P132=1),Home_Data!$B$88,1) -> 1 | AM132: =AC132*AD132*AE132*AF132*AG132*AH132*AI132*AJ132*AK132*AL132 -> 1965.2396 | AN132: =AM132*EXP(-Car_Data!$B$123*Home_Data!$B$91) -> 1431.3299 | AO132: =AM132*EXP(Car_Data!$B$123*Home_Data!$B$91) -> 2698.3066 | AP132: =IF($U132>0,IF(AND($U132>=AN132,$U132<=AO132),1,0),"") | AQ132: =IF($U132>0,$U132/AM132-1,"")
A133: CA-1006 | B133: CA | C133: 3600 | D133: 1974 | E133: 5 | F133: frame | G133: own | H133: 0 | I133: 930000 | J133: 5000 | K133: 300 | M133: 0 | N133: 0 | O133: 0 | P133: 0 | Q133: 1 | R133: earthquake region | V133: =MATCH($B133,Home_Data!$B$5:$B$56,0) -> 5 | W133: =MIN(MAX($I133,50000),3000000) -> 930000 | X133: =IFERROR(MIN(3,MAX(1,MATCH(W133,Home_Data!$C$4:$F$4,1))),1) -> 3 | Y133: =INDEX(Home_Data!$C$5:$F$56,V133,X133) -> 2090 | Z133: =INDEX(Home_Data!$C$5:$F$56,V133,X133+1) -> 3092 | AA133: =INDEX(Home_Data!$C$4:$F$4,X133) -> 400000 | AB133: =INDEX(Home_Data!$C$4:$F$4,X133+1) -> 600000 | AC133: =IF($I133<200000,INDEX(Home_Data!$C$5:$F$56,V133,1)*(MAX($I133,Home_Data!$B$90)/200000)^Home_Data!$B$89,Y133*(W133/AA133)^(LN(Z133/Y133)/LN(AB133/AA133))) -> 4721.5877 | AD133: =IF($K133=100,Home_Data!$B$67,IF($K133=500,Home_Data!$B$69,Home_Data!$B$68)) -> 1 | AE133: =IF($J133<=Home_Data!$B$61,Home_Data!$B$64,IF($J133>=Home_Data!$B$63,Home_Data!$B$66,IF($J133<=Home_Data!$B$62,Home_Data!$B$64+(Home_Data!$B$65-Home_Data!$B$64)*(LN($J133)-LN(Home_Data!$B$61))/(LN(Home_Data!$B$62)-LN(Home_Data!$B$61)),Home_Data!$B$65+(Home_Data!$B$66-Home_Data!$B$65)*(LN($J133)-LN(Home_Data!$B$62))/(LN(Home_Data!$B$63)-LN(Home_Data!$B$62))))) -> 0.84 | AF133: =IF($E133>=20,Home_Data!$B$80,IF($E133>=10,Home_Data!$B$79,1)) -> 1 | AG133: =IF($D133<1960,Home_Data!$B$81,IF($D133<1980,Home_Data!$B$82,IF($D133>=2000,Home_Data!$B$83,1))) -> 1.08 | AH133: =IF($F133="brick",Home_Data!$B$78,1) -> 1 | AI133: =IF($G133="rental",Home_Data!$B$84,IF($G133="vacation",Home_Data!$B$85,1)) -> 1 | AJ133: =INDEX(Home_Data!$B$70:$B$73,MIN(3,MAX(0,$H133))+1) -> 1 | AK133: =IF(INDEX(Home_Data!$H$5:$H$56,V133)="Yes",1,IF($L133="poor",Home_Data!$B$74,IF($L133="fair",Home_Data!$B$75,IF($L133="excellent",Home_Data!$B$77,Home_Data!$B$76)))) -> 1 | AL133: =IF(($N133=1),Home_Data!$B$86,1)*IF(($O133=1),Home_Data!$B$87,1)*IF(($P133=1),Home_Data!$B$88,1) -> 1 | AM133: =AC133*AD133*AE133*AF133*AG133*AH133*AI133*AJ133*AK133*AL133 -> 4283.4244 | AN133: =AM133*EXP(-Car_Data!$B$123*Home_Data!$B$91) -> 3119.7179 | AO133: =AM133*EXP(Car_Data!$B$123*Home_Data!$B$91) -> 5881.2126 | AP133: =IF($U133>0,IF(AND($U133>=AN133,$U133<=AO133),1,0),"") | AQ133: =IF($U133>0,$U133/AM133-1,"")
A134: CA-1007 | B134: CA | C134: 2350 | D134: 2002 | E134: 9 | F134: brick | G134: own | H134: 1 | I134: 475000 | J134: 1000 | K134: 300 | M134: 0 | N134: 0 | O134: 0 | P134: 0 | Q134: 1 | R134: earthquake region | V134: =MATCH($B134,Home_Data!$B$5:$B$56,0) -> 5 | W134: =MIN(MAX($I134,50000),3000000) -> 475000 | X134: =IFERROR(MIN(3,MAX(1,MATCH(W134,Home_Data!$C$4:$F$4,1))),1) -> 3 | Y134: =INDEX(Home_Data!$C$5:$F$56,V134,X134) -> 2090 | Z134: =INDEX(Home_Data!$C$5:$F$56,V134,X134+1) -> 3092 | AA134: =INDEX(Home_Data!$C$4:$F$4,X134) -> 400000 | AB134: =INDEX(Home_Data!$C$4:$F$4,X134+1) -> 600000 | AC134: =IF($I134<200000,INDEX(Home_Data!$C$5:$F$56,V134,1)*(MAX($I134,Home_Data!$B$90)/200000)^Home_Data!$B$89,Y134*(W134/AA134)^(LN(Z134/Y134)/LN(AB134/AA134))) -> 2467.3895 | AD134: =IF($K134=100,Home_Data!$B$67,IF($K134=500,Home_Data!$B$69,Home_Data!$B$68)) -> 1 | AE134: =IF($J134<=Home_Data!$B$61,Home_Data!$B$64,IF($J134>=Home_Data!$B$63,Home_Data!$B$66,IF($J134<=Home_Data!$B$62,Home_Data!$B$64+(Home_Data!$B$65-Home_Data!$B$64)*(LN($J134)-LN(Home_Data!$B$61))/(LN(Home_Data!$B$62)-LN(Home_Data!$B$61)),Home_Data!$B$65+(Home_Data!$B$66-Home_Data!$B$65)*(LN($J134)-LN(Home_Data!$B$62))/(LN(Home_Data!$B$63)-LN(Home_Data!$B$62))))) -> 1 | AF134: =IF($E134>=20,Home_Data!$B$80,IF($E134>=10,Home_Data!$B$79,1)) -> 1 | AG134: =IF($D134<1960,Home_Data!$B$81,IF($D134<1980,Home_Data!$B$82,IF($D134>=2000,Home_Data!$B$83,1))) -> 0.95 | AH134: =IF($F134="brick",Home_Data!$B$78,1) -> 0.98 | AI134: =IF($G134="rental",Home_Data!$B$84,IF($G134="vacation",Home_Data!$B$85,1)) -> 1 | AJ134: =INDEX(Home_Data!$B$70:$B$73,MIN(3,MAX(0,$H134))+1) -> 1.16 | AK134: =IF(INDEX(Home_Data!$H$5:$H$56,V134)="Yes",1,IF($L134="poor",Home_Data!$B$74,IF($L134="fair",Home_Data!$B$75,IF($L134="excellent",Home_Data!$B$77,Home_Data!$B$76)))) -> 1 | AL134: =IF(($N134=1),Home_Data!$B$86,1)*IF(($O134=1),Home_Data!$B$87,1)*IF(($P134=1),Home_Data!$B$88,1) -> 1 | AM134: =AC134*AD134*AE134*AF134*AG134*AH134*AI134*AJ134*AK134*AL134 -> 2664.682 | AN134: =AM134*EXP(-Car_Data!$B$123*Home_Data!$B$91) -> 1940.7501 | AO134: =AM134*EXP(Car_Data!$B$123*Home_Data!$B$91) -> 3658.6525 | AP134: =IF($U134>0,IF(AND($U134>=AN134,$U134<=AO134),1,0),"") | AQ134: =IF($U134>0,$U134/AM134-1,"")
A135: CA-1008 | B135: CA | C135: 3800 | D135: 1975 | E135: 2 | F135: brick | G135: own | H135: 0 | I135: 1105000 | J135: 1000 | K135: 100 | M135: 0 | N135: 0 | O135: 0 | P135: 0 | Q135: 0 | R135: inland, no special hazard | V135: =MATCH($B135,Home_Data!$B$5:$B$56,0) -> 5 | W135: =MIN(MAX($I135,50000),3000000) -> 1105000 | X135: =IFERROR(MIN(3,MAX(1,MATCH(W135,Home_Data!$C$4:$F$4,1))),1) -> 3 | Y135: =INDEX(Home_Data!$C$5:$F$56,V135,X135) -> 2090 | Z135: =INDEX(Home_Data!$C$5:$F$56,V135,X135+1) -> 3092 | AA135: =INDEX(Home_Data!$C$4:$F$4,X135) -> 400000 | AB135: =INDEX(Home_Data!$C$4:$F$4,X135+1) -> 600000 | AC135: =IF($I135<200000,INDEX(Home_Data!$C$5:$F$56,V135,1)*(MAX($I135,Home_Data!$B$90)/200000)^Home_Data!$B$89,Y135*(W135/AA135)^(LN(Z135/Y135)/LN(AB135/AA135))) -> 5577.2079 | AD135: =IF($K135=100,Home_Data!$B$67,IF($K135=500,Home_Data!$B$69,Home_Data!$B$68)) -> 0.991 | AE135: =IF($J135<=Home_Data!$B$61,Home_Data!$B$64,IF($J135>=Home_Data!$B$63,Home_Data!$B$66,IF($J135<=Home_Data!$B$62,Home_Data!$B$64+(Home_Data!$B$65-Home_Data!$B$64)*(LN($J135)-LN(Home_Data!$B$61))/(LN(Home_Data!$B$62)-LN(Home_Data!$B$61)),Home_Data!$B$65+(Home_Data!$B$66-Home_Data!$B$65)*(LN($J135)-LN(Home_Data!$B$62))/(LN(Home_Data!$B$63)-LN(Home_Data!$B$62))))) -> 1 | AF135: =IF($E135>=20,Home_Data!$B$80,IF($E135>=10,Home_Data!$B$79,1)) -> 1 | AG135: =IF($D135<1960,Home_Data!$B$81,IF($D135<1980,Home_Data!$B$82,IF($D135>=2000,Home_Data!$B$83,1))) -> 1.08 | AH135: =IF($F135="brick",Home_Data!$B$78,1) -> 0.98 | AI135: =IF($G135="rental",Home_Data!$B$84,IF($G135="vacation",Home_Data!$B$85,1)) -> 1 | AJ135: =INDEX(Home_Data!$B$70:$B$73,MIN(3,MAX(0,$H135))+1) -> 1 | AK135: =IF(INDEX(Home_Data!$H$5:$H$56,V135)="Yes",1,IF($L135="poor",Home_Data!$B$74,IF($L135="fair",Home_Data!$B$75,IF($L135="excellent",Home_Data!$B$77,Home_Data!$B$76)))) -> 1 | AL135: =IF(($N135=1),Home_Data!$B$86,1)*IF(($O135=1),Home_Data!$B$87,1)*IF(($P135=1),Home_Data!$B$88,1) -> 1 | AM135: =AC135*AD135*AE135*AF135*AG135*AH135*AI135*AJ135*AK135*AL135 -> 5849.7906 | AN135: =AM135*EXP(-Car_Data!$B$123*Home_Data!$B$91) -> 4260.539 | AO135: =AM135*EXP(Car_Data!$B$123*Home_Data!$B$91) -> 8031.8593 | AP135: =IF($U135>0,IF(AND($U135>=AN135,$U135<=AO135),1,0),"") | AQ135: =IF($U135>0,$U135/AM135-1,"")
A136: CA-1009 | B136: CA | C136: 1500 | D136: 2007 | E136: 15 | F136: brick | G136: own | H136: 2 | I136: 320000 | J136: 5000 | K136: 300 | M136: 0 | N136: 0 | O136: 0 | P136: 0 | Q136: 1 | R136: earthquake region | V136: =MATCH($B136,Home_Data!$B$5:$B$56,0) -> 5 | W136: =MIN(MAX($I136,50000),3000000) -> 320000 | X136: =IFERROR(MIN(3,MAX(1,MATCH(W136,Home_Data!$C$4:$F$4,1))),1) -> 2 | Y136: =INDEX(Home_Data!$C$5:$F$56,V136,X136) -> 1653 | Z136: =INDEX(Home_Data!$C$5:$F$56,V136,X136+1) -> 2090 | AA136: =INDEX(Home_Data!$C$4:$F$4,X136) -> 300000 | AB136: =INDEX(Home_Data!$C$4:$F$4,X136+1) -> 400000 | AC136: =IF($I136<200000,INDEX(Home_Data!$C$5:$F$56,V136,1)*(MAX($I136,Home_Data!$B$90)/200000)^Home_Data!$B$89,Y136*(W136/AA136)^(LN(Z136/Y136)/LN(AB136/AA136))) -> 1742.3168 | AD136: =IF($K136=100,Home_Data!$B$67,IF($K136=500,Home_Data!$B$69,Home_Data!$B$68)) -> 1 | AE136: =IF($J136<=Home_Data!$B$61,Home_Data!$B$64,IF($J136>=Home_Data!$B$63,Home_Data!$B$66,IF($J136<=Home_Data!$B$62,Home_Data!$B$64+(Home_Data!$B$65-Home_Data!$B$64)*(LN($J136)-LN(Home_Data!$B$61))/(LN(Home_Data!$B$62)-LN(Home_Data!$B$61)),Home_Data!$B$65+(Home_Data!$B$66-Home_Data!$B$65)*(LN($J136)-LN(Home_Data!$B$62))/(LN(Home_Data!$B$63)-LN(Home_Data!$B$62))))) -> 0.84 | AF136: =IF($E136>=20,Home_Data!$B$80,IF($E136>=10,Home_Data!$B$79,1)) -> 1.1 | AG136: =IF($D136<1960,Home_Data!$B$81,IF($D136<1980,Home_Data!$B$82,IF($D136>=2000,Home_Data!$B$83,1))) -> 0.95 | AH136: =IF($F136="brick",Home_Data!$B$78,1) -> 0.98 | AI136: =IF($G136="rental",Home_Data!$B$84,IF($G136="vacation",Home_Data!$B$85,1)) -> 1 | AJ136: =INDEX(Home_Data!$B$70:$B$73,MIN(3,MAX(0,$H136))+1) -> 1.29 | AK136: =IF(INDEX(Home_Data!$H$5:$H$56,V136)="Yes",1,IF($L136="poor",Home_Data!$B$74,IF($L136="fair",Home_Data!$B$75,IF($L136="excellent",Home_Data!$B$77,Home_Data!$B$76)))) -> 1 | AL136: =IF(($N136=1),Home_Data!$B$86,1)*IF(($O136=1),Home_Data!$B$87,1)*IF(($P136=1),Home_Data!$B$88,1) -> 1 | AM136: =AC136*AD136*AE136*AF136*AG136*AH136*AI136*AJ136*AK136*AL136 -> 1933.4746 | AN136: =AM136*EXP(-Car_Data!$B$123*Home_Data!$B$91) -> 1408.1947 | AO136: =AM136*EXP(Car_Data!$B$123*Home_Data!$B$91) -> 2654.6927 | AP136: =IF($U136>0,IF(AND($U136>=AN136,$U136<=AO136),1,0),"") | AQ136: =IF($U136>0,$U136/AM136-1,"")
A137: CA-1010 | B137: CA | C137: 1800 | D137: 2011 | E137: 0 | F137: frame | G137: own | H137: 0 | I137: 475000 | J137: 1000 | K137: 500 | M137: 0 | N137: 0 | O137: 0 | P137: 0 | Q137: 1 | R137: earthquake region | V137: =MATCH($B137,Home_Data!$B$5:$B$56,0) -> 5 | W137: =MIN(MAX($I137,50000),3000000) -> 475000 | X137: =IFERROR(MIN(3,MAX(1,MATCH(W137,Home_Data!$C$4:$F$4,1))),1) -> 3 | Y137: =INDEX(Home_Data!$C$5:$F$56,V137,X137) -> 2090 | Z137: =INDEX(Home_Data!$C$5:$F$56,V137,X137+1) -> 3092 | AA137: =INDEX(Home_Data!$C$4:$F$4,X137) -> 400000 | AB137: =INDEX(Home_Data!$C$4:$F$4,X137+1) -> 600000 | AC137: =IF($I137<200000,INDEX(Home_Data!$C$5:$F$56,V137,1)*(MAX($I137,Home_Data!$B$90)/200000)^Home_Data!$B$89,Y137*(W137/AA137)^(LN(Z137/Y137)/LN(AB137/AA137))) -> 2467.3895 | AD137: =IF($K137=100,Home_Data!$B$67,IF($K137=500,Home_Data!$B$69,Home_Data!$B$68)) -> 1.005 | AE137: =IF($J137<=Home_Data!$B$61,Home_Data!$B$64,IF($J137>=Home_Data!$B$63,Home_Data!$B$66,IF($J137<=Home_Data!$B$62,Home_Data!$B$64+(Home_Data!$B$65-Home_Data!$B$64)*(LN($J137)-LN(Home_Data!$B$61))/(LN(Home_Data!$B$62)-LN(Home_Data!$B$61)),Home_Data!$B$65+(Home_Data!$B$66-Home_Data!$B$65)*(LN($J137)-LN(Home_Data!$B$62))/(LN(Home_Data!$B$63)-LN(Home_Data!$B$62))))) -> 1 | AF137: =IF($E137>=20,Home_Data!$B$80,IF($E137>=10,Home_Data!$B$79,1)) -> 1 | AG137: =IF($D137<1960,Home_Data!$B$81,IF($D137<1980,Home_Data!$B$82,IF($D137>=2000,Home_Data!$B$83,1))) -> 0.95 | AH137: =IF($F137="brick",Home_Data!$B$78,1) -> 1 | AI137: =IF($G137="rental",Home_Data!$B$84,IF($G137="vacation",Home_Data!$B$85,1)) -> 1 | AJ137: =INDEX(Home_Data!$B$70:$B$73,MIN(3,MAX(0,$H137))+1) -> 1 | AK137: =IF(INDEX(Home_Data!$H$5:$H$56,V137)="Yes",1,IF($L137="poor",Home_Data!$B$74,IF($L137="fair",Home_Data!$B$75,IF($L137="excellent",Home_Data!$B$77,Home_Data!$B$76)))) -> 1 | AL137: =IF(($N137=1),Home_Data!$B$86,1)*IF(($O137=1),Home_Data!$B$87,1)*IF(($P137=1),Home_Data!$B$88,1) -> 1 | AM137: =AC137*AD137*AE137*AF137*AG137*AH137*AI137*AJ137*AK137*AL137 -> 2355.7402 | AN137: =AM137*EXP(-Car_Data!$B$123*Home_Data!$B$91) -> 1715.7405 | AO137: =AM137*EXP(Car_Data!$B$123*Home_Data!$B$91) -> 3234.4702 | AP137: =IF($U137>0,IF(AND($U137>=AN137,$U137<=AO137),1,0),"") | AQ137: =IF($U137>0,$U137/AM137-1,"")
A138: CA-1011 | B138: CA | C138: 1200 | D138: 1985 | E138: 5 | F138: frame | G138: own | H138: 1 | I138: 260000 | J138: 2500 | K138: 500 | M138: 0 | N138: 0 | O138: 0 | P138: 0 | Q138: 0 | R138: inland, no special hazard | V138: =MATCH($B138,Home_Data!$B$5:$B$56,0) -> 5 | W138: =MIN(MAX($I138,50000),3000000) -> 260000 | X138: =IFERROR(MIN(3,MAX(1,MATCH(W138,Home_Data!$C$4:$F$4,1))),1) -> 1 | Y138: =INDEX(Home_Data!$C$5:$F$56,V138,X138) -> 1244 | Z138: =INDEX(Home_Data!$C$5:$F$56,V138,X138+1) -> 1653 | AA138: =INDEX(Home_Data!$C$4:$F$4,X138) -> 200000 | AB138: =INDEX(Home_Data!$C$4:$F$4,X138+1) -> 300000 | AC138: =IF($I138<200000,INDEX(Home_Data!$C$5:$F$56,V138,1)*(MAX($I138,Home_Data!$B$90)/200000)^Home_Data!$B$89,Y138*(W138/AA138)^(LN(Z138/Y138)/LN(AB138/AA138))) -> 1495.2119 | AD138: =IF($K138=100,Home_Data!$B$67,IF($K138=500,Home_Data!$B$69,Home_Data!$B$68)) -> 1.005 | AE138: =IF($J138<=Home_Data!$B$61,Home_Data!$B$64,IF($J138>=Home_Data!$B$63,Home_Data!$B$66,IF($J138<=Home_Data!$B$62,Home_Data!$B$64+(Home_Data!$B$65-Home_Data!$B$64)*(LN($J138)-LN(Home_Data!$B$61))/(LN(Home_Data!$B$62)-LN(Home_Data!$B$61)),Home_Data!$B$65+(Home_Data!$B$66-Home_Data!$B$65)*(LN($J138)-LN(Home_Data!$B$62))/(LN(Home_Data!$B$63)-LN(Home_Data!$B$62))))) -> 0.91 | AF138: =IF($E138>=20,Home_Data!$B$80,IF($E138>=10,Home_Data!$B$79,1)) -> 1 | AG138: =IF($D138<1960,Home_Data!$B$81,IF($D138<1980,Home_Data!$B$82,IF($D138>=2000,Home_Data!$B$83,1))) -> 1 | AH138: =IF($F138="brick",Home_Data!$B$78,1) -> 1 | AI138: =IF($G138="rental",Home_Data!$B$84,IF($G138="vacation",Home_Data!$B$85,1)) -> 1 | AJ138: =INDEX(Home_Data!$B$70:$B$73,MIN(3,MAX(0,$H138))+1) -> 1.16 | AK138: =IF(INDEX(Home_Data!$H$5:$H$56,V138)="Yes",1,IF($L138="poor",Home_Data!$B$74,IF($L138="fair",Home_Data!$B$75,IF($L138="excellent",Home_Data!$B$77,Home_Data!$B$76)))) -> 1 | AL138: =IF(($N138=1),Home_Data!$B$86,1)*IF(($O138=1),Home_Data!$B$87,1)*IF(($P138=1),Home_Data!$B$88,1) -> 1 | AM138: =AC138*AD138*AE138*AF138*AG138*AH138*AI138*AJ138*AK138*AL138 -> 1586.2375 | AN138: =AM138*EXP(-Car_Data!$B$123*Home_Data!$B$91) -> 1155.2938 | AO138: =AM138*EXP(Car_Data!$B$123*Home_Data!$B$91) -> 2177.9303 | AP138: =IF($U138>0,IF(AND($U138>=AN138,$U138<=AO138),1,0),"") | AQ138: =IF($U138>0,$U138/AM138-1,"")
A139: CA-1012 | B139: CA | C139: 3150 | D139: 1968 | E139: 24 | F139: frame | G139: own | H139: 0 | I139: 845000 | J139: 5000 | K139: 300 | M139: 0 | N139: 0 | O139: 1 | P139: 0 | Q139: 1 | R139: wildfire-exposed area; earthquake region | V139: =MATCH($B139,Home_Data!$B$5:$B$56,0) -> 5 | W139: =MIN(MAX($I139,50000),3000000) -> 845000 | X139: =IFERROR(MIN(3,MAX(1,MATCH(W139,Home_Data!$C$4:$F$4,1))),1) -> 3 | Y139: =INDEX(Home_Data!$C$5:$F$56,V139,X139) -> 2090 | Z139: =INDEX(Home_Data!$C$5:$F$56,V139,X139+1) -> 3092 | AA139: =INDEX(Home_Data!$C$4:$F$4,X139) -> 400000 | AB139: =INDEX(Home_Data!$C$4:$F$4,X139+1) -> 600000 | AC139: =IF($I139<200000,INDEX(Home_Data!$C$5:$F$56,V139,1)*(MAX($I139,Home_Data!$B$90)/200000)^Home_Data!$B$89,Y139*(W139/AA139)^(LN(Z139/Y139)/LN(AB139/AA139))) -> 4304.0738 | AD139: =IF($K139=100,Home_Data!$B$67,IF($K139=500,Home_Data!$B$69,Home_Data!$B$68)) -> 1 | AE139: =IF($J139<=Home_Data!$B$61,Home_Data!$B$64,IF($J139>=Home_Data!$B$63,Home_Data!$B$66,IF($J139<=Home_Data!$B$62,Home_Data!$B$64+(Home_Data!$B$65-Home_Data!$B$64)*(LN($J139)-LN(Home_Data!$B$61))/(LN(Home_Data!$B$62)-LN(Home_Data!$B$61)),Home_Data!$B$65+(Home_Data!$B$66-Home_Data!$B$65)*(LN($J139)-LN(Home_Data!$B$62))/(LN(Home_Data!$B$63)-LN(Home_Data!$B$62))))) -> 0.84 | AF139: =IF($E139>=20,Home_Data!$B$80,IF($E139>=10,Home_Data!$B$79,1)) -> 1.3 | AG139: =IF($D139<1960,Home_Data!$B$81,IF($D139<1980,Home_Data!$B$82,IF($D139>=2000,Home_Data!$B$83,1))) -> 1.08 | AH139: =IF($F139="brick",Home_Data!$B$78,1) -> 1 | AI139: =IF($G139="rental",Home_Data!$B$84,IF($G139="vacation",Home_Data!$B$85,1)) -> 1 | AJ139: =INDEX(Home_Data!$B$70:$B$73,MIN(3,MAX(0,$H139))+1) -> 1 | AK139: =IF(INDEX(Home_Data!$H$5:$H$56,V139)="Yes",1,IF($L139="poor",Home_Data!$B$74,IF($L139="fair",Home_Data!$B$75,IF($L139="excellent",Home_Data!$B$77,Home_Data!$B$76)))) -> 1 | AL139: =IF(($N139=1),Home_Data!$B$86,1)*IF(($O139=1),Home_Data!$B$87,1)*IF(($P139=1),Home_Data!$B$88,1) -> 1.15 | AM139: =AC139*AD139*AE139*AF139*AG139*AH139*AI139*AJ139*AK139*AL139 -> 5837.4603 | AN139: =AM139*EXP(-Car_Data!$B$123*Home_Data!$B$91) -> 4251.5586 | AO139: =AM139*EXP(Car_Data!$B$123*Home_Data!$B$91) -> 8014.9296 | AP139: =IF($U139>0,IF(AND($U139>=AN139,$U139<=AO139),1,0),"") | AQ139: =IF($U139>0,$U139/AM139-1,"")
... A187: CA-1060 | B187: CA | C187: 1250 | D187: 2020 | E187: 5 | F187: frame | G187: own | H187: 0 | I187: 275000 | J187: 1000 | K187: 300 | M187: 0 | N187: 0 | O187: 0 | P187: 0 | Q187: 0 | R187: inland, no special hazard | V187: =MATCH($B187,Home_Data!$B$5:$B$56,0) -> 5 | W187: =MIN(MAX($I187,50000),3000000) -> 275000 | X187: =IFERROR(MIN(3,MAX(1,MATCH(W187,Home_Data!$C$4:$F$4,1))),1) -> 1 | Y187: =INDEX(Home_Data!$C$5:$F$56,V187,X187) -> 1244 | Z187: =INDEX(Home_Data!$C$5:$F$56,V187,X187+1) -> 1653 | AA187: =INDEX(Home_Data!$C$4:$F$4,X187) -> 200000 | AB187: =INDEX(Home_Data!$C$4:$F$4,X187+1) -> 300000 | AC187: =IF($I187<200000,INDEX(Home_Data!$C$5:$F$56,V187,1)*(MAX($I187,Home_Data!$B$90)/200000)^Home_Data!$B$89,Y187*(W187/AA187)^(LN(Z187/Y187)/LN(AB187/AA187))) -> 1555.179 | AD187: =IF($K187=100,Home_Data!$B$67,IF($K187=500,Home_Data!$B$69,Home_Data!$B$68)) -> 1 | AE187: =IF($J187<=Home_Data!$B$61,Home_Data!$B$64,IF($J187>=Home_Data!$B$63,Home_Data!$B$66,IF($J187<=Home_Data!$B$62,Home_Data!$B$64+(Home_Data!$B$65-Home_Data!$B$64)*(LN($J187)-LN(Home_Data!$B$61))/(LN(Home_Data!$B$62)-LN(Home_Data!$B$61)),Home_Data!$B$65+(Home_Data!$B$66-Home_Data!$B$65)*(LN($J187)-LN(Home_Data!$B$62))/(LN(Home_Data!$B$63)-LN(Home_Data!$B$62))))) -> 1 | AF187: =IF($E187>=20,Home_Data!$B$80,IF($E187>=10,Home_Data!$B$79,1)) -> 1 | AG187: =IF($D187<1960,Home_Data!$B$81,IF($D187<1980,Home_Data!$B$82,IF($D187>=2000,Home_Data!$B$83,1))) -> 0.95 | AH187: =IF($F187="brick",Home_Data!$B$78,1) -> 1 | AI187: =IF($G187="rental",Home_Data!$B$84,IF($G187="vacation",Home_Data!$B$85,1)) -> 1 | AJ187: =INDEX(Home_Data!$B$70:$B$73,MIN(3,MAX(0,$H187))+1) -> 1 | AK187: =IF(INDEX(Home_Data!$H$5:$H$56,V187)="Yes",1,IF($L187="poor",Home_Data!$B$74,IF($L187="fair",Home_Data!$B$75,IF($L187="excellent",Home_Data!$B$77,Home_Data!$B$76)))) -> 1 | AL187: =IF(($N187=1),Home_Data!$B$86,1)*IF(($O187=1),Home_Data!$B$87,1)*IF(($P187=1),Home_Data!$B$88,1) -> 1 | AM187: =AC187*AD187*AE187*AF187*AG187*AH187*AI187*AJ187*AK187*AL187 -> 1477.4201 | AN187: =AM187*EXP(-Car_Data!$B$123*Home_Data!$B$91) -> 1076.0395 | AO187: =AM187*EXP(Car_Data!$B$123*Home_Data!$B$91) -> 2028.5222 | AP187: =IF($U187>0,IF(AND($U187>=AN187,$U187<=AO187),1,0),"") | AQ187: =IF($U187>0,$U187/AM187-1,"")

Sheet Quote_Test
A1: Quote test: how well does the model match your real quotes?
A2: Reads the Quote_Requests sheet. Nothing to enter here. Results appear as soon as prices are entered there.
A4: Measure | B4: Value
A5: Quotes entered | B5: =COUNT(Quote_Requests!$U$8:$U$2008) -> 0
A6: Inside the model's range (target 80% or more) | B6: =IF(B5=0,"",SUMIF(Quote_Requests!$AP$8:$AP$2008,1)/B5)
A7: Median error (target 15% or less) | B7: {=IF(B5=0,"",MEDIAN(IF(Quote_Requests!$U$8:$U$2008>0,ABS(Quote_Requests!$U$8:$U$2008/Quote_Requests!$AM$8:$AM$2008-1))))}
A8: Average bias (positive = real prices higher than the model) | B8: =IF(B5=0,"",AVERAGE(Quote_Requests!$AQ$8:$AQ$2008))
A9: 90th percentile error | B9: {=IF(B5=0,"",PERCENTILE(IF(Quote_Requests!$U$8:$U$2008>0,ABS(Quote_Requests!$U$8:$U$2008/Quote_Requests!$AM$8:$AM$2008-1)),0.9))}
A11: Verdict | B11: =IF(B5=0,"No quotes entered yet",IF(B5<30,"Too few quotes to judge (need 50 to 100 per state)",IF(AND(B6>=0.8,B7<=0.15),"Meets both targets","Does not meet the targets"))) -> No quotes entered yet
A13: By state
A14: State | B14: Quotes | C14: Inside range | D14: Median price / model | E14: Suggested change to the state price level
A15: TX | B15: =COUNTIFS(Quote_Requests!$B$8:$B$2008,A15,Quote_Requests!$U$8:$U$2008,">0") -> 0 | C15: =IF(B15=0,"",SUMIFS(Quote_Requests!$AP$8:$AP$2008,Quote_Requests!$B$8:$B$2008,A15)/B15) | D15: {=IF(B15<10,"",MEDIAN(IF((Quote_Requests!$B$8:$B$2008=A15)*(Quote_Requests!$U$8:$U$2008>0),Quote_Requests!$U$8:$U$2008/Quote_Requests!$AM$8:$AM$2008)))} | E15: =IF(D15="","Fewer than 10 quotes: no suggestion",IF(ABS(D15-1)>0.1,"Multiply this state's price level by "&TEXT(D15,"0.00"),"Within 10%: no change needed")) -> Fewer than 10 quotes: no suggestion
A16: FL | B16: =COUNTIFS(Quote_Requests!$B$8:$B$2008,A16,Quote_Requests!$U$8:$U$2008,">0") -> 0 | C16: =IF(B16=0,"",SUMIFS(Quote_Requests!$AP$8:$AP$2008,Quote_Requests!$B$8:$B$2008,A16)/B16) | D16: {=IF(B16<10,"",MEDIAN(IF((Quote_Requests!$B$8:$B$2008=A16)*(Quote_Requests!$U$8:$U$2008>0),Quote_Requests!$U$8:$U$2008/Quote_Requests!$AM$8:$AM$2008)))} | E16: =IF(D16="","Fewer than 10 quotes: no suggestion",IF(ABS(D16-1)>0.1,"Multiply this state's price level by "&TEXT(D16,"0.00"),"Within 10%: no change needed")) -> Fewer than 10 quotes: no suggestion
A17: CA | B17: =COUNTIFS(Quote_Requests!$B$8:$B$2008,A17,Quote_Requests!$U$8:$U$2008,">0") -> 0 | C17: =IF(B17=0,"",SUMIFS(Quote_Requests!$AP$8:$AP$2008,Quote_Requests!$B$8:$B$2008,A17)/B17) | D17: {=IF(B17<10,"",MEDIAN(IF((Quote_Requests!$B$8:$B$2008=A17)*(Quote_Requests!$U$8:$U$2008>0),Quote_Requests!$U$8:$U$2008/Quote_Requests!$AM$8:$AM$2008)))} | E17: =IF(D17="","Fewer than 10 quotes: no suggestion",IF(ABS(D17-1)>0.1,"Multiply this state's price level by "&TEXT(D17,"0.00"),"Within 10%: no change needed")) -> Fewer than 10 quotes: no suggestion
A19: Notes
A20: Targets are starting points from the project plan, not industry standards; agree them with an actuary.
A21: Do not tune the model on the same quotes you use to prove it works. Hold back about a third of the profiles for the final test.
A22: The web tool's Test tab also compares insurers per profile and suggests a range width.
A23: Quotes must be for identical coverage and gathered about the same day. Declined quotes: leave the price blank and note it.

Sheet OK_Benchmark
A1: Model vs. official Oklahoma insurer prices
A2: Official median = median annual premium across insurers (and cities and genders for cars). The model is set to Oklahoma with the assumptions shown. Workings are to the right.
H3: Workings: car (Oklahoma; car worth $12,000; minimum liability; full own-car cover, $500 deductibles; clean record; no credit answer)
A4: Profile | B4: Official median insurer ($) | C4: Model estimate ($) | D4: Model / official | E4: Reading | H4: State row | I4: Published state median ($) | J4: Liability share | K4: Own-car cover share | L4: Vehicle value factor | M4: Deductible factor | N4: Area factor (full cover only) | O4: Cover factor (liability + own-car) | P4: Age table position | Q4: Age multiple | R4: Inexperience multiple | S4: Accident multiple | T4: Ticket multiple | U4: DUI multiple | V4: Mileage multiple | W4: Use multiple | X4: Credit multiple (1.00 where banned) | Y4: Estimate before rounding ($)
A5: Car: 16, single, drives to school | B5: {=MEDIAN(IF((OK_Official_Data!$A$4:$A$1803="auto")*(OK_Official_Data!$D$4:$D$1803="scenario A (age 16)"),OK_Official_Data!$H$4:$H$1803))} -> 6694 | C5: =Y5 -> 7325.402 | D5: =C5/B5 -> 1.0943236 | E5: =IF(D5<0.8,"Model low",IF(D5>1.25,"Model high","Within 20% / 25% of the median insurer")) -> Within 20% / 25% of the median insurer | H5: =MATCH("OK",Car_Data!$B$5:$B$56,0) -> 36 | I5: =INDEX(Car_Data!$C$5:$C$56,H5) -> 2192 | J5: =INDEX(Car_Data!$B$100:$B$103,MATCH("min",Car_Data!$A$100:$A$103,0)) -> 0.26 | K5: =INDEX(Car_Data!$B$104:$B$106,MATCH("full",Car_Data!$A$104:$A$106,0)) -> 0.64 | L5: =IF(K5=0,1,MIN(Car_Data!$B$121,MAX(Car_Data!$B$120,(MAX(12000,1000)/Car_Data!$B$118)^Car_Data!$B$119))) -> 0.74558385 | M5: =IF(K5=0,1,IF(500<=500,Car_Data!$B$113,IF(500>=2000,Car_Data!$B$114,1))) -> 1.146789 | N5: =IF("full"="full",1+IF(FALSE(),Car_Data!$B$115,0)+IF(FALSE(),Car_Data!$B$116,0)+IF(FALSE(),Car_Data!$B$117,0),1) -> 1 | O5: =J5+K5*L5*M5*N5 -> 0.80721751 | P5: =IFERROR(MATCH(16,Car_Data!$A$61:$A$74,1),1) -> 1 | Q5: =IF(P5>=ROWS(Car_Data!$A$61:$A$74),INDEX(Car_Data!$B$61:$B$74,ROWS(Car_Data!$A$61:$A$74)),INDEX(Car_Data!$B$61:$B$74,P5)+(INDEX(Car_Data!$B$61:$B$74,P5+1)-INDEX(Car_Data!$B$61:$B$74,P5))*(16-INDEX(Car_Data!$A$61:$A$74,P5))/(INDEX(Car_Data!$A$61:$A$74,P5+1)-INDEX(Car_Data!$A$61:$A$74,P5))) -> 3.6 | R5: =IF(0<2,Car_Data!$B$95,1) -> 1.15 | S5: =INDEX(Car_Data!$B$79:$B$82,MIN(3,MAX(0,0))+1) -> 1 | T5: =INDEX(Car_Data!$B$83:$B$86,MIN(3,MAX(0,0))+1) -> 1 | U5: =IF(FALSE(),Car_Data!$B$87,1) -> 1 | V5: =IF("mid"="high",Car_Data!$B$92,1) -> 1 | W5: =IF("personal"="commercial",Car_Data!$B$94,IF("personal"="business",Car_Data!$B$93,1)) -> 1 | X5: =IF(INDEX(Car_Data!$E$5:$E$56,H5)="Yes",1,IF(""="poor",Car_Data!$B$88,IF(""="fair",Car_Data!$B$89,IF(""="excellent",Car_Data!$B$91,Car_Data!$B$90)))) -> 1 | Y5: =I5*O5*Q5*R5*S5*T5*U5*V5*W5*X5 -> 7325.402
A6: Car: 21, single, commutes | B6: {=MEDIAN(IF((OK_Official_Data!$A$4:$A$1803="auto")*(OK_Official_Data!$D$4:$D$1803="scenario B (age 21)"),OK_Official_Data!$H$4:$H$1803))} -> 3084 | C6: =Y6 -> 3347.7441 | D6: =C6/B6 -> 1.0855201 | E6: =IF(D6<0.8,"Model low",IF(D6>1.25,"Model high","Within 20% / 25% of the median insurer")) -> Within 20% / 25% of the median insurer | H6: =MATCH("OK",Car_Data!$B$5:$B$56,0) -> 36 | I6: =INDEX(Car_Data!$C$5:$C$56,H6) -> 2192 | J6: =INDEX(Car_Data!$B$100:$B$103,MATCH("min",Car_Data!$A$100:$A$103,0)) -> 0.26 | K6: =INDEX(Car_Data!$B$104:$B$106,MATCH("full",Car_Data!$A$104:$A$106,0)) -> 0.64 | L6: =IF(K6=0,1,MIN(Car_Data!$B$121,MAX(Car_Data!$B$120,(MAX(12000,1000)/Car_Data!$B$118)^Car_Data!$B$119))) -> 0.74558385 | M6: =IF(K6=0,1,IF(500<=500,Car_Data!$B$113,IF(500>=2000,Car_Data!$B$114,1))) -> 1.146789 | N6: =IF("full"="full",1+IF(FALSE(),Car_Data!$B$115,0)+IF(FALSE(),Car_Data!$B$116,0)+IF(FALSE(),Car_Data!$B$117,0),1) -> 1 | O6: =J6+K6*L6*M6*N6 -> 0.80721751 | P6: =IFERROR(MATCH(21,Car_Data!$A$61:$A$74,1),1) -> 3 | Q6: =IF(P6>=ROWS(Car_Data!$A$61:$A$74),INDEX(Car_Data!$B$61:$B$74,ROWS(Car_Data!$A$61:$A$74)),INDEX(Car_Data!$B$61:$B$74,P6)+(INDEX(Car_Data!$B$61:$B$74,P6+1)-INDEX(Car_Data!$B$61:$B$74,P6))*(21-INDEX(Car_Data!$A$61:$A$74,P6))/(INDEX(Car_Data!$A$61:$A$74,P6+1)-INDEX(Car_Data!$A$61:$A$74,P6))) -> 1.892 | R6: =IF(3<2,Car_Data!$B$95,1) -> 1 | S6: =INDEX(Car_Data!$B$79:$B$82,MIN(3,MAX(0,0))+1) -> 1 | T6: =INDEX(Car_Data!$B$83:$B$86,MIN(3,MAX(0,0))+1) -> 1 | U6: =IF(FALSE(),Car_Data!$B$87,1) -> 1 | V6: =IF("mid"="high",Car_Data!$B$92,1) -> 1 | W6: =IF("personal"="commercial",Car_Data!$B$94,IF("personal"="business",Car_Data!$B$93,1)) -> 1 | X6: =IF(INDEX(Car_Data!$E$5:$E$56,H6)="Yes",1,IF(""="poor",Car_Data!$B$88,IF(""="fair",Car_Data!$B$89,IF(""="excellent",Car_Data!$B$91,Car_Data!$B$90)))) -> 1 | Y6: =I6*O6*Q6*R6*S6*T6*U6*V6*W6*X6 -> 3347.7441
A7: Car: 36, married, commutes | B7: {=MEDIAN(IF((OK_Official_Data!$A$4:$A$1803="auto")*(OK_Official_Data!$D$4:$D$1803="scenario C (age 36)"),OK_Official_Data!$H$4:$H$1803))} -> 1879 | C7: =Y7 -> 1764.1125 | D7: =C7/B7 -> 0.93885711 | E7: =IF(D7<0.8,"Model low",IF(D7>1.25,"Model high","Within 20% / 25% of the median insurer")) -> Within 20% / 25% of the median insurer | H7: =MATCH("OK",Car_Data!$B$5:$B$56,0) -> 36 | I7: =INDEX(Car_Data!$C$5:$C$56,H7) -> 2192 | J7: =INDEX(Car_Data!$B$100:$B$103,MATCH("min",Car_Data!$A$100:$A$103,0)) -> 0.26 | K7: =INDEX(Car_Data!$B$104:$B$106,MATCH("full",Car_Data!$A$104:$A$106,0)) -> 0.64 | L7: =IF(K7=0,1,MIN(Car_Data!$B$121,MAX(Car_Data!$B$120,(MAX(12000,1000)/Car_Data!$B$118)^Car_Data!$B$119))) -> 0.74558385 | M7: =IF(K7=0,1,IF(500<=500,Car_Data!$B$113,IF(500>=2000,Car_Data!$B$114,1))) -> 1.146789 | N7: =IF("full"="full",1+IF(FALSE(),Car_Data!$B$115,0)+IF(FALSE(),Car_Data!$B$116,0)+IF(FALSE(),Car_Data!$B$117,0),1) -> 1 | O7: =J7+K7*L7*M7*N7 -> 0.80721751 | P7: =IFERROR(MATCH(36,Car_Data!$A$61:$A$74,1),1) -> 6 | Q7: =IF(P7>=ROWS(Car_Data!$A$61:$A$74),INDEX(Car_Data!$B$61:$B$74,ROWS(Car_Data!$A$61:$A$74)),INDEX(Car_Data!$B$61:$B$74,P7)+(INDEX(Car_Data!$B$61:$B$74,P7+1)-INDEX(Car_Data!$B$61:$B$74,P7))*(36-INDEX(Car_Data!$A$61:$A$74,P7))/(INDEX(Car_Data!$A$61:$A$74,P7+1)-INDEX(Car_Data!$A$61:$A$74,P7))) -> 0.997 | R7: =IF(18<2,Car_Data!$B$95,1) -> 1 | S7: =INDEX(Car_Data!$B$79:$B$82,MIN(3,MAX(0,0))+1) -> 1 | T7: =INDEX(Car_Data!$B$83:$B$86,MIN(3,MAX(0,0))+1) -> 1 | U7: =IF(FALSE(),Car_Data!$B$87,1) -> 1 | V7: =IF("mid"="high",Car_Data!$B$92,1) -> 1 | W7: =IF("personal"="commercial",Car_Data!$B$94,IF("personal"="business",Car_Data!$B$93,1)) -> 1 | X7: =IF(INDEX(Car_Data!$E$5:$E$56,H7)="Yes",1,IF(""="poor",Car_Data!$B$88,IF(""="fair",Car_Data!$B$89,IF(""="excellent",Car_Data!$B$91,Car_Data!$B$90)))) -> 1 | Y7: =I7*O7*Q7*R7*S7*T7*U7*V7*W7*X7 -> 1764.1125
A8: Car: 55, married, commutes | B8: {=MEDIAN(IF((OK_Official_Data!$A$4:$A$1803="auto")*(OK_Official_Data!$D$4:$D$1803="scenario D (age 55)"),OK_Official_Data!$H$4:$H$1803))} -> 1601 | C8: =Y8 -> 1590.7093 | D8: =C8/B8 -> 0.99357232 | E8: =IF(D8<0.8,"Model low",IF(D8>1.25,"Model high","Within 20% / 25% of the median insurer")) -> Within 20% / 25% of the median insurer | H8: =MATCH("OK",Car_Data!$B$5:$B$56,0) -> 36 | I8: =INDEX(Car_Data!$C$5:$C$56,H8) -> 2192 | J8: =INDEX(Car_Data!$B$100:$B$103,MATCH("min",Car_Data!$A$100:$A$103,0)) -> 0.26 | K8: =INDEX(Car_Data!$B$104:$B$106,MATCH("full",Car_Data!$A$104:$A$106,0)) -> 0.64 | L8: =IF(K8=0,1,MIN(Car_Data!$B$121,MAX(Car_Data!$B$120,(MAX(12000,1000)/Car_Data!$B$118)^Car_Data!$B$119))) -> 0.74558385 | M8: =IF(K8=0,1,IF(500<=500,Car_Data!$B$113,IF(500>=2000,Car_Data!$B$114,1))) -> 1.146789 | N8: =IF("full"="full",1+IF(FALSE(),Car_Data!$B$115,0)+IF(FALSE(),Car_Data!$B$116,0)+IF(FALSE(),Car_Data!$B$117,0),1) -> 1 | O8: =J8+K8*L8*M8*N8 -> 0.80721751 | P8: =IFERROR(MATCH(55,Car_Data!$A$61:$A$74,1),1) -> 10 | Q8: =IF(P8>=ROWS(Car_Data!$A$61:$A$74),INDEX(Car_Data!$B$61:$B$74,ROWS(Car_Data!$A$61:$A$74)),INDEX(Car_Data!$B$61:$B$74,P8)+(INDEX(Car_Data!$B$61:$B$74,P8+1)-INDEX(Car_Data!$B$61:$B$74,P8))*(55-INDEX(Car_Data!$A$61:$A$74,P8))/(INDEX(Car_Data!$A$61:$A$74,P8+1)-INDEX(Car_Data!$A$61:$A$74,P8))) -> 0.899 | R8: =IF(37<2,Car_Data!$B$95,1) -> 1 | S8: =INDEX(Car_Data!$B$79:$B$82,MIN(3,MAX(0,0))+1) -> 1 | T8: =INDEX(Car_Data!$B$83:$B$86,MIN(3,MAX(0,0))+1) -> 1 | U8: =IF(FALSE(),Car_Data!$B$87,1) -> 1 | V8: =IF("mid"="high",Car_Data!$B$92,1) -> 1 | W8: =IF("personal"="commercial",Car_Data!$B$94,IF("personal"="business",Car_Data!$B$93,1)) -> 1 | X8: =IF(INDEX(Car_Data!$E$5:$E$56,H8)="Yes",1,IF(""="poor",Car_Data!$B$88,IF(""="fair",Car_Data!$B$89,IF(""="excellent",Car_Data!$B$91,Car_Data!$B$90)))) -> 1 | Y8: =I8*O8*Q8*R8*S8*T8*U8*V8*W8*X8 -> 1590.7093
A9: Car: 70, married, pleasure use | B9: {=MEDIAN(IF((OK_Official_Data!$A$4:$A$1803="auto")*(OK_Official_Data!$D$4:$D$1803="scenario E (age 70)"),OK_Official_Data!$H$4:$H$1803))} -> 1501 | C9: =Y9 -> 1500.4688 | D9: =C9/B9 -> 0.99964612 | E9: =IF(D9<0.8,"Model low",IF(D9>1.25,"Model high","Within 20% / 25% of the median insurer")) -> Within 20% / 25% of the median insurer | H9: =MATCH("OK",Car_Data!$B$5:$B$56,0) -> 36 | I9: =INDEX(Car_Data!$C$5:$C$56,H9) -> 2192 | J9: =INDEX(Car_Data!$B$100:$B$103,MATCH("min",Car_Data!$A$100:$A$103,0)) -> 0.26 | K9: =INDEX(Car_Data!$B$104:$B$106,MATCH("full",Car_Data!$A$104:$A$106,0)) -> 0.64 | L9: =IF(K9=0,1,MIN(Car_Data!$B$121,MAX(Car_Data!$B$120,(MAX(12000,1000)/Car_Data!$B$118)^Car_Data!$B$119))) -> 0.74558385 | M9: =IF(K9=0,1,IF(500<=500,Car_Data!$B$113,IF(500>=2000,Car_Data!$B$114,1))) -> 1.146789 | N9: =IF("full"="full",1+IF(FALSE(),Car_Data!$B$115,0)+IF(FALSE(),Car_Data!$B$116,0)+IF(FALSE(),Car_Data!$B$117,0),1) -> 1 | O9: =J9+K9*L9*M9*N9 -> 0.80721751 | P9: =IFERROR(MATCH(70,Car_Data!$A$61:$A$74,1),1) -> 13 | Q9: =IF(P9>=ROWS(Car_Data!$A$61:$A$74),INDEX(Car_Data!$B$61:$B$74,ROWS(Car_Data!$A$61:$A$74)),INDEX(Car_Data!$B$61:$B$74,P9)+(INDEX(Car_Data!$B$61:$B$74,P9+1)-INDEX(Car_Data!$B$61:$B$74,P9))*(70-INDEX(Car_Data!$A$61:$A$74,P9))/(INDEX(Car_Data!$A$61:$A$74,P9+1)-INDEX(Car_Data!$A$61:$A$74,P9))) -> 0.848 | R9: =IF(52<2,Car_Data!$B$95,1) -> 1 | S9: =INDEX(Car_Data!$B$79:$B$82,MIN(3,MAX(0,0))+1) -> 1 | T9: =INDEX(Car_Data!$B$83:$B$86,MIN(3,MAX(0,0))+1) -> 1 | U9: =IF(FALSE(),Car_Data!$B$87,1) -> 1 | V9: =IF("mid"="high",Car_Data!$B$92,1) -> 1 | W9: =IF("personal"="commercial",Car_Data!$B$94,IF("personal"="business",Car_Data!$B$93,1)) -> 1 | X9: =IF(INDEX(Car_Data!$E$5:$E$56,H9)="Yes",1,IF(""="poor",Car_Data!$B$88,IF(""="fair",Car_Data!$B$89,IF(""="excellent",Car_Data!$B$91,Car_Data!$B$90)))) -> 1 | Y9: =I9*O9*Q9*R9*S9*T9*U9*V9*W9*X9 -> 1500.4688
H11: Workings: home (Oklahoma; 1% deductible; $100,000 liability; roof 5 years; built 1990; no claims; no credit answer; no local-hazard flags)
A12: Profile | B12: Official median insurer ($) | C12: Model estimate ($) | D12: Model / official | E12: Reading | H12: State row | I12: Limit used for the curve ($) | J12: Curve segment | K12: State price at segment start ($) | L12: State price at segment end ($) | M12: Segment start limit ($) | N12: Segment end limit ($) | O12: State price at your house limit ($) | P12: Liability factor | Q12: Deductible factor | R12: Roof multiple | S12: House-age multiple | T12: Construction multiple | U12: Use multiple | V12: Claims multiple | W12: Credit multiple (1.00 where banned) | X12: Local-hazard multiple | Y12: Estimate before rounding ($)
A13: Home: $100K house cover, frame | B13: {=MEDIAN(IF((OK_Official_Data!$A$4:$A$1803="home")*(OK_Official_Data!$D$4:$D$1803="scenario 1 (dwelling $100,000, deductible 1%)")*(OK_Official_Data!$F$4:$F$1803="frame"),OK_Official_Data!$H$4:$H$1803))} -> 2615 | C13: =Y13 -> 2455.7335 | D13: =C13/B13 -> 0.93909504 | E13: =IF(D13<0.8,"Model low",IF(D13>1.25,"Model high","Within 20% / 25% of the median insurer")) -> Within 20% / 25% of the median insurer | H13: =MATCH("OK",Home_Data!$B$5:$B$56,0) -> 36 | I13: =MIN(MAX(100000,50000),3000000) -> 100000 | J13: =IFERROR(MIN(3,MAX(1,MATCH(I13,Home_Data!$C$4:$F$4,1))),1) -> 1 | K13: =INDEX(Home_Data!$C$5:$F$56,H13,J13) -> 3756 | L13: =INDEX(Home_Data!$C$5:$F$56,H13,J13+1) -> 5378 | M13: =INDEX(Home_Data!$C$4:$F$4,J13) -> 200000 | N13: =INDEX(Home_Data!$C$4:$F$4,J13+1) -> 300000 | O13: =IF(100000<200000,INDEX(Home_Data!$C$5:$F$56,H13,1)*(MAX(100000,Home_Data!$B$90)/200000)^Home_Data!$B$89,K13*(I13/M13)^(LN(L13/K13)/LN(N13/M13))) -> 2478.0359 | P13: =IF(100=100,Home_Data!$B$67,IF(100=500,Home_Data!$B$69,Home_Data!$B$68)) -> 0.991 | Q13: =IF(1000<=Home_Data!$B$61,Home_Data!$B$64,IF(1000>=Home_Data!$B$63,Home_Data!$B$66,IF(1000<=Home_Data!$B$62,Home_Data!$B$64+(Home_Data!$B$65-Home_Data!$B$64)*(LN(1000)-LN(Home_Data!$B$61))/(LN(Home_Data!$B$62)-LN(Home_Data!$B$61)),Home_Data!$B$65+(Home_Data!$B$66-Home_Data!$B$65)*(LN(1000)-LN(Home_Data!$B$62))/(LN(Home_Data!$B$63)-LN(Home_Data!$B$62))))) -> 1 | R13: =IF(5>=20,Home_Data!$B$80,IF(5>=10,Home_Data!$B$79,1)) -> 1 | S13: =IF(1990<1960,Home_Data!$B$81,IF(1990<1980,Home_Data!$B$82,IF(1990>=2000,Home_Data!$B$83,1))) -> 1 | T13: =IF("frame"="brick",Home_Data!$B$78,1) -> 1 | U13: =IF("own"="rental",Home_Data!$B$84,IF("own"="vacation",Home_Data!$B$85,1)) -> 1 | V13: =INDEX(Home_Data!$B$70:$B$73,MIN(3,MAX(0,0))+1) -> 1 | W13: =IF(INDEX(Home_Data!$H$5:$H$56,H13)="Yes",1,IF(""="poor",Home_Data!$B$74,IF(""="fair",Home_Data!$B$75,IF(""="excellent",Home_Data!$B$77,Home_Data!$B$76)))) -> 1 | X13: =IF(FALSE(),Home_Data!$B$86,1)*IF(FALSE(),Home_Data!$B$87,1)*IF(FALSE(),Home_Data!$B$88,1) -> 1 | Y13: =O13*P13*Q13*R13*S13*T13*U13*V13*W13*X13 -> 2455.7335
A14: Home: $200K house cover, frame | B14: {=MEDIAN(IF((OK_Official_Data!$A$4:$A$1803="home")*(OK_Official_Data!$D$4:$D$1803="scenario 2 (dwelling $200,000, deductible 1%)")*(OK_Official_Data!$F$4:$F$1803="frame"),OK_Official_Data!$H$4:$H$1803))} -> 3863 | C14: =Y14 -> 3468.7801 | D14: =C14/B14 -> 0.8979498 | E14: =IF(D14<0.8,"Model low",IF(D14>1.25,"Model high","Within 20% / 25% of the median insurer")) -> Within 20% / 25% of the median insurer | H14: =MATCH("OK",Home_Data!$B$5:$B$56,0) -> 36 | I14: =MIN(MAX(200000,50000),3000000) -> 200000 | J14: =IFERROR(MIN(3,MAX(1,MATCH(I14,Home_Data!$C$4:$F$4,1))),1) -> 1 | K14: =INDEX(Home_Data!$C$5:$F$56,H14,J14) -> 3756 | L14: =INDEX(Home_Data!$C$5:$F$56,H14,J14+1) -> 5378 | M14: =INDEX(Home_Data!$C$4:$F$4,J14) -> 200000 | N14: =INDEX(Home_Data!$C$4:$F$4,J14+1) -> 300000 | O14: =IF(200000<200000,INDEX(Home_Data!$C$5:$F$56,H14,1)*(MAX(200000,Home_Data!$B$90)/200000)^Home_Data!$B$89,K14*(I14/M14)^(LN(L14/K14)/LN(N14/M14))) -> 3756 | P14: =IF(100=100,Home_Data!$B$67,IF(100=500,Home_Data!$B$69,Home_Data!$B$68)) -> 0.991 | Q14: =IF(2000<=Home_Data!$B$61,Home_Data!$B$64,IF(2000>=Home_Data!$B$63,Home_Data!$B$66,IF(2000<=Home_Data!$B$62,Home_Data!$B$64+(Home_Data!$B$65-Home_Data!$B$64)*(LN(2000)-LN(Home_Data!$B$61))/(LN(Home_Data!$B$62)-LN(Home_Data!$B$61)),Home_Data!$B$65+(Home_Data!$B$66-Home_Data!$B$65)*(LN(2000)-LN(Home_Data!$B$62))/(LN(Home_Data!$B$63)-LN(Home_Data!$B$62))))) -> 0.93191763 | R14: =IF(5>=20,Home_Data!$B$80,IF(5>=10,Home_Data!$B$79,1)) -> 1 | S14: =IF(1990<1960,Home_Data!$B$81,IF(1990<1980,Home_Data!$B$82,IF(1990>=2000,Home_Data!$B$83,1))) -> 1 | T14: =IF("frame"="brick",Home_Data!$B$78,1) -> 1 | U14: =IF("own"="rental",Home_Data!$B$84,IF("own"="vacation",Home_Data!$B$85,1)) -> 1 | V14: =INDEX(Home_Data!$B$70:$B$73,MIN(3,MAX(0,0))+1) -> 1 | W14: =IF(INDEX(Home_Data!$H$5:$H$56,H14)="Yes",1,IF(""="poor",Home_Data!$B$74,IF(""="fair",Home_Data!$B$75,IF(""="excellent",Home_Data!$B$77,Home_Data!$B$76)))) -> 1 | X14: =IF(FALSE(),Home_Data!$B$86,1)*IF(FALSE(),Home_Data!$B$87,1)*IF(FALSE(),Home_Data!$B$88,1) -> 1 | Y14: =O14*P14*Q14*R14*S14*T14*U14*V14*W14*X14 -> 3468.7801
A15: Home: $300K house cover, frame | B15: {=MEDIAN(IF((OK_Official_Data!$A$4:$A$1803="home")*(OK_Official_Data!$D$4:$D$1803="scenario 3 (dwelling $300,000, deductible 1%)")*(OK_Official_Data!$F$4:$F$1803="frame"),OK_Official_Data!$H$4:$H$1803))} -> 5198.5 | C15: =Y15 -> 4751.8034 | D15: =C15/B15 -> 0.91407203 | E15: =IF(D15<0.8,"Model low",IF(D15>1.25,"Model high","Within 20% / 25% of the median insurer")) -> Within 20% / 25% of the median insurer | H15: =MATCH("OK",Home_Data!$B$5:$B$56,0) -> 36 | I15: =MIN(MAX(300000,50000),3000000) -> 300000 | J15: =IFERROR(MIN(3,MAX(1,MATCH(I15,Home_Data!$C$4:$F$4,1))),1) -> 2 | K15: =INDEX(Home_Data!$C$5:$F$56,H15,J15) -> 5378 | L15: =INDEX(Home_Data!$C$5:$F$56,H15,J15+1) -> 7105 | M15: =INDEX(Home_Data!$C$4:$F$4,J15) -> 300000 | N15: =INDEX(Home_Data!$C$4:$F$4,J15+1) -> 400000 | O15: =IF(300000<200000,INDEX(Home_Data!$C$5:$F$56,H15,1)*(MAX(300000,Home_Data!$B$90)/200000)^Home_Data!$B$89,K15*(I15/M15)^(LN(L15/K15)/LN(N15/M15))) -> 5378 | P15: =IF(100=100,Home_Data!$B$67,IF(100=500,Home_Data!$B$69,Home_Data!$B$68)) -> 0.991 | Q15: =IF(3000<=Home_Data!$B$61,Home_Data!$B$64,IF(3000>=Home_Data!$B$63,Home_Data!$B$66,IF(3000<=Home_Data!$B$62,Home_Data!$B$64+(Home_Data!$B$65-Home_Data!$B$64)*(LN(3000)-LN(Home_Data!$B$61))/(LN(Home_Data!$B$62)-LN(Home_Data!$B$61)),Home_Data!$B$65+(Home_Data!$B$66-Home_Data!$B$65)*(LN(3000)-LN(Home_Data!$B$62))/(LN(Home_Data!$B$63)-LN(Home_Data!$B$62))))) -> 0.89158759 | R15: =IF(5>=20,Home_Data!$B$80,IF(5>=10,Home_Data!$B$79,1)) -> 1 | S15: =IF(1990<1960,Home_Data!$B$81,IF(1990<1980,Home_Data!$B$82,IF(1990>=2000,Home_Data!$B$83,1))) -> 1 | T15: =IF("frame"="brick",Home_Data!$B$78,1) -> 1 | U15: =IF("own"="rental",Home_Data!$B$84,IF("own"="vacation",Home_Data!$B$85,1)) -> 1 | V15: =INDEX(Home_Data!$B$70:$B$73,MIN(3,MAX(0,0))+1) -> 1 | W15: =IF(INDEX(Home_Data!$H$5:$H$56,H15)="Yes",1,IF(""="poor",Home_Data!$B$74,IF(""="fair",Home_Data!$B$75,IF(""="excellent",Home_Data!$B$77,Home_Data!$B$76)))) -> 1 | X15: =IF(FALSE(),Home_Data!$B$86,1)*IF(FALSE(),Home_Data!$B$87,1)*IF(FALSE(),Home_Data!$B$88,1) -> 1 | Y15: =O15*P15*Q15*R15*S15*T15*U15*V15*W15*X15 -> 4751.8034
A16: Home: $400K house cover, frame | B16: {=MEDIAN(IF((OK_Official_Data!$A$4:$A$1803="home")*(OK_Official_Data!$D$4:$D$1803="scenario 4 (dwelling $400,000, deductible 1%)")*(OK_Official_Data!$F$4:$F$1803="frame"),OK_Official_Data!$H$4:$H$1803))} -> 6526 | C16: =Y16 -> 6073.1561 | D16: =C16/B16 -> 0.93060928 | E16: =IF(D16<0.8,"Model low",IF(D16>1.25,"Model high","Within 20% / 25% of the median insurer")) -> Within 20% / 25% of the median insurer | H16: =MATCH("OK",Home_Data!$B$5:$B$56,0) -> 36 | I16: =MIN(MAX(400000,50000),3000000) -> 400000 | J16: =IFERROR(MIN(3,MAX(1,MATCH(I16,Home_Data!$C$4:$F$4,1))),1) -> 3 | K16: =INDEX(Home_Data!$C$5:$F$56,H16,J16) -> 7105 | L16: =INDEX(Home_Data!$C$5:$F$56,H16,J16+1) -> 10232 | M16: =INDEX(Home_Data!$C$4:$F$4,J16) -> 400000 | N16: =INDEX(Home_Data!$C$4:$F$4,J16+1) -> 600000 | O16: =IF(400000<200000,INDEX(Home_Data!$C$5:$F$56,H16,1)*(MAX(400000,Home_Data!$B$90)/200000)^Home_Data!$B$89,K16*(I16/M16)^(LN(L16/K16)/LN(N16/M16))) -> 7105 | P16: =IF(100=100,Home_Data!$B$67,IF(100=500,Home_Data!$B$69,Home_Data!$B$68)) -> 0.991 | Q16: =IF(4000<=Home_Data!$B$61,Home_Data!$B$64,IF(4000>=Home_Data!$B$63,Home_Data!$B$66,IF(4000<=Home_Data!$B$62,Home_Data!$B$64+(Home_Data!$B$65-Home_Data!$B$64)*(LN(4000)-LN(Home_Data!$B$61))/(LN(Home_Data!$B$62)-LN(Home_Data!$B$61)),Home_Data!$B$65+(Home_Data!$B$66-Home_Data!$B$65)*(LN(4000)-LN(Home_Data!$B$62))/(LN(Home_Data!$B$63)-LN(Home_Data!$B$62))))) -> 0.86253497 | R16: =IF(5>=20,Home_Data!$B$80,IF(5>=10,Home_Data!$B$79,1)) -> 1 | S16: =IF(1990<1960,Home_Data!$B$81,IF(1990<1980,Home_Data!$B$82,IF(1990>=2000,Home_Data!$B$83,1))) -> 1 | T16: =IF("frame"="brick",Home_Data!$B$78,1) -> 1 | U16: =IF("own"="rental",Home_Data!$B$84,IF("own"="vacation",Home_Data!$B$85,1)) -> 1 | V16: =INDEX(Home_Data!$B$70:$B$73,MIN(3,MAX(0,0))+1) -> 1 | W16: =IF(INDEX(Home_Data!$H$5:$H$56,H16)="Yes",1,IF(""="poor",Home_Data!$B$74,IF(""="fair",Home_Data!$B$75,IF(""="excellent",Home_Data!$B$77,Home_Data!$B$76)))) -> 1 | X16: =IF(FALSE(),Home_Data!$B$86,1)*IF(FALSE(),Home_Data!$B$87,1)*IF(FALSE(),Home_Data!$B$88,1) -> 1 | Y16: =O16*P16*Q16*R16*S16*T16*U16*V16*W16*X16 -> 6073.1561
A17: Home: $500K house cover, frame | B17: {=MEDIAN(IF((OK_Official_Data!$A$4:$A$1803="home")*(OK_Official_Data!$D$4:$D$1803="scenario 5 (dwelling $500,000, deductible 1%)")*(OK_Official_Data!$F$4:$F$1803="frame"),OK_Official_Data!$H$4:$H$1803))} -> 7539 | C17: =Y17 -> 7229.1774 | D17: =C17/B17 -> 0.95890401 | E17: =IF(D17<0.8,"Model low",IF(D17>1.25,"Model high","Within 20% / 25% of the median insurer")) -> Within 20% / 25% of the median insurer | H17: =MATCH("OK",Home_Data!$B$5:$B$56,0) -> 36 | I17: =MIN(MAX(500000,50000),3000000) -> 500000 | J17: =IFERROR(MIN(3,MAX(1,MATCH(I17,Home_Data!$C$4:$F$4,1))),1) -> 3 | K17: =INDEX(Home_Data!$C$5:$F$56,H17,J17) -> 7105 | L17: =INDEX(Home_Data!$C$5:$F$56,H17,J17+1) -> 10232 | M17: =INDEX(Home_Data!$C$4:$F$4,J17) -> 400000 | N17: =INDEX(Home_Data!$C$4:$F$4,J17+1) -> 600000 | O17: =IF(500000<200000,INDEX(Home_Data!$C$5:$F$56,H17,1)*(MAX(500000,Home_Data!$B$90)/200000)^Home_Data!$B$89,K17*(I17/M17)^(LN(L17/K17)/LN(N17/M17))) -> 8684.3224 | P17: =IF(100=100,Home_Data!$B$67,IF(100=500,Home_Data!$B$69,Home_Data!$B$68)) -> 0.991 | Q17: =IF(5000<=Home_Data!$B$61,Home_Data!$B$64,IF(5000>=Home_Data!$B$63,Home_Data!$B$66,IF(5000<=Home_Data!$B$62,Home_Data!$B$64+(Home_Data!$B$65-Home_Data!$B$64)*(LN(5000)-LN(Home_Data!$B$61))/(LN(Home_Data!$B$62)-LN(Home_Data!$B$61)),Home_Data!$B$65+(Home_Data!$B$66-Home_Data!$B$65)*(LN(5000)-LN(Home_Data!$B$62))/(LN(Home_Data!$B$63)-LN(Home_Data!$B$62))))) -> 0.84 | R17: =IF(5>=20,Home_Data!$B$80,IF(5>=10,Home_Data!$B$79,1)) -> 1 | S17: =IF(1990<1960,Home_Data!$B$81,IF(1990<1980,Home_Data!$B$82,IF(1990>=2000,Home_Data!$B$83,1))) -> 1 | T17: =IF("frame"="brick",Home_Data!$B$78,1) -> 1 | U17: =IF("own"="rental",Home_Data!$B$84,IF("own"="vacation",Home_Data!$B$85,1)) -> 1 | V17: =INDEX(Home_Data!$B$70:$B$73,MIN(3,MAX(0,0))+1) -> 1 | W17: =IF(INDEX(Home_Data!$H$5:$H$56,H17)="Yes",1,IF(""="poor",Home_Data!$B$74,IF(""="fair",Home_Data!$B$75,IF(""="excellent",Home_Data!$B$77,Home_Data!$B$76)))) -> 1 | X17: =IF(FALSE(),Home_Data!$B$86,1)*IF(FALSE(),Home_Data!$B$87,1)*IF(FALSE(),Home_Data!$B$88,1) -> 1 | Y17: =O17*P17*Q17*R17*S17*T17*U17*V17*W17*X17 -> 7229.1774
A18: Home: $300K house cover, masonry | B18: {=MEDIAN(IF((OK_Official_Data!$A$4:$A$1803="home")*(OK_Official_Data!$D$4:$D$1803="scenario 3 (dwelling $300,000, deductible 1%)")*(OK_Official_Data!$F$4:$F$1803="masonry"),OK_Official_Data!$H$4:$H$1803))} -> 4971.5 | C18: =Y18 -> 4656.7674 | D18: =C18/B18 -> 0.93669262 | E18: =IF(D18<0.8,"Model low",IF(D18>1.25,"Model high","Within 20% / 25% of the median insurer")) -> Within 20% / 25% of the median insurer | H18: =MATCH("OK",Home_Data!$B$5:$B$56,0) -> 36 | I18: =MIN(MAX(300000,50000),3000000) -> 300000 | J18: =IFERROR(MIN(3,MAX(1,MATCH(I18,Home_Data!$C$4:$F$4,1))),1) -> 2 | K18: =INDEX(Home_Data!$C$5:$F$56,H18,J18) -> 5378 | L18: =INDEX(Home_Data!$C$5:$F$56,H18,J18+1) -> 7105 | M18: =INDEX(Home_Data!$C$4:$F$4,J18) -> 300000 | N18: =INDEX(Home_Data!$C$4:$F$4,J18+1) -> 400000 | O18: =IF(300000<200000,INDEX(Home_Data!$C$5:$F$56,H18,1)*(MAX(300000,Home_Data!$B$90)/200000)^Home_Data!$B$89,K18*(I18/M18)^(LN(L18/K18)/LN(N18/M18))) -> 5378 | P18: =IF(100=100,Home_Data!$B$67,IF(100=500,Home_Data!$B$69,Home_Data!$B$68)) -> 0.991 | Q18: =IF(3000<=Home_Data!$B$61,Home_Data!$B$64,IF(3000>=Home_Data!$B$63,Home_Data!$B$66,IF(3000<=Home_Data!$B$62,Home_Data!$B$64+(Home_Data!$B$65-Home_Data!$B$64)*(LN(3000)-LN(Home_Data!$B$61))/(LN(Home_Data!$B$62)-LN(Home_Data!$B$61)),Home_Data!$B$65+(Home_Data!$B$66-Home_Data!$B$65)*(LN(3000)-LN(Home_Data!$B$62))/(LN(Home_Data!$B$63)-LN(Home_Data!$B$62))))) -> 0.89158759 | R18: =IF(5>=20,Home_Data!$B$80,IF(5>=10,Home_Data!$B$79,1)) -> 1 | S18: =IF(1990<1960,Home_Data!$B$81,IF(1990<1980,Home_Data!$B$82,IF(1990>=2000,Home_Data!$B$83,1))) -> 1 | T18: =IF("brick"="brick",Home_Data!$B$78,1) -> 0.98 | U18: =IF("own"="rental",Home_Data!$B$84,IF("own"="vacation",Home_Data!$B$85,1)) -> 1 | V18: =INDEX(Home_Data!$B$70:$B$73,MIN(3,MAX(0,0))+1) -> 1 | W18: =IF(INDEX(Home_Data!$H$5:$H$56,H18)="Yes",1,IF(""="poor",Home_Data!$B$74,IF(""="fair",Home_Data!$B$75,IF(""="excellent",Home_Data!$B$77,Home_Data!$B$76)))) -> 1 | X18: =IF(FALSE(),Home_Data!$B$86,1)*IF(FALSE(),Home_Data!$B$87,1)*IF(FALSE(),Home_Data!$B$88,1) -> 1 | Y18: =O18*P18*Q18*R18*S18*T18*U18*V18*W18*X18 -> 4656.7674
A21: How much insurers differ for the same customer (price / median price of the same profile)
A22: Line | B22: Cheapest tenth (10th percentile) | C22: Lower quarter (25th) | D22: Upper quarter (75th) | E22: Dearest tenth (90th) | F22: Log standard deviation | G22: Prices
A23: Car | B23: {=PERCENTILE(IF(OK_Official_Data!$A$4:$A$1803="auto",OK_Official_Data!$K$4:$K$1803),0.1)} -> 0.59239445 | C23: {=PERCENTILE(IF(OK_Official_Data!$A$4:$A$1803="auto",OK_Official_Data!$K$4:$K$1803),0.25)} -> 0.79246094 | D23: {=PERCENTILE(IF(OK_Official_Data!$A$4:$A$1803="auto",OK_Official_Data!$K$4:$K$1803),0.75)} -> 1.2136511 | E23: {=PERCENTILE(IF(OK_Official_Data!$A$4:$A$1803="auto",OK_Official_Data!$K$4:$K$1803),0.9)} -> 1.5728651 | F23: {=STDEV(IF(OK_Official_Data!$A$4:$A$1803="auto",LN(OK_Official_Data!$K$4:$K$1803)))} -> 0.39210158 | G23: =COUNTIF(OK_Official_Data!$A$4:$A$1803,"auto") -> 1000
A24: Home | B24: {=PERCENTILE(IF(OK_Official_Data!$A$4:$A$1803="home",OK_Official_Data!$K$4:$K$1803),0.1)} -> 0.4648509 | C24: {=PERCENTILE(IF(OK_Official_Data!$A$4:$A$1803="home",OK_Official_Data!$K$4:$K$1803),0.25)} -> 0.74557673 | D24: {=PERCENTILE(IF(OK_Official_Data!$A$4:$A$1803="home",OK_Official_Data!$K$4:$K$1803),0.75)} -> 1.2160996 | E24: {=PERCENTILE(IF(OK_Official_Data!$A$4:$A$1803="home",OK_Official_Data!$K$4:$K$1803),0.9)} -> 1.3709664 | F24: {=STDEV(IF(OK_Official_Data!$A$4:$A$1803="home",LN(OK_Official_Data!$K$4:$K$1803)))} -> 0.42123826 | G24: =COUNTIF(OK_Official_Data!$A$4:$A$1803,"home") -> 800
A26: Highest divided by lowest insurer price for the same profile (median across profiles)
A27: Documented in the report as about 4.7x (home) and 4.9x (car). Reproduce with a pivot on the Group key column.
A29: Caution: some model parameters (own-car and liability shares, the age-16 multiple, masonry, the sub-$200,000 slope, the spread) were set from this same data, so the fit is partly in-sample. One state, one moment, standard programs only.

Sheet Validation
A1: Validation summary
A2: Live ratios link to OK_Benchmark. "Before" values are from the first version of the model (documented in the report).
A4: Check | B4: Before the fixes | C4: After (live from OK_Benchmark)
A5: Car: 16, single, drives to school: model / median insurer | B5: 0.62 | C5: =OK_Benchmark!D5 -> 1.0943236
A6: Car: 21, single, commutes: model / median insurer | B6: 0.91 | C6: =OK_Benchmark!D6 -> 1.0855201
A7: Car: 36, married, commutes: model / median insurer | B7: 0.79 | C7: =OK_Benchmark!D7 -> 0.93885711
A8: Car: 55, married, commutes: model / median insurer | B8: 0.83 | C8: =OK_Benchmark!D8 -> 0.99357232
A9: Car: 70, married, pleasure use: model / median insurer | B9: 0.84 | C9: =OK_Benchmark!D9 -> 0.99964612
A10: Home: $100K frame: model / median insurer | B10: 0.77 | C10: =OK_Benchmark!D13 -> 0.93909504
A11: Home: $200K frame: model / median insurer | B11: 0.96 | C11: =OK_Benchmark!D14 -> 0.8979498
A12: Home: $300K frame: model / median insurer | B12: 0.93 | C12: =OK_Benchmark!D15 -> 0.91407203
A13: Home: $400K frame: model / median insurer | B13: 0.98 | C13: =OK_Benchmark!D16 -> 0.93060928
A14: Home: $500K frame: model / median insurer | B14: 0.96 | C14: =OK_Benchmark!D17 -> 0.95890401
A21: Other independent checks
A22: Check | B22: Result
A23: 20-year-old, clean record, national (NerdWallet March 2026: $395 a month = $4,740 a year) | B23: Model within 1%. With Insurify's 1.48x the model was about 27% low.
A24: 40-year-old with one speeding ticket, national ($241 a month) | B24: Model within 3%.
A25: Car state medians, March vs. September 2026 (23 states) | B25: 22 of 23 within 20%; Florida moved 23%.
A26: Home coverage curve, leave-one-out over 51 states | B26: Interior points 1.2% mean error; end points 2.9%.
A27: Home vintage drift (Insurance.com earlier table vs. September 2026, 17 states) | B27: All within 35%; largest move 17%.
A28: Home cross-source: InsuranceQuotes vs. Insurance.com, ten states | B28: The other source is 38% to 80% of the model level; inside the range in 5 of 10 states (fail).

Sheet Car_Data
A1: Car data and factors
A2: Blue cells are inputs you can change; every calculator formula reads from here. Basis column says whether a figure is published (sourced) or our assumption.
A4: State | B4: Code | C4: Published median ($/yr) | D4: Index vs. national | E4: Credit banned for car pricing? | F4: Credit limited? | G4: No-fault state? | H4: PIP and lawsuit threshold | I4: Uninsured-motorist status | J4: Minimum liability (bodily injury per person / per accident / property damage, $000) | K4: Status of the minimum
A5: Alabama | B5: AL | C5: 2178 | D5: =C5/$C$56 -> 0.92918089 | E5: No | F5: No | G5: No | I5: Not tracked here | J5: 25/50/25 | K5: Consumer guides only; confirm with your state
A6: Alaska | B6: AK | C6: 1650 | D6: =C6/$C$56 -> 0.70392491 | E6: No | F6: No | G6: No | I6: Not tracked here | J6: 50/100/25 | K6: Consumer guides only; confirm with your state
A7: Arizona | B7: AZ | C7: 2947 | D7: =C7/$C$56 -> 1.2572526 | E7: No | F7: No | G7: No | I7: Not tracked here | J7: 25/50/15 | K7: Consumer guides only; confirm with your state
A8: Arkansas | B8: AR | C8: 2642 | D8: =C8/$C$56 -> 1.1271331 | E8: No | F8: No | G8: No | I8: Not tracked here | J8: 25/50/25 | K8: Consumer guides only; confirm with your state
A9: California | B9: CA | C9: 1931 | D9: =C9/$C$56 -> 0.82380546 | E9: Yes | F9: No | G9: No | I9: Not tracked here | J9: 30/60/15 since January 1, 2025 (SB 1107) | K9: State law identified; agency page not opened
A10: Colorado | B10: CO | C10: 3249 | D10: =C10/$C$56 -> 1.3860922 | E10: No | F10: No | G10: No | I10: Not tracked here | J10: 25/50/15 | K10: Consumer guides only; confirm with your state
A11: Connecticut | B11: CT | C11: 2789 | D11: =C11/$C$56 -> 1.1898464 | E11: No | F11: No | G11: No | I11: Required | J11: 25/50/25, plus 25/50 uninsured and underinsured motorist cover | K11: Consumer guides only; confirm with your state
A12: Delaware | B12: DE | C12: 2643 | D12: =C12/$C$56 -> 1.1275597 | E12: No | F12: No | G12: No | I12: Not tracked here | J12: 25/50/10, plus $15,000/$30,000 personal injury protection | K12: Consumer guides only; confirm with your state
A13: Florida | B13: FL | C13: 3295 | D13: =C13/$C$56 -> 1.4057167 | E13: No | F13: No | G13: Yes | H13: PIP $10,000; a serious-injury (verbal) threshold | I13: Not tracked here | J13: No bodily-injury minimum. $10,000 personal injury protection and $10,000 property damage. After certain at-fault crashes, 10/20/10 with an SR-22 for three years may be required | K13: Checked against an official state source
A14: Georgia | B14: GA | C14: 3136 | D14: =C14/$C$56 -> 1.337884 | E14: No | F14: No | G14: No | I14: Not tracked here | J14: 25/50/25 | K14: Consumer guides only; confirm with your state
A15: Hawaii | B15: HI | C15: 1975 | D15: =C15/$C$56 -> 0.84257679 | E15: Yes | F15: No | G15: Yes | H15: PIP $10,000; a $5,000 medical-cost threshold | I15: Must be offered; may be rejected in writing | J15: 40/80/20, plus $10,000 personal injury protection (from January 1, 2026) | K15: Checked against an official state source
A16: Idaho | B16: ID | C16: 1998 | D16: =C16/$C$56 -> 0.85238908 | E16: No | F16: No | G16: No | I16: Not tracked here | J16: 25/50/15 | K16: Consumer guides only; confirm with your state
A17: Illinois | B17: IL | C17: 2461 | D17: =C17/$C$56 -> 1.0499147 | E17: No | F17: No | G17: No | I17: Required | J17: 25/50/20, plus uninsured-motorist cover. The Secretary of State's brochure confirms uninsured-motorist cover is automatic | K17: Partly checked; confirm the limits
A18: Indiana | B18: IN | C18: 1950 | D18: =C18/$C$56 -> 0.83191126 | E18: No | F18: No | G18: No | I18: Not tracked here | J18: 25/50/25 | K18: Consumer guides only; confirm with your state
A19: Iowa | B19: IA | C19: 2228 | D19: =C19/$C$56 -> 0.95051195 | E19: No | F19: No | G19: No | I19: Not tracked here | J19: 20/40/15 | K19: Consumer guides only; confirm with your state
A20: Kansas | B20: KS | C20: 2511 | D20: =C20/$C$56 -> 1.0712457 | E20: No | F20: No | G20: Yes | H20: PIP $4,500 to $9,000 (sources differ); a $2,000 medical-cost threshold | I20: Required | J20: 25/50/25, plus personal injury protection (guides differ: $4,500 or $9,000) and 25/50 uninsured-motorist cover | K20: Consumer guides only; confirm with your state
A21: Kentucky | B21: KY | C21: 3259 | D21: =C21/$C$56 -> 1.3903584 | E21: No | F21: No | G21: Yes | H21: PIP $10,000; a $1,000 threshold | I21: Not tracked here | J21: 25/50/25, plus $10,000 personal injury protection | K21: Consumer guides only; confirm with your state
A22: Louisiana | B22: LA | C22: 4296 | D22: =C22/$C$56 -> 1.8327645 | E22: No | F22: No | G22: No | I22: Not tracked here | J22: 15/30/25 | K22: Consumer guides only; confirm with your state
A23: Maine | B23: ME | C23: 1701 | D23: =C23/$C$56 -> 0.72568259 | E23: No | F23: No | G23: No | I23: Required | J23: 50/100/25, plus 50/100 uninsured-motorist cover and $2,000 medical payments | K23: Consumer guides only; confirm with your state
A24: Maryland | B24: MD | C24: 3052 | D24: =C24/$C$56 -> 1.3020478 | E24: No | F24: No | G24: No | I24: Not tracked here | J24: Not checked. Look up the minimum with your state insurance department | K24: Not checked
A25: Massachusetts | B25: MA | C25: 1851 | D25: =C25/$C$56 -> 0.78967577 | E25: Yes | F25: No | G25: Yes | H25: PIP $8,000; a $2,000 medical-cost threshold | I25: Required | J25: 25/50/30, plus $8,000 personal injury protection and 25/50 uninsured-motorist cover (policies written or renewed on or after July 1, 2025) | K25: Checked against an official state source
A26: Michigan | B26: MI | C26: 2944 | D26: =C26/$C$56 -> 1.2559727 | E26: Yes | F26: No | G26: Yes | H26: PIP a choice of levels, unlimited by default; a serious-injury threshold | I26: Not tracked here | J26: Bodily injury 50/100 (default 250/500), $1 million property protection, and a choice of personal injury protection levels (unlimited by default) | K26: Checked against an official state source
A27: Minnesota | B27: MN | C27: 2508 | D27: =C27/$C$56 -> 1.0699659 | E27: No | F27: No | G27: Yes | H27: PIP $40,000; a $4,000 threshold | I27: Not tracked here | J27: Not checked. Look up the minimum with your state insurance department | K27: Not checked
A28: Mississippi | B28: MS | C28: 2499 | D28: =C28/$C$56 -> 1.0661263 | E28: No | F28: No | G28: No | I28: Not tracked here | J28: Not checked. Look up the minimum with your state insurance department | K28: Not checked
A29: Missouri | B29: MO | C29: 2622 | D29: =C29/$C$56 -> 1.1186007 | E29: No | F29: No | G29: No | I29: Not tracked here | J29: Not checked. Look up the minimum with your state insurance department | K29: Not checked
A30: Montana | B30: MT | C30: 2778 | D30: =C30/$C$56 -> 1.1851536 | E30: No | F30: No | G30: No | I30: Not tracked here | J30: Not checked. Look up the minimum with your state insurance department | K30: Not checked
A31: Nebraska | B31: NE | C31: 1955 | D31: =C31/$C$56 -> 0.83404437 | E31: No | F31: No | G31: No | I31: Not tracked here | J31: Not checked. Look up the minimum with your state insurance department | K31: Not checked
A32: Nevada | B32: NV | C32: 3428 | D32: =C32/$C$56 -> 1.4624573 | E32: No | F32: No | G32: No | I32: Not tracked here | J32: 25/50/20 | K32: Consumer guides only; confirm with your state
A33: New Hampshire | B33: NH | C33: 1568 | D33: =C33/$C$56 -> 0.66894198 | E33: No | F33: No | G33: No | I33: Not tracked here | J33: No general insurance requirement; drivers must show financial responsibility if in a crash | K33: Consumer guides only; confirm with your state
A34: New Jersey | B34: NJ | C34: 3664 | D34: =C34/$C$56 -> 1.5631399 | E34: No | F34: No | G34: Yes | H34: PIP $15,000; a serious-injury (verbal) threshold | I34: Not tracked here | J34: 35/70/25 on a standard policy (raised recently) | K34: Consumer guides only; confirm with your state
A35: New Mexico | B35: NM | C35: 2132 | D35: =C35/$C$56 -> 0.90955631 | E35: No | F35: No | G35: No | I35: Not tracked here | J35: Not checked. Look up the minimum with your state insurance department | K35: Not checked
A36: New York | B36: NY | C36: 2674 | D36: =C36/$C$56 -> 1.140785 | E36: No | F36: No | G36: Yes | H36: PIP $50,000; a serious-injury (verbal) threshold | I36: Required | J36: 25/50/10 (injury 25/50; death 50/100), plus 25/50 uninsured-motorist cover and $50,000 personal injury protection | K36: Checked against an official state source
A37: North Carolina | B37: NC | C37: 1789 | D37: =C37/$C$56 -> 0.76322526 | E37: No | F37: No | G37: No | I37: Required | J37: 30/60/25, plus uninsured and underinsured motorist cover. Some websites claim a 2025 increase that we could not confirm | K37: Checked against an official state source
A38: North Dakota | B38: ND | C38: 2423 | D38: =C38/$C$56 -> 1.0337031 | E38: No | F38: No | G38: Yes | H38: PIP $30,000; a $2,500 threshold | I38: Not tracked here | J38: Not checked. Look up the minimum with your state insurance department | K38: Not checked
A39: Ohio | B39: OH | C39: 1803 | D39: =C39/$C$56 -> 0.76919795 | E39: No | F39: No | G39: No | I39: Not tracked here | J39: 25/50/25 | K39: Checked against an official state source
A40: Oklahoma | B40: OK | C40: 2192 | D40: =C40/$C$56 -> 0.93515358 | E40: No | F40: No | G40: No | I40: Not tracked here | J40: 25/50/25 | K40: Consumer guides only; confirm with your state
A41: Oregon | B41: OR | C41: 2187 | D41: =C41/$C$56 -> 0.93302048 | E41: No | F41: Yes | G41: No | I41: Not tracked here | J41: Not checked. Look up the minimum with your state insurance department | K41: Not checked
A42: Pennsylvania | B42: PA | C42: 2239 | D42: =C42/$C$56 -> 0.95520478 | E42: No | F42: No | G42: Yes | H42: PIP $5,000; a serious-injury threshold if you chose limited tort | I42: Must be offered; may be rejected in writing | J42: 15/30/5, plus $5,000 first-party medical benefits | K42: Checked against an official state source
A43: Rhode Island | B43: RI | C43: 3121 | D43: =C43/$C$56 -> 1.3314846 | E43: No | F43: No | G43: No | I43: Not tracked here | J43: Not checked. Look up the minimum with your state insurance department | K43: Not checked
A44: South Carolina | B44: SC | C44: 2288 | D44: =C44/$C$56 -> 0.97610922 | E44: No | F44: No | G44: No | I44: Not tracked here | J44: Not checked. Look up the minimum with your state insurance department | K44: Not checked
A45: South Dakota | B45: SD | C45: 2212 | D45: =C45/$C$56 -> 0.94368601 | E45: No | F45: No | G45: No | I45: Not tracked here | J45: Not checked. Look up the minimum with your state insurance department | K45: Not checked
A46: Tennessee | B46: TN | C46: 2130 | D46: =C46/$C$56 -> 0.90870307 | E46: No | F46: No | G46: No | I46: Not tracked here | J46: 25/50/25 | K46: Consumer guides only; confirm with your state
A47: Texas | B47: TX | C47: 3608 | D47: =C47/$C$56 -> 1.5392491 | E47: No | F47: No | G47: No | I47: Must be offered; may be rejected in writing | J47: 30/60/25 | K47: Checked against an official state source
A48: Utah | B48: UT | C48: 2321 | D48: =C48/$C$56 -> 0.99018771 | E48: No | F48: Yes | G48: Yes | H48: PIP $3,000; a $3,000 threshold | I48: Not tracked here | J48: 30/65/25, plus $3,000 personal injury protection (raised in 2025) | K48: Consumer guides only; confirm with your state
A49: Vermont | B49: VT | C49: 1463 | D49: =C49/$C$56 -> 0.62414676 | E49: No | F49: No | G49: No | I49: Not tracked here | J49: Not checked. Look up the minimum with your state insurance department | K49: Not checked
A50: Virginia | B50: VA | C50: 2151 | D50: =C50/$C$56 -> 0.91766212 | E50: No | F50: No | G50: No | I50: Not tracked here | J50: Not checked. Look up the minimum with your state insurance department | K50: Not checked
A51: Washington | B51: WA | C51: 2333 | D51: =C51/$C$56 -> 0.99530717 | E51: No | F51: No | G51: No | I51: Not tracked here | J51: 25/50/10 | K51: Checked against an official state source
A52: Washington, D.C. | B52: DC | C52: 2655 | D52: =C52/$C$56 -> 1.1326792 | E52: No | F52: No | G52: No | I52: Not tracked here | J52: Not checked. Look up the minimum with your state insurance department | K52: Not checked
A53: West Virginia | B53: WV | C53: 2144 | D53: =C53/$C$56 -> 0.91467577 | E53: No | F53: No | G53: No | I53: Not tracked here | J53: Not checked. Look up the minimum with your state insurance department | K53: Not checked
A54: Wisconsin | B54: WI | C54: 2316 | D54: =C54/$C$56 -> 0.98805461 | E54: No | F54: No | G54: No | I54: Not tracked here | J54: Not checked. Look up the minimum with your state insurance department | K54: Not checked
A55: Wyoming | B55: WY | C55: 1148 | D55: =C55/$C$56 -> 0.48976109 | E55: No | F55: No | G55: No | I55: Not tracked here | J55: 25/50/20 | K55: Consumer guides only; confirm with your state
A56: Another place | B56: OTHER | C56: 2344 | D56: =C56/$C$56 -> 1 | E56: No | F56: No | G56: No | I56: Not tracked here | J56: Look up your state's minimum with your state insurance department | K56: Not checked
A57: Source: NerdWallet, September 2026, analysis of public rate filings (Quadrant). Reference driver: 35 years old, clean record, good credit, 2023 Toyota Camry, 12,000 miles a year, 100/300/50 liability with uninsured motorist, collision and comprehensive with $1,000 deductibles. "OTHER" row = national median. Minimums: see the Min_Liability sheet for sources.
A59: Age multiples (relative to a 35-year-old)
A60: Age (from) | B60: Multiple | C60: Basis
A61: 16 | B61: 3.6 | C61: Oklahoma Insurance Department official samples (teen as principal operator, median insurer, 3.6x a 36-year-old)
A62: 19 | B62: 2.5 | C62: Assumed (between 16 and 20)
A63: 20 | B63: 2.04 | C63: NerdWallet March 2026: $395 a month for a clean-record 20-year-old vs. about $194 for a 35-year-old = 2.04x
A64: 25 | B64: 1.3 | C64: Assumed
A65: 30 | B65: 1.1 | C65: Insurify average full-coverage rates by age
A66: 35 | B66: 1 | C66: Reference
A67: 40 | B67: 0.985 | C67: Insurify
A68: 45 | B68: 0.964 | C68: Insurify
A69: 50 | B69: 0.934 | C69: Insurify
A70: 55 | B70: 0.899 | C70: Insurify
A71: 60 | B71: 0.863 | C71: Insurify
A72: 65 | B72: 0.822 | C72: Insurify
... A74: 99 | B74: 0.848 | C74: Insurify (70+)
A77: Record, credit, mileage and use multiples
A78: Item | B78: Multiple | C78: Basis
A79: Accidents you caused: 0 | B79: 1 | C79: Reference
A80: Accidents: 1 | B80: 1.49 | C80: Sourced: NerdWallet
A81: Accidents: 2 | B81: 2 | C81: Assumed (extrapolated)
A82: Accidents: 3 or more | B82: 2.4 | C82: Assumed (extrapolated)
A83: Tickets: 0 | B83: 1 | C83: Reference
A84: Tickets: 1 | B84: 1.29 | C84: Sourced: NerdWallet
A85: Tickets: 2 | B85: 1.6 | C85: Assumed (extrapolated)
A86: Tickets: 3 or more | B86: 1.9 | C86: Assumed (extrapolated)
A87: DUI | B87: 1.89 | C87: Sourced: NerdWallet
A88: Credit: poor | B88: 1.68 | C88: Sourced: NerdWallet
A89: Credit: fair | B89: 1.3 | C89: Assumed
A90: Credit: good | B90: 1 | C90: Reference
... A95: Under 2 years driving | B95: 1.15 | C95: Assumed
A98: Cover shares (share of a full 100/300/50 policy = 1.00)
A99: Code | B99: Share | C99: Basis
A100: min | B100: 0.26 | C100: Anchored: NerdWallet minimum-limit policy = 27.5% of full nationally; Oklahoma official samples
A101: l50 | B101: 0.31 | C101: Assumed (between minimum and 100/300)
A102: l100 | B102: 0.36 | C102: Anchored: liability = 1.00 minus own-car share
A103: unsure | B103: 0.33 | C103: Assumed
A104: liab | B104: 0 | C104: No own-car cover
A105: coll | B105: 0.45 | C105: Assumed split of own-car cover
A106: full | B106: 0.64 | C106: Oklahoma official samples: minimum liability + $500-deductible own-car cover cost the median insurer 0.86 of the full 100/300/50 median
A109: Other car factors
A110: Item | B110: Value | C110: Basis
A111: Deductible saving, $500 to $1,000 | B111: 0.128 | C111: Sourced: NerdWallet average savings
A112: Deductible saving, $1,000 to $2,000 | B112: 0.135 | C112: Sourced: NerdWallet
A113: Factor for a $500 deductible | B113: =1/(1-B111) -> 1.146789 | C113: Formula
...

Sheet Home_Data
A1: Home data and factors
A2: Insurance.com state averages (updated September 15, 2026; rates from Quadrant): annual premium for the dwelling coverage shown, $1,000 deductible, $300,000 liability, good credit.
A4: State | B4: Code | C4: 200000 | D4: 300000 | E4: 400000 | F4: 600000 | G4: Index at $300,000 | H4: Credit banned for home pricing? | I4: Note
A5: Alabama | B5: AL | C5: 2852 | D5: 3716 | E5: 4506 | F5: 6118 | G5: =D5/$D$56 -> 1.2938719 | H5: No
A6: Alaska | B6: AK | C6: 1177 | D6: 1492 | E6: 1825 | F6: 2420 | G6: =D6/$D$56 -> 0.51949861 | H6: No
A7: Arizona | B7: AZ | C7: 1895 | D7: 2397 | E7: 2917 | F7: 4011 | G7: =D7/$D$56 -> 0.83461003 | H7: No
A8: Arkansas | B8: AR | C8: 2458 | D8: 3195 | E8: 3960 | F8: 5450 | G8: =D8/$D$56 -> 1.1124652 | H8: No
A9: California | B9: CA | C9: 1244 | D9: 1653 | E9: 2090 | F9: 3092 | G9: =D9/$D$56 -> 0.5755571 | H9: Yes
A10: Colorado | B10: CO | C10: 4058 | D10: 5511 | E10: 6847 | F10: 8994 | G10: =D10/$D$56 -> 1.9188719 | H10: No
A11: Connecticut | B11: CT | C11: 1673 | D11: 2132 | E11: 2600 | F11: 3524 | G11: =D11/$D$56 -> 0.74233983 | H11: No
A12: Delaware | B12: DE | C12: 1140 | D12: 1461 | E12: 1796 | F12: 2662 | G12: =D12/$D$56 -> 0.50870474 | H12: No
A13: Florida | B13: FL | C13: 6203 | D13: 8471 | E13: 11161 | F13: 16690 | G13: =D13/$D$56 -> 2.9495125 | H13: No
A14: Georgia | B14: GA | C14: 1784 | D14: 2301 | E14: 2888 | F14: 4120 | G14: =D14/$D$56 -> 0.80118384 | H14: No
A15: Hawaii | B15: HI | C15: 558 | D15: 738 | E15: 943 | F15: 1315 | G15: =D15/$D$56 -> 0.25696379 | H15: No | I15: Average excludes hurricane cover
A16: Idaho | B16: ID | C16: 1800 | D16: 2412 | E16: 3009 | F16: 4189 | G16: =D16/$D$56 -> 0.83983287 | H16: No
A17: Illinois | B17: IL | C17: 2176 | D17: 2802 | E17: 3357 | F17: 4678 | G17: =D17/$D$56 -> 0.97562674 | H17: No
A18: Indiana | B18: IN | C18: 2183 | D18: 2869 | E18: 3490 | F18: 4597 | G18: =D18/$D$56 -> 0.99895543 | H18: No
A19: Iowa | B19: IA | C19: 2406 | D19: 3148 | E19: 3820 | F19: 5051 | G19: =D19/$D$56 -> 1.0961003 | H19: No
A20: Kansas | B20: KS | C20: 3822 | D20: 5289 | E20: 6763 | F20: 9553 | G20: =D20/$D$56 -> 1.8415738 | H20: No
A21: Kentucky | B21: KY | C21: 3587 | D21: 4471 | E21: 5450 | F21: 7030 | G21: =D21/$D$56 -> 1.5567549 | H21: No
A22: Louisiana | B22: LA | C22: 3766 | D22: 5185 | E22: 6613 | F22: 9540 | G22: =D22/$D$56 -> 1.8053621 | H22: No
A23: Maine | B23: ME | C23: 956 | D23: 1299 | E23: 1642 | F23: 2377 | G23: =D23/$D$56 -> 0.45229805 | H23: No
A24: Maryland | B24: MD | C24: 1743 | D24: 2242 | E24: 2728 | F24: 3659 | G24: =D24/$D$56 -> 0.78064067 | H24: Yes
A25: Massachusetts | B25: MA | C25: 1616 | D25: 2112 | E25: 2584 | F25: 3543 | G25: =D25/$D$56 -> 0.73537604 | H25: Yes
A26: Michigan | B26: MI | C26: 2249 | D26: 3071 | E26: 4044 | F26: 5545 | G26: =D26/$D$56 -> 1.0692897 | H26: No
A27: Minnesota | B27: MN | C27: 2344 | D27: 3333 | E27: 4257 | F27: 5698 | G27: =D27/$D$56 -> 1.1605153 | H27: No
... A55: Wyoming | B55: WY | C55: 1470 | D55: 2075 | E55: 2730 | F55: 4051 | G55: =D55/$D$56 -> 0.72249304 | H55: No
A56: Another place | B56: OTHER | C56: 2156 | D56: 2872 | E56: 3579 | F56: 4960 | G56: =D56/$D$56 -> 1 | H56: No | I56: National average
A57: Source: Insurance.com average rates by state. Another published source (InsuranceQuotes) is 38% to 80% of these figures in ten states; treat home prices as one source's view.
A59: Home factors
A60: Item | B60: Value | C60: Basis
A61: Deductible $1,000 (x point) | B61: 1000
A62: Deductible $2,500 (x point) | B62: 2500
A63: Deductible $5,000 (x point) | B63: 5000
A64: Deductible factor at $1,000 | B64: 1 | C64: Reference
A65: Deductible factor at $2,500 | B65: 0.91 | C65: Sourced: Insurance.com averages
A66: Deductible factor at $5,000 | B66: 0.84 | C66: Sourced: Insurance.com averages
A67: Liability $100,000 | B67: 0.991 | C67: Sourced: Insurance.com averages
A68: Liability $300,000 | B68: 1 | C68: Reference
A69: Liability $500,000 | B69: 1.005 | C69: Sourced: Insurance.com averages
A70: Claims in 5 years: 0 | B70: 1 | C70: Reference
A71: Claims: 1 | B71: 1.16 | C71: Sourced: MoneyGeek March 2026 ($3,961 vs. $3,417)
A72: Claims: 2 | B72: 1.29 | C72: Sourced: MoneyGeek ($4,418)
A73: Claims: 3 or more | B73: 1.45 | C73: Assumed
A74: Credit: poor | B74: 2.11 | C74: Sourced: Bankrate ($5,122 vs. $2,424 good); studies disagree widely
A75: Credit: fair / average | B75: 1.07 | C75: Sourced: Bankrate ($2,601)
... A91: Total spread (sigma) for homes | B91: 0.47 | C91: Insurer spread 0.42-0.43 in Oklahoma samples plus an assumed 0.20
A93: Rebuild cost per square foot
A94: Estimate | B94: Per sq ft | C94: Basis
A95: Low | B95: 162 | C95: NAHB national average for new construction (state range $154 to $230)
A96: Midpoint | B96: 280 | C96: NerdWallet using First Street data (NJ about $330, MT about $240)
A97: High | B97: 350 | C97: Insure.com survey of actual rebuilds
A99: Average claim sizes (Insurance Information Institute, weighted 2018 to 2022)
A100: Cause | B100: Average claim ($) | C100: Basis
A101: Fire and lightning | B101: 83991 | C101: Sourced: Insurance Information Institute
A102: Bodily injury or property damage liability | B102: 31690 | C102: Sourced: Insurance Information Institute
A103: Water damage and freezing | B103: 13954 | C103: Sourced: Insurance Information Institute
A104: Wind and hail | B104: 13511 | C104: Sourced: Insurance Information Institute
A105: Theft | B105: 5024 | C105: Sourced: Insurance Information Institute
A107: Roof life and illustrative assumptions
A108: Item | B108: Value | C108: Basis
A109: Roof life: asphalt (years) | B109: 20 | C109: Assumed (asphalt shingles are reported at 15 to 30 years)
A110: Roof life: tile (years) | B110: 35 | C110: Assumed (asphalt shingles are reported at 15 to 30 years)
A111: Roof life: metal (years) | B111: 45 | C111: Assumed (asphalt shingles are reported at 15 to 30 years)
A112: Roof life: other (years) | B112: 25 | C112: Assumed (asphalt shingles are reported at 15 to 30 years)
A113: Code-upgrade cost as a share of rebuild | B113: 0.1 | C113: Assumed
A114: Extended replacement cost as a share of the house limit | B114: 0.25 | C114: Assumed
A115: Ordinance-or-law cover as a share of the house limit | B115: 0.1 | C115: Assumed
A116: Illustrative hurricane loss ($) | B116: 40000 | C116: Assumed
A117: Illustrative sewer-backup loss ($) | B117: 10000 | C117: Assumed
A118: Illustrative large lawsuit ($) | B118: 500000 | C118: Assumed
A119: Assumed umbrella limit ($) | B119: 1000000 | C119: Assumed
A120: Illustrative flood loss ($) | B120: 50000 | C120: Assumed
... A122: Maximum roof depreciation | B122: 0.85 | C122: Assumed

Sheet OK_Official_Data
A1: Oklahoma Insurance Department official insurer samples
A2: Real premiums from about 20 insurers for identical sample customers. Auto: six-month premium, 2018 Chevrolet Malibu, 25/50/25 liability, $500 collision and comprehensive, clean record (updated September 2026). Home: HO-3 at replacement cost, 1% deductible, $100,000 liability (updated August 2026).
A3: Line | B3: City | C3: Insurer | D3: Scenario | E3: Gender | F3: Construction | G3: Six-month premium ($) | H3: Annual premium ($) | I3: Group key | J3: Group median ($) | K3: Price / group median
A4: auto | B4: Oklahoma City | C4: ALLSTATE FIRE & CASUALTY INS. CO. | D4: scenario A (age 16) | E4: male | G4: 6845 | H4: =G4*2 -> 13690 | I4: =A4&"|"&B4&"|"&D4&"|"&E4&F4 -> auto|Oklahoma City|scenario A (age 16)|male | J4: {=MEDIAN(IF($I$4:$I$1803=I4,$H$4:$H$1803))} -> 8358 | K4: =H4/J4 -> 1.6379517
A5: auto | B5: Oklahoma City | C5: ALLSTATE FIRE & CASUALTY INS. CO. | D5: scenario A (age 16) | E5: female | G5: 6287 | H5: =G5*2 -> 12574 | I5: =A5&"|"&B5&"|"&D5&"|"&E5&F5 -> auto|Oklahoma City|scenario A (age 16)|female | J5: {=MEDIAN(IF($I$4:$I$1803=I5,$H$4:$H$1803))} -> 6710 | K5: =H5/J5 -> 1.8739195
A6: auto | B6: Oklahoma City | C6: ALLSTATE FIRE & CASUALTY INS. CO. | D6: scenario B (age 21) | E6: male | G6: 2067 | H6: =G6*2 -> 4134 | I6: =A6&"|"&B6&"|"&D6&"|"&E6&F6 -> auto|Oklahoma City|scenario B (age 21)|male | J6: {=MEDIAN(IF($I$4:$I$1803=I6,$H$4:$H$1803))} -> 3517 | K6: =H6/J6 -> 1.1754336
A7: auto | B7: Oklahoma City | C7: ALLSTATE FIRE & CASUALTY INS. CO. | D7: scenario B (age 21) | E7: female | G7: 1683 | H7: =G7*2 -> 3366 | I7: =A7&"|"&B7&"|"&D7&"|"&E7&F7 -> auto|Oklahoma City|scenario B (age 21)|female | J7: {=MEDIAN(IF($I$4:$I$1803=I7,$H$4:$H$1803))} -> 3138 | K7: =H7/J7 -> 1.0726577
A8: auto | B8: Oklahoma City | C8: ALLSTATE FIRE & CASUALTY INS. CO. | D8: scenario C (age 36) | E8: male | G8: 1095 | H8: =G8*2 -> 2190 | I8: =A8&"|"&B8&"|"&D8&"|"&E8&F8 -> auto|Oklahoma City|scenario C (age 36)|male | J8: {=MEDIAN(IF($I$4:$I$1803=I8,$H$4:$H$1803))} -> 2128 | K8: =H8/J8 -> 1.0291353
A9: auto | B9: Oklahoma City | C9: ALLSTATE FIRE & CASUALTY INS. CO. | D9: scenario C (age 36) | E9: female | G9: 1095 | H9: =G9*2 -> 2190 | I9: =A9&"|"&B9&"|"&D9&"|"&E9&F9 -> auto|Oklahoma City|scenario C (age 36)|female | J9: {=MEDIAN(IF($I$4:$I$1803=I9,$H$4:$H$1803))} -> 2026 | K9: =H9/J9 -> 1.0809477
A10: auto | B10: Oklahoma City | C10: ALLSTATE FIRE & CASUALTY INS. CO. | D10: scenario D (age 55) | E10: male | G10: 1074 | H10: =G10*2 -> 2148 | I10: =A10&"|"&B10&"|"&D10&"|"&E10&F10 -> auto|Oklahoma City|scenario D (age 55)|male | J10: {=MEDIAN(IF($I$4:$I$1803=I10,$H$4:$H$1803))} -> 1762 | K10: =H10/J10 -> 1.2190692
A11: auto | B11: Oklahoma City | C11: ALLSTATE FIRE & CASUALTY INS. CO. | D11: scenario D (age 55) | E11: female | G11: 1016 | H11: =G11*2 -> 2032 | I11: =A11&"|"&B11&"|"&D11&"|"&E11&F11 -> auto|Oklahoma City|scenario D (age 55)|female | J11: {=MEDIAN(IF($I$4:$I$1803=I11,$H$4:$H$1803))} -> 1664 | K11: =H11/J11 -> 1.2211538
A12: auto | B12: Oklahoma City | C12: ALLSTATE FIRE & CASUALTY INS. CO. | D12: scenario E (age 70) | E12: male | G12: 1136 | H12: =G12*2 -> 2272 | I12: =A12&"|"&B12&"|"&D12&"|"&E12&F12 -> auto|Oklahoma City|scenario E (age 70)|male | J12: {=MEDIAN(IF($I$4:$I$1803=I12,$H$4:$H$1803))} -> 1649 | K12: =H12/J12 -> 1.3778047
A13: auto | B13: Oklahoma City | C13: ALLSTATE FIRE & CASUALTY INS. CO. | D13: scenario E (age 70) | E13: female | G13: 1074 | H13: =G13*2 -> 2148 | I13: =A13&"|"&B13&"|"&D13&"|"&E13&F13 -> auto|Oklahoma City|scenario E (age 70)|female | J13: {=MEDIAN(IF($I$4:$I$1803=I13,$H$4:$H$1803))} -> 1664 | K13: =H13/J13 -> 1.2908654
A14: auto | B14: Oklahoma City | C14: AMERICAN FARMERS & RANCHERS MUTUAL INS. CO. | D14: scenario A (age 16) | E14: male | G14: 3067 | H14: =G14*2 -> 6134 | I14: =A14&"|"&B14&"|"&D14&"|"&E14&F14 -> auto|Oklahoma City|scenario A (age 16)|male | J14: {=MEDIAN(IF($I$4:$I$1803=I14,$H$4:$H$1803))} -> 8358 | K14: =H14/J14 -> 0.73390763
A15: auto | B15: Oklahoma City | C15: AMERICAN FARMERS & RANCHERS MUTUAL INS. CO. | D15: scenario A (age 16) | E15: female | G15: 2940 | H15: =G15*2 -> 5880 | I15: =A15&"|"&B15&"|"&D15&"|"&E15&F15 -> auto|Oklahoma City|scenario A (age 16)|female | J15: {=MEDIAN(IF($I$4:$I$1803=I15,$H$4:$H$1803))} -> 6710 | K15: =H15/J15 -> 0.87630402
... A1003: auto | B1003: McAlester | C1003: USAA GENERAL INDEMNITY CO. | D1003: scenario E (age 70) | E1003: female | G1003: 812 | H1003: =G1003*2 -> 1624 | I1003: =A1003&"|"&B1003&"|"&D1003&"|"&E1003&F1003 -> auto|McAlester|scenario E (age 70)|female | J1003: {=MEDIAN(IF($I$4:$I$1803=I1003,$H$4:$H$1803))} -> 1353 | K1003: =H1003/J1003 -> 1.2002956
A1004: home | B1004: Oklahoma City | C1004: ALLSTATE INSURANCE CO. | D1004: scenario 1 (dwelling $100,000, deductible 1%) | F1004: frame | H1004: 2507 | I1004: =A1004&"|"&B1004&"|"&D1004&"|"&E1004&F1004 -> home|Oklahoma City|scenario 1 (dwelling $100,000, deductible 1%)|frame | J1004: {=MEDIAN(IF($I$4:$I$1803=I1004,$H$4:$H$1803))} -> 2742 | K1004: =H1004/J1004 -> 0.91429613
A1005: home | B1005: Oklahoma City | C1005: ALLSTATE INSURANCE CO. | D1005: scenario 1 (dwelling $100,000, deductible 1%) | F1005: masonry | H1005: 2342 | I1005: =A1005&"|"&B1005&"|"&D1005&"|"&E1005&F1005 -> home|Oklahoma City|scenario 1 (dwelling $100,000, deductible 1%)|masonry | J1005: {=MEDIAN(IF($I$4:$I$1803=I1005,$H$4:$H$1803))} -> 2754 | K1005: =H1005/J1005 -> 0.85039942
A1006: home | B1006: Oklahoma City | C1006: ALLSTATE INSURANCE CO. | D1006: scenario 2 (dwelling $200,000, deductible 1%) | F1006: frame | H1006: 5025 | I1006: =A1006&"|"&B1006&"|"&D1006&"|"&E1006&F1006 -> home|Oklahoma City|scenario 2 (dwelling $200,000, deductible 1%)|frame | J1006: {=MEDIAN(IF($I$4:$I$1803=I1006,$H$4:$H$1803))} -> 4325 | K1006: =H1006/J1006 -> 1.1618497
A1007: home | B1007: Oklahoma City | C1007: ALLSTATE INSURANCE CO. | D1007: scenario 2 (dwelling $200,000, deductible 1%) | F1007: masonry | H1007: 4660 | I1007: =A1007&"|"&B1007&"|"&D1007&"|"&E1007&F1007 -> home|Oklahoma City|scenario 2 (dwelling $200,000, deductible 1%)|masonry | J1007: {=MEDIAN(IF($I$4:$I$1803=I1007,$H$4:$H$1803))} -> 4381 | K1007: =H1007/J1007 -> 1.0636841
A1008: home | B1008: Oklahoma City | C1008: ALLSTATE INSURANCE CO. | D1008: scenario 3 (dwelling $300,000, deductible 1%) | F1008: frame | H1008: 7698 | I1008: =A1008&"|"&B1008&"|"&D1008&"|"&E1008&F1008 -> home|Oklahoma City|scenario 3 (dwelling $300,000, deductible 1%)|frame | J1008: {=MEDIAN(IF($I$4:$I$1803=I1008,$H$4:$H$1803))} -> 5727 | K1008: =H1008/J1008 -> 1.3441592
A1009: home | B1009: Oklahoma City | C1009: ALLSTATE INSURANCE CO. | D1009: scenario 3 (dwelling $300,000, deductible 1%) | F1009: masonry | H1009: 7144 | I1009: =A1009&"|"&B1009&"|"&D1009&"|"&E1009&F1009 -> home|Oklahoma City|scenario 3 (dwelling $300,000, deductible 1%)|masonry | J1009: {=MEDIAN(IF($I$4:$I$1803=I1009,$H$4:$H$1803))} -> 5959 | K1009: =H1009/J1009 -> 1.1988589
A1010: home | B1010: Oklahoma City | C1010: ALLSTATE INSURANCE CO. | D1010: scenario 4 (dwelling $400,000, deductible 1%) | F1010: frame | H1010: 10370 | I1010: =A1010&"|"&B1010&"|"&D1010&"|"&E1010&F1010 -> home|Oklahoma City|scenario 4 (dwelling $400,000, deductible 1%)|frame | J1010: {=MEDIAN(IF($I$4:$I$1803=I1010,$H$4:$H$1803))} -> 6965.5 | K1010: =H1010/J1010 -> 1.4887661
A1011: home | B1011: Oklahoma City | C1011: ALLSTATE INSURANCE CO. | D1011: scenario 4 (dwelling $400,000, deductible 1%) | F1011: masonry | H1011: 9627 | I1011: =A1011&"|"&B1011&"|"&D1011&"|"&E1011&F1011 -> home|Oklahoma City|scenario 4 (dwelling $400,000, deductible 1%)|masonry | J1011: {=MEDIAN(IF($I$4:$I$1803=I1011,$H$4:$H$1803))} -> 7153 | K1011: =H1011/J1011 -> 1.3458689
A1012: home | B1012: Oklahoma City | C1012: ALLSTATE INSURANCE CO. | D1012: scenario 5 (dwelling $500,000, deductible 1%) | F1012: frame | H1012: 13042 | I1012: =A1012&"|"&B1012&"|"&D1012&"|"&E1012&F1012 -> home|Oklahoma City|scenario 5 (dwelling $500,000, deductible 1%)|frame | J1012: {=MEDIAN(IF($I$4:$I$1803=I1012,$H$4:$H$1803))} -> 8254.5 | K1012: =H1012/J1012 -> 1.5799867
A1013: home | B1013: Oklahoma City | C1013: ALLSTATE INSURANCE CO. | D1013: scenario 5 (dwelling $500,000, deductible 1%) | F1013: masonry | H1013: 12112 | I1013: =A1013&"|"&B1013&"|"&D1013&"|"&E1013&F1013 -> home|Oklahoma City|scenario 5 (dwelling $500,000, deductible 1%)|masonry | J1013: {=MEDIAN(IF($I$4:$I$1803=I1013,$H$4:$H$1803))} -> 8121 | K1013: =H1013/J1013 -> 1.4914419
A1014: home | B1014: Oklahoma City | C1014: ALLSTATE VEHICLE & PROPERTY INSURANCE CO. | D1014: scenario 1 (dwelling $100,000, deductible 1%) | F1014: frame | H1014: 1280 | I1014: =A1014&"|"&B1014&"|"&D1014&"|"&E1014&F1014 -> home|Oklahoma City|scenario 1 (dwelling $100,000, deductible 1%)|frame | J1014: {=MEDIAN(IF($I$4:$I$1803=I1014,$H$4:$H$1803))} -> 2742 | K1014: =H1014/J1014 -> 0.46681255
A1015: home | B1015: Oklahoma City | C1015: ALLSTATE VEHICLE & PROPERTY INSURANCE CO. | D1015: scenario 1 (dwelling $100,000, deductible 1%) | F1015: masonry | H1015: 1269 | I1015: =A1015&"|"&B1015&"|"&D1015&"|"&E1015&F1015 -> home|Oklahoma City|scenario 1 (dwelling $100,000, deductible 1%)|masonry | J1015: {=MEDIAN(IF($I$4:$I$1803=I1015,$H$4:$H$1803))} -> 2754 | K1015: =H1015/J1015 -> 0.46078431
... A1803: home | B1803: McAlester | C1803: USAA GENERAL INDEMNITY CO. | D1803: scenario 5 (dwelling $500,000, deductible 1%) | F1803: masonry | H1803: 8776 | I1803: =A1803&"|"&B1803&"|"&D1803&"|"&E1803&F1803 -> home|McAlester|scenario 5 (dwelling $500,000, deductible 1%)|masonry | J1803: {=MEDIAN(IF($I$4:$I$1803=I1803,$H$4:$H$1803))} -> 6962.5 | K1803: =H1803/J1803 -> 1.2604668

Sheet Fairness_Screen
A1: Fairness screen: adverse impact ratios
A2: Enter each group's count and favorable count. Blue rows below are EXAMPLE values only: replace them with your data. A flag is a prompt to investigate, not a finding of discrimination.
A4: Group | B4: Rows (n) | C4: Favorable outcomes | D4: Favorable rate | E4: Adverse impact ratio (vs. highest) | F4: p-value vs. highest group | G4: Result | I4: Reference group (highest rate)
A5: Example group A | B5: 300 | C5: 186 | D5: =IF(AND(ISNUMBER(B5),B5>0),C5/B5,"") -> 0.62 | E5: =IF(D5="","",D5/MAX($D$5:$D$12)) -> 1 | F5: =IF(OR(D5="",D5=$J$5),"",2*(1-NORMSDIST(ABS(D5-$J$5)/SQRT(((C5+$J$7)/(B5+$J$6))*(1-(C5+$J$7)/(B5+$J$6))*(1/B5+1/$J$6))))) | G5: =IF(D5="","",IF(D5=MAX($D$5:$D$12),"Highest rate",IF(B5<30,"Too few rows",IF(E5<0.8,IF(AND(F5<>"",F5<0.05),"Review (statistically clear)","Review (may be noise)"),"Within 0.80")))) -> Highest rate | I5: Rate | J5: =MAX($D$5:$D$12) -> 0.62
A6: Example group B | B6: 300 | C6: 150 | D6: =IF(AND(ISNUMBER(B6),B6>0),C6/B6,"") -> 0.5 | E6: =IF(D6="","",D6/MAX($D$5:$D$12)) -> 0.80645161 | F6: =IF(OR(D6="",D6=$J$5),"",2*(1-NORMSDIST(ABS(D6-$J$5)/SQRT(((C6+$J$7)/(B6+$J$6))*(1-(C6+$J$7)/(B6+$J$6))*(1/B6+1/$J$6))))) -> 0.0030685843 | G6: =IF(D6="","",IF(D6=MAX($D$5:$D$12),"Highest rate",IF(B6<30,"Too few rows",IF(E6<0.8,IF(AND(F6<>"",F6<0.05),"Review (statistically clear)","Review (may be noise)"),"Within 0.80")))) -> Within 0.80 | I6: Rows | J6: =INDEX($B$5:$B$12,MATCH($J$5,$D$5:$D$12,0)) -> 300
A7: Example group C | B7: 300 | C7: 108 | D7: =IF(AND(ISNUMBER(B7),B7>0),C7/B7,"") -> 0.36 | E7: =IF(D7="","",D7/MAX($D$5:$D$12)) -> 0.58064516 | F7: =IF(OR(D7="",D7=$J$5),"",2*(1-NORMSDIST(ABS(D7-$J$5)/SQRT(((C7+$J$7)/(B7+$J$6))*(1-(C7+$J$7)/(B7+$J$6))*(1/B7+1/$J$6))))) -> 1.8909296e-10 | G7: =IF(D7="","",IF(D7=MAX($D$5:$D$12),"Highest rate",IF(B7<30,"Too few rows",IF(E7<0.8,IF(AND(F7<>"",F7<0.05),"Review (statistically clear)","Review (may be noise)"),"Within 0.80")))) -> Review (statistically clear) | I7: Favorable outcomes | J7: =INDEX($C$5:$C$12,MATCH($J$5,$D$5:$D$12,0)) -> 186
D8: =IF(AND(ISNUMBER(B8),B8>0),C8/B8,"") | E8: =IF(D8="","",D8/MAX($D$5:$D$12)) | F8: =IF(OR(D8="",D8=$J$5),"",2*(1-NORMSDIST(ABS(D8-$J$5)/SQRT(((C8+$J$7)/(B8+$J$6))*(1-(C8+$J$7)/(B8+$J$6))*(1/B8+1/$J$6))))) | G8: =IF(D8="","",IF(D8=MAX($D$5:$D$12),"Highest rate",IF(B8<30,"Too few rows",IF(E8<0.8,IF(AND(F8<>"",F8<0.05),"Review (statistically clear)","Review (may be noise)"),"Within 0.80"))))
D9: =IF(AND(ISNUMBER(B9),B9>0),C9/B9,"") | E9: =IF(D9="","",D9/MAX($D$5:$D$12)) | F9: =IF(OR(D9="",D9=$J$5),"",2*(1-NORMSDIST(ABS(D9-$J$5)/SQRT(((C9+$J$7)/(B9+$J$6))*(1-(C9+$J$7)/(B9+$J$6))*(1/B9+1/$J$6))))) | G9: =IF(D9="","",IF(D9=MAX($D$5:$D$12),"Highest rate",IF(B9<30,"Too few rows",IF(E9<0.8,IF(AND(F9<>"",F9<0.05),"Review (statistically clear)","Review (may be noise)"),"Within 0.80"))))
D10: =IF(AND(ISNUMBER(B10),B10>0),C10/B10,"") | E10: =IF(D10="","",D10/MAX($D$5:$D$12)) | F10: =IF(OR(D10="",D10=$J$5),"",2*(1-NORMSDIST(ABS(D10-$J$5)/SQRT(((C10+$J$7)/(B10+$J$6))*(1-(C10+$J$7)/(B10+$J$6))*(1/B10+1/$J$6))))) | G10: =IF(D10="","",IF(D10=MAX($D$5:$D$12),"Highest rate",IF(B10<30,"Too few rows",IF(E10<0.8,IF(AND(F10<>"",F10<0.05),"Review (statistically clear)","Review (may be noise)"),"Within 0.80"))))
D11: =IF(AND(ISNUMBER(B11),B11>0),C11/B11,"") | E11: =IF(D11="","",D11/MAX($D$5:$D$12)) | F11: =IF(OR(D11="",D11=$J$5),"",2*(1-NORMSDIST(ABS(D11-$J$5)/SQRT(((C11+$J$7)/(B11+$J$6))*(1-(C11+$J$7)/(B11+$J$6))*(1/B11+1/$J$6))))) | G11: =IF(D11="","",IF(D11=MAX($D$5:$D$12),"Highest rate",IF(B11<30,"Too few rows",IF(E11<0.8,IF(AND(F11<>"",F11<0.05),"Review (statistically clear)","Review (may be noise)"),"Within 0.80"))))
D12: =IF(AND(ISNUMBER(B12),B12>0),C12/B12,"") | E12: =IF(D12="","",D12/MAX($D$5:$D$12)) | F12: =IF(OR(D12="",D12=$J$5),"",2*(1-NORMSDIST(ABS(D12-$J$5)/SQRT(((C12+$J$7)/(B12+$J$6))*(1-(C12+$J$7)/(B12+$J$6))*(1/B12+1/$J$6))))) | G12: =IF(D12="","",IF(D12=MAX($D$5:$D$12),"Highest rate",IF(B12<30,"Too few rows",IF(E12<0.8,IF(AND(F12<>"",F12<0.05),"Review (statistically clear)","Review (may be noise)"),"Within 0.80"))))
A14: How to read this
A15: Adverse impact ratio below 0.80 (the "four-fifths" rule of thumb) is flagged. Differences can reflect real differences in risk, which regulators distinguish from unfair discrimination.
A16: Groups under 30 rows are unreliable. Group labels inferred from names or addresses have measurement error; prefer labels collected lawfully.
A17: Document what you tested, the result and what you did about it. The web tool's Trust and fairness tab also runs a proxy screen and cost-ratio tests.

Sheet Monitoring
A1: Monitoring over time
A2: Each month, enter the results from the Quote_Test sheet (or your own quote test). Blue rows are EXAMPLE values: replace them. Alerts follow the thresholds in the model card.
A4: Month | B4: Quotes | C4: Inside range | D4: Median error | E4: Average bias | F4: Alert
A5: 2026-06 | B5: 42 | C5: 0.86 | D5: 0.11 | E5: 0.02 | F5: =IF(A5="","",IF(B5<10,"Too few quotes to judge",IF(OR(ABS(E5)>0.1,C5<0.8),"ACT: bias above 10% or coverage below 80%",IF(D5>0.15,"WATCH: median error above 15%","OK")))) -> OK
A6: 2026-07 | B6: 40 | C6: 0.84 | D6: 0.12 | E6: 0.05 | F6: =IF(A6="","",IF(B6<10,"Too few quotes to judge",IF(OR(ABS(E6)>0.1,C6<0.8),"ACT: bias above 10% or coverage below 80%",IF(D6>0.15,"WATCH: median error above 15%","OK")))) -> OK
A7: 2026-08 | B7: 38 | C7: 0.71 | D7: 0.19 | E7: 0.14 | F7: =IF(A7="","",IF(B7<10,"Too few quotes to judge",IF(OR(ABS(E7)>0.1,C7<0.8),"ACT: bias above 10% or coverage below 80%",IF(D7>0.15,"WATCH: median error above 15%","OK")))) -> ACT: bias above 10% or coverage below 80%
A8: 2026-09 | B8: 44 | C8: 0.66 | D8: 0.22 | E8: 0.18 | F8: =IF(A8="","",IF(B8<10,"Too few quotes to judge",IF(OR(ABS(E8)>0.1,C8<0.8),"ACT: bias above 10% or coverage below 80%",IF(D8>0.15,"WATCH: median error above 15%","OK")))) -> ACT: bias above 10% or coverage below 80%
F9: =IF(A9="","",IF(B9<10,"Too few quotes to judge",IF(OR(ABS(E9)>0.1,C9<0.8),"ACT: bias above 10% or coverage below 80%",IF(D9>0.15,"WATCH: median error above 15%","OK"))))
F10: =IF(A10="","",IF(B10<10,"Too few quotes to judge",IF(OR(ABS(E10)>0.1,C10<0.8),"ACT: bias above 10% or coverage below 80%",IF(D10>0.15,"WATCH: median error above 15%","OK"))))
F11: =IF(A11="","",IF(B11<10,"Too few quotes to judge",IF(OR(ABS(E11)>0.1,C11<0.8),"ACT: bias above 10% or coverage below 80%",IF(D11>0.15,"WATCH: median error above 15%","OK"))))
F12: =IF(A12="","",IF(B12<10,"Too few quotes to judge",IF(OR(ABS(E12)>0.1,C12<0.8),"ACT: bias above 10% or coverage below 80%",IF(D12>0.15,"WATCH: median error above 15%","OK"))))
F13: =IF(A13="","",IF(B13<10,"Too few quotes to judge",IF(OR(ABS(E13)>0.1,C13<0.8),"ACT: bias above 10% or coverage below 80%",IF(D13>0.15,"WATCH: median error above 15%","OK"))))
F14: =IF(A14="","",IF(B14<10,"Too few quotes to judge",IF(OR(ABS(E14)>0.1,C14<0.8),"ACT: bias above 10% or coverage below 80%",IF(D14>0.15,"WATCH: median error above 15%","OK"))))
F15: =IF(A15="","",IF(B15<10,"Too few quotes to judge",IF(OR(ABS(E15)>0.1,C15<0.8),"ACT: bias above 10% or coverage below 80%",IF(D15>0.15,"WATCH: median error above 15%","OK"))))
F16: =IF(A16="","",IF(B16<10,"Too few quotes to judge",IF(OR(ABS(E16)>0.1,C16<0.8),"ACT: bias above 10% or coverage below 80%",IF(D16>0.15,"WATCH: median error above 15%","OK"))))
A19: Thresholds: bias above 10%, inside-range below 80%, median error above 15%. Also compare the mix of inputs each month (state, house size, roof age); a shift in the mix is a reason to re-check the model. Common rule of thumb for the population stability index: below 0.10 stable, 0.10 to 0.25 moderate, above 0.25 large.

Sheet Fairness_Rules_Audit
A1: What changes the price, and how much
A2: Each row changes one input from a baseline and shows the multiple of the baseline estimate (computed by the web tool). Basis says whether the multiple is published or assumed.
A4: Line | B4: Input change | C4: Effect on estimate | D4: Basis | E4: Fairness note
A5: Car | B5: Age 20 | C5: 2.04 | D5: Sourced (NerdWallet) | E5: Age is a permitted rating factor in most states, but rules vary
A6: Car | B6: Age 65 | C6: 0.822 | D6: Sourced (Insurify)
A7: Car | B7: One speeding ticket | C7: 1.29 | D7: Sourced (NerdWallet) | E7: Driving record is a conduct-based factor
A8: Car | B8: One at-fault crash | C8: 1.49 | D8: Sourced (NerdWallet) | E8: Driving record is a conduct-based factor
A9: Car | B9: DUI | C9: 1.89 | D9: Sourced (NerdWallet) | E9: Driving record is a conduct-based factor
A10: Car | B10: Poor credit | C10: 1.68 | D10: Sourced (NerdWallet) | E10: Credit is banned in CA, HI, MA and MI for car pricing; the tool ignores it there. Credit is often reviewed for correlation with protected classes
A11: Car | B11: Excellent credit | C11: 0.92 | D11: Assumed | E11: Same review point as above
A12: Car | B12: Over 15,000 miles a year | C12: 1.1 | D12: Assumed
A13: Car | B13: Delivery or rideshare use | C13: 1.35 | D13: Assumed
A14: Home | B14: One claim in five years | C14: 1.16 | D14: Sourced (MoneyGeek) | E14: Claims history is conduct- and loss-based
A15: Home | B15: Two claims | C15: 1.29 | D15: Sourced (MoneyGeek)
A16: Home | B16: Poor credit | C16: 2.11 | D16: Sourced (Bankrate) | E16: Credit is banned in CA, MD and MA for home pricing; the tool ignores it there. Studies disagree widely on the size
A17: Home | B17: Roof 20 years or older | C17: 1.3 | D17: Assumed | E17: Property condition factor
A18: Home | B18: Rental instead of owner-occupied | C18: 1.2 | D18: Assumed
A19: Home | B19: Hurricane area | C19: 1.15 | D19: Assumed | E19: Area hazard ratings can correlate with neighborhood demographics; used as planning information only
A20: Car | B20: State (lowest to highest published median) | C20: 3.7421603 | D20: Sourced (NerdWallet) | E20: Location is a standard factor; state-level only, the tool does not use ZIP code or address for price
A21: Home | B21: State (lowest to highest published average) | C21: 11.47832 | D21: Sourced (Insurance.com) | E21: Same as above
A23: Inputs used: state, age, driving record, claims, credit (where allowed), property facts. Not used: ZIP code, gender, marital status, occupation, income, education, race, religion, national origin.

Sheet Controls_Register
A1: Governance controls register
A2: Control names follow the list PwC gives for AI in property and casualty insurance. Status is honest: two controls are not built.
A4: Control | B4: How it is met | C4: Status
A5: Model inventory | B5: This tool contains four models: car price, home price, coverage-gap scores, and the insurer-price percentile. Listed in the model card. | C5: Built
A6: Approved-use register | B6: Educational comparison and coverage checking only. Not for underwriting, pricing filed rates, claims decisions, or binding coverage. | C6: Built (stated in the model card)
A7: Data lineage | B7: Every published figure has a named source and date in the decision receipt and the model card. Assumptions are labelled. | C7: Built
A8: Validation standards | B8: Range coverage of at least 80% of real quotes and median error of 15% or less, per state. Tested on Oklahoma's official samples; not yet on real quotes elsewhere. | C8: Partial
A9: Monitoring | B9: The Monitoring tool reports error and drift by month from a file of quotes. | C9: Built (needs data)
A10: Bias and adverse-impact testing | B10: The Fairness screen computes adverse impact ratios and proxy checks on user data. | C10: Built (needs data)
A11: Change control | B11: Version number and change log below. No formal approval process. | C11: Partial
A12: Incident management | B12: No process is defined. The owner should decide how errors are reported, triaged and corrected. | C12: Not built
A13: Audit trail | B13: The decision receipt and the copied summary record what produced each result. Nothing is stored between sessions. | C13: Partial
A14: Third-party oversight | B14: Public data sources are listed. There is no contract or review of them beyond reading their documentation. | C14: Partial
A15: Human oversight and accountable owner | B15: Results tell users to confirm with a licensed agent and their state insurance department. No named owner exists. | C15: Not built
A16: Consumer notice | B16: Every result states that it is a learning model, not a quote. | C16: Built
A18: Owner: not assigned. Incident process: not defined. Decide both before wider use.

Sheet Min_Liability
A1: Legal minimum car liability by state
A2: Numbers read: bodily injury per person / per accident / property damage, in thousands of dollars. "Official" means read on a state agency page or document.
A4: State | B4: Minimum | C4: Status | D4: Source
A5: Texas | B5: 30/60/25 | C5: Official | D5: https://www.tdi.texas.gov/bulletins/2010/cc46.html
A6: Florida | B6: No bodily-injury minimum. $10,000 personal injury protection and $10,000 property damage. After certain at-fault crashes, 10/20/10 with an SR-22 for three years may be required | C6: Official | D6: https://flhsmv.gov/insurance/
A7: New York | B7: 25/50/10 (injury 25/50; death 50/100), plus 25/50 uninsured-motorist cover and $50,000 personal injury protection | C7: Official | D7: https://dmv.ny.gov/insurance/new-york-state-insurance-requirements
A8: Michigan | B8: Bodily injury 50/100 (default 250/500), $1 million property protection, and a choice of personal injury protection levels (unlimited by default) | C8: Official | D8: https://michigan.gov/-/media/Project/Websites/autoinsurance/PDFs/FIS-PUB_5100a.pdf
A9: Pennsylvania | B9: 15/30/5, plus $5,000 first-party medical benefits | C9: Official | D9: https://www.pa.gov/agencies/insurance/consumer-help-center/learn-about-insurance/auto-insurance
A10: Washington | B10: 25/50/10 | C10: Official | D10: https://dol.wa.gov/node/192
A11: Massachusetts | B11: 25/50/30, plus $8,000 personal injury protection and 25/50 uninsured-motorist cover (policies written or renewed on or after July 1, 2025) | C11: Official | D11: https://www.mass.gov/doc/2025-a-new-motor-vehicle-mandatory-coverage-limits/download
A12: Hawaii | B12: 40/80/20, plus $10,000 personal injury protection (from January 1, 2026) | C12: Official | D12: https://cca.hawaii.gov/ins/files/2023/05/Auto-Minimum-Limits-FAQs.pdf
A13: Ohio | B13: 25/50/25 | C13: Official | D13: https://dam.assets.ohio.gov/image/upload/publicsafety.ohio.gov/bmv3101.pdf
A14: North Carolina | B14: 30/60/25, plus uninsured and underinsured motorist cover. Some websites claim a 2025 increase that we could not confirm | C14: Official | D14: https://ncdoi.gov/media/5/open
A15: California | B15: 30/60/15 since January 1, 2025 (SB 1107) | C15: Statute identified | D15: https://www.fmglaw.com/?p=35636
A16: Illinois | B16: 25/50/20, plus uninsured-motorist cover. The Secretary of State's brochure confirms uninsured-motorist cover is automatic | C16: Partly checked | D16: Illinois Secretary of State brochure (confirms automatic uninsured-motorist cover)
A18: All other states: see the Car_Data sheet (column J and K). Utah, New Jersey, Hawaii and Massachusetts changed recently; confirm any figure with your state insurance department. Georgia, Oklahoma, Louisiana and Colorado are from consumer guides only.

Sheet Home_Reference
A1: Home insurance reference notes
A2: Plain-language facts used by the home calculator. Sources named in each row.
A4: Topic | B4: What to know | C4: Source
A5: Policy form | B5: HO-3 covers the house on an all-causes basis except exclusions; contents are usually named perils. Some forms apply a coinsurance penalty if the house is insured for less than 80% of replacement cost. | C5: Florida Citizens HO-3 coverage comparison worksheets
A6: Typical structure | B6: Other structures about 2% to 10% of the house limit; contents about 25% to 50%; loss of use about 10% to 20%; liability options $100,000 to $500,000; medical payments $2,000 to $5,000. | C6: Florida Citizens worksheets
A7: Special limits | B7: Theft of jewelry often capped at about $1,000 to $1,500; firearms about $1,000 to $2,500; silverware about $2,500; money $200. | C7: Florida Citizens worksheets
A8: Ordinance or law | B8: Pays extra to rebuild to current codes; a common example is 10% of the house limit. | C8: Sure (endorsement examples)
A9: Extended replacement cost | B9: Adds roughly 10% to 50% of the house limit if rebuilding costs more. | C9: NerdWallet
A10: Water backup | B10: Sewer and drain backup is usually excluded from a standard policy; an example endorsement limit is $10,000. | C10: Sure; general policy knowledge
A11: Storm deductibles | B11: Hurricane and wind or hail deductibles are usually a percentage (1% to 5%, up to 10%) of the house limit. About 19 states and D.C. use some form. Florida requires insurers to offer $500, 2%, 5% and 10% options, applied once per hurricane season and triggered only by a National Weather Service hurricane. | C11: Progressive; Policygenius; NC Dept. of Insurance; Florida sources
A12: Roof age | B12: Around 15 years insurers begin to ask for inspections, switch the roof to actual cash value, add surcharges or decline; by 20 years many restrict cover. Most sources are roofing contractors, so treat percentages as marketing-grade. | C12: Cedur; RoofVista; Winik; roofing-it.com
A13: Flood | B13: Standard homeowners policies exclude flood. NFIP offers up to $250,000 for a home and $100,000 for contents (contents must be requested), with a 30-day wait. Lenders must require flood cover for federally backed mortgages in a Special Flood Hazard Area. | C13: Municipal NFIP pages (Davie FL, Lafayette LA, Somers WI); FEMA
A14: Earthquake | B14: Excluded from standard policies; sold as an add-on with a large deductible. | C14: General policy knowledge
A15: Insurer of last resort | B15: Florida: Citizens Property Insurance. California: the FAIR Plan (about 668,000 policies and about $724 billion of exposure at a January 2026 hearing; named perils only per a broker summary). North Carolina coastal homes can have a separate wind policy. | C15: Insurance Business; Falcon West (broker); NC Dept. of Insurance
... A17: Market conditions | B17: All-peril claim severity in 2025 was up 25.9% from 2024 and 93.2% above 2019; fire and lightning severity up 67.3%. | C17: LexisNexis 2026 Home Trends Report

Sheet Consultancy_Benchmark
A1: What the consultancies point to, and what was built
A2: Ten firms with prominent US insurance practices (my selection; no authoritative ranking found). PwC, Milliman and Deloitte were read at excerpt level this round; the others from earlier excerpts. All sell to insurers; this tool serves consumers.
A4: Firm | B4: What its material emphasizes | C4: What the toolkit does about it | D4: Not done
A5: PwC | B5: Govern decisions, not just models; controls: model inventory, approved-use register, data lineage, validation standards, monitoring, change control, incident management, audit trails, third-party oversight; auditable rationales; bias and adverse-impact monitoring | C5: 12-item controls register; decision receipt; monitoring template; fairness screen | D5: Incident process; accountable owner
A6: Milliman | B6: Disparate-impact analysis and model review; rate-filing and validation support | C6: Adverse impact ratio and significance test; validation against official rates | D6: Independent third-party review
A7: Deloitte | B7: Trust, transparency and human oversight; a Swiss survey of 1,291 policyholders found 51% fear AI may make unfair decisions (not US data) | C7: Plain-language reasons; model card; "confirm with an agent" throughout | D7: US survey evidence
A8: McKinsey | B8: Coverage gaps and limits of AI (earlier excerpt) | C8: Protection-gap scores; cost-saving options that avoid new gaps | D8: McKinsey pages not read this round
A9: Oliver Wyman | B9: Ratemaking, predictive models and validation (earlier excerpt) | C9: Validation against official data; spread-based ranges | D9: Full GLM ratemaking pipeline
A10: KPMG | B10: Transparent actuarial models; climate and cost pressure (earlier excerpt) | C10: Sourced-versus-assumed tables; market-access notes
A11: EY | B11: AI roadmap gated by governance and data readiness (earlier excerpt) | C11: Phase gates; controls register
A12: BCG | B12: Personalization and benchmarks (earlier excerpt) | C12: Percentile and published-group comparison | D12: True peer benchmark needs a quote database
A13: Accenture | B13: Claims and customer experience (earlier excerpt) | C13: Guided flow; claim-readiness checklist | D13: Claims automation (out of scope)
A14: Cognizant | B14: Flood maps and GIS with claims history (earlier excerpt) | C14: FEMA flood and hazard lookup helper (in the web tool) | D14: Live test of the helper

Sheet Checklists
A1: Checklists
A2: Tick the "Done?" cells (type x or a date).
A4: Step | B4: What to do | C4: Done?
A5: A. Try the web tool in a real browser
A6: 1 | B6: Double-click insurance-price-check.html; it opens in Chrome, Edge or Safari.
A7: 2 | B7: Click through the car steps and press "Check my price". Nothing overlaps or is cut off; the bar and numbers are readable.
A8: 3 | B8: Repeat for Home insurance.
A9: 4 | B9: Make the window narrow, like a phone. It still reads properly.
A10: 5 | B10: Press Ctrl+P (Cmd+P on Mac). The preview shows results without menus and forms.
A11: 6 | B11: Press "Copy summary" and paste into Notes. The text appears.
A12: 7 | B12: Press Tab repeatedly. You can see where you are and press buttons with Enter.
A13: 8 | B13: Optional: turn on VoiceOver (Cmd+F5) or Narrator (Ctrl+Windows+Enter) and listen to the first screen.
A14: B. Test the address lookup
A15: 1 | B15: Check Python is 3.8 or higher: python --version (Mac: python3 --version).
A16: 2 | B16: In the folder with the files, run once: python insurance_risk_service.py --live-check. Good = a block of results with a flood zone. Not good = FAILED; send me the text.
A17: 3 | B17: Start the helper: python insurance_risk_service.py (leave the window open).
A18: 4 | B18: In the tool choose Home insurance, go to the Risks step, open "Optional: look up my address", enter a full address, press Look up.
A19: 5 | B19: Try one address you know is in a flood zone and one that is not; compare with msc.fema.gov.
A20: 6 | B20: Press Ctrl+C in the helper window to stop it.
A21: C. Collect real quotes
A22: 1 | B22: Get an independent agent to price the profiles on the Quote_Requests sheet with 3 to 5 insurers on the same day for the standard coverage.
A23: 2 | B23: Copy each row once per insurer; enter insurer, date and annual price in the yellow cells.
A24: 3 | B24: Read the Quote_Test sheet. Keep about a third of the profiles back for the final test.
A25: 4 | B25: If a state's median price / model is outside 0.90 to 1.10, adjust that state's price level and re-test.

Sheet Quote_Kit
A1: Quote collection protocol
A2: How to collect real home quotes for identical coverage. Not legal advice.
A4: Topic | B4: Guidance
A5: Who collects | B5: An independent agent or agency is best: it can rate the same home with several insurers in one sitting. Volunteers pricing their own homes also work. Do not scrape insurer websites, submit false details to consumer forms, or use addresses you have no permission to use. Ask counsel if unsure.
A6: How many | B6: 60 profiles per state (this workbook), 3 to 5 insurers each = 180 to 300 quotes per state. Hold back about one third of profiles for the final test.
A7: Standard coverage | B7: HO-3, owner-occupied; house cover at the profile limit at replacement cost (record the insurer's own figure if it differs); other structures 10%, contents 50%, loss of use 20%; the profile liability and deductible; no optional endorsements; no elective discounts. Record hurricane or wind deductible percentages and roof payment basis that applied.
A8: Real property vs. profile | B8: Insurers' systems often fill in year built, size or roof from public data. If the real property differs from the profile, overwrite the profile columns with the true values so the model is tested on what the insurer used.
A9: Same day | B9: Price all insurers within a few days; rates change.
A10: Declines | B10: Leave the price blank and note it. The share of declines is itself useful, especially in Florida and California.
A11: Decisions | B11: Meets both targets on the held-back third: describe that state's estimates as validated against N quotes from a named date. Misses: adjust the state price level, re-test, and keep the "rough guide" label if it still fails.
A12: Where more official data exists | B12: Oklahoma's samples are in the OK_Official_Data sheet. Texas publishes similar sample rates on HelpInsure.com (interactive); Delaware requires insurers to submit sample homeowners rates. Copy tables into the OK_Official_Data layout to extend the benchmark.

Sheet Limits_Next_Steps
A1: Limits and next steps
A2: Plain-language summary of what is and is not done.
A4: # | B4: Limit | C4: What would fix it
A5: 1 | B5: No real-quote validation in Texas, Florida or California. Oklahoma's official samples are the only real per-insurer data tested, and some fixes used the same data (partly in-sample). | C5: Fill the Quote_Requests sheet and read Quote_Test
A6: 2 | B6: Home prices are one source's view. Another published source is 25% to 60% lower in the states compared. | C6: Choose or license a home-price dataset
A7: 3 | B7: State-level only. City moved the same profile's price by up to about 16% (car) and 22% (home) within Oklahoma. | C7: Address-level data (the web tool's helper adds hazard boxes only)
A8: 4 | B8: The percentile borrows Oklahoma's insurer spread for every state. | C8: More states' official samples (Texas HelpInsure)
A9: 5 | B9: Address helper passed offline tests only. Tested in Chromium (desktop and phone sizes) only; Safari, Firefox, real phones and screen-reader use not tested. | C9: Checklists A and B
A10: 6 | B10: No accountable owner, no incident process, no legal review. | C10: You, with counsel

Sheet Sources
A1: Sources
A2: From search results reviewed on September 29, 2026. Where full pages were not opened, figures are approximate. Commercial sites are flagged.
A4: Topic | B4: Source | C4: Link
A5: Official data | B5: Oklahoma Insurance Department auto rate comparison (Sept 2026) | C5: https://www.oid.ok.gov/consumers/insurance-basics/auto-insurance-rate-comparison/
A6: Official data | B6: Oklahoma Insurance Department home rate comparison (Aug 2026) | C6: https://www.oid.ok.gov/consumers/insurance-basics/home-insurance-rate-comparison/
A7: Official data | B7: Texas HelpInsure data call | C7: https://tdi.texas.gov/company/data-collection/dchlpins.html
A8: Car prices | B8: NerdWallet state medians and driver-profile relativities (Sept 2026) | C8: https://www.nerdwallet.com/insurance/auto/car-insurance-calculator
A9: Car prices | B9: NerdWallet full-coverage analysis | C9: https://www.nerdwallet.com/insurance/auto/cheap-full-coverage-insurance
A10: Car prices | B10: Insurify rates by age | C10: https://insurify.com/car-insurance/cheap-car-insurance/age/
A11: Car prices | B11: NerdWallet deductible savings | C11: https://www.nerdwallet.com/insurance/auto/news/insurance-deductible-savings
A12: Home prices | B12: Insurance.com average rates by state (Sept 15, 2026) | C12: https://www.insurance.com/home-and-renters-insurance/home-insurance-basics/average-homeowners-insurance-rates-by-state
A13: Home prices | B13: InsuranceQuotes | C13: https://www.insurancequotes.com/home/rates-by-state
A14: Home prices | B14: Compare.com | C14: https://www.compare.com/homeowners-insurance/average-cost-home-insurance
A15: Claims and credit | B15: MoneyGeek: costs after a claim | C15: https://www.moneygeek.com/insurance/homeowners/home-insurance-costs-after-a-claim/
... A30: Consultancies | B30: Deloitte 2026 global insurance outlook | C30: https://www.deloitte.com/content/dam/insights/articles/2025/us188426_cfs_insurance-outlook-2026/pdf/DI_2026-global-insurance-outlook.pdf
